Workbook
Name Áreadeimpresión: 'Planilla de control'!$A$1:$M$2

Sheet Referencias
A1: Referencias:
A2: A - La ubicación está vacía y en sistema figura ocupada
A3: B - La ubicación está ocupada y en sistema figura vacía
A4: C - El material que se encuentra en la ubicación no coincide con el material que aparece en sistema
A5: D - Error de cantidad

Sheet BORRADOR
A1: DATOS SAP
A2: Tipo almacén | B2: Ubicación | C2: Material | D2: Unidad almacén | E2: Bloqueo de entradas | F2: Stock disponible | G2: Stock a entrar | H2: Motivo bloqueo | I2: calle, modulo y nivel | J2: Nivel | K2: Calle | L2: Alveolo | M2: Deposito
A3: PC5 | B3: 21A1A | C3: 02A311351ASS00 | D3: 09001450548127 | F3: 960 | G3: 0 | I3: =IF(OR(LEN(B3)=9,LEN(B3)=5),MID(B3,1,4),MID(B3,1,5)) -> 21A1 | J3: =IF(MID(I3,5,1)<>"",MID(I3,4,2),MID(I3,4,1))*1 -> 1 | K3: =+MID(B3,1,2)*1 -> 21 | L3: =+MID(B3,3,1) -> A | M3: =+IF(A3="1FO","D3",IF(A3="1CT","D4",IF(OR(A3="PC2",A3="RAB"),"MQ200","MQ250"))) -> MQ250
A4: PC5 | B4: 21A1B | C4: 02A311291K0S02 | D4: 09001441718893 | F4: 600 | G4: 0 | I4: =IF(OR(LEN(B4)=9,LEN(B4)=5),MID(B4,1,4),MID(B4,1,5)) -> 21A1 | J4: =IF(MID(I4,5,1)<>"",MID(I4,4,2),MID(I4,4,1))*1 -> 1 | K4: =+MID(B4,1,2)*1 -> 21 | L4: =+MID(B4,3,1) -> A | M4: =+IF(A4="1FO","D3",IF(A4="1CT","D4",IF(OR(A4="PC2",A4="RAB"),"MQ200","MQ250"))) -> MQ250
A5: PC5 | B5: 21A1C | C5: << vacías >> | F5: 0 | G5: 0 | I5: =IF(OR(LEN(B5)=9,LEN(B5)=5),MID(B5,1,4),MID(B5,1,5)) -> 21A1 | J5: =IF(MID(I5,5,1)<>"",MID(I5,4,2),MID(I5,4,1))*1 -> 1 | K5: =+MID(B5,1,2)*1 -> 21 | L5: =+MID(B5,3,1) -> A | M5: =+IF(A5="1FO","D3",IF(A5="1CT","D4",IF(OR(A5="PC2",A5="RAB"),"MQ200","MQ250"))) -> MQ250
A6: PC5 | B6: 21A2A | C6: 02A311149B0S00 | D6: 09001442244588 | F6: 924 | G6: 0 | I6: =IF(OR(LEN(B6)=9,LEN(B6)=5),MID(B6,1,4),MID(B6,1,5)) -> 21A2 | J6: =IF(MID(I6,5,1)<>"",MID(I6,4,2),MID(I6,4,1))*1 -> 2 | K6: =+MID(B6,1,2)*1 -> 21 | L6: =+MID(B6,3,1) -> A | M6: =+IF(A6="1FO","D3",IF(A6="1CT","D4",IF(OR(A6="PC2",A6="RAB"),"MQ200","MQ250"))) -> MQ250
A7: PC5 | B7: 21A2B | C7: 02A311285BCS00 | D7: 09001450548206 | F7: 960 | G7: 0 | I7: =IF(OR(LEN(B7)=9,LEN(B7)=5),MID(B7,1,4),MID(B7,1,5)) -> 21A2 | J7: =IF(MID(I7,5,1)<>"",MID(I7,4,2),MID(I7,4,1))*1 -> 2 | K7: =+MID(B7,1,2)*1 -> 21 | L7: =+MID(B7,3,1) -> A | M7: =+IF(A7="1FO","D3",IF(A7="1CT","D4",IF(OR(A7="PC2",A7="RAB"),"MQ200","MQ250"))) -> MQ250
A8: PC5 | B8: 21A2C | C8: 02J31125500S07 | D8: 09001447654953 | F8: 378 | G8: 0 | I8: =IF(OR(LEN(B8)=9,LEN(B8)=5),MID(B8,1,4),MID(B8,1,5)) -> 21A2 | J8: =IF(MID(I8,5,1)<>"",MID(I8,4,2),MID(I8,4,1))*1 -> 2 | K8: =+MID(B8,1,2)*1 -> 21 | L8: =+MID(B8,3,1) -> A | M8: =+IF(A8="1FO","D3",IF(A8="1CT","D4",IF(OR(A8="PC2",A8="RAB"),"MQ200","MQ250"))) -> MQ250
A9: PC5 | B9: 21A3A | C9: 02J31125500S07 | D9: 09001450358496 | F9: 0 | G9: 378 | I9: =IF(OR(LEN(B9)=9,LEN(B9)=5),MID(B9,1,4),MID(B9,1,5)) -> 21A3 | J9: =IF(MID(I9,5,1)<>"",MID(I9,4,2),MID(I9,4,1))*1 -> 3 | K9: =+MID(B9,1,2)*1 -> 21 | L9: =+MID(B9,3,1) -> A | M9: =+IF(A9="1FO","D3",IF(A9="1CT","D4",IF(OR(A9="PC2",A9="RAB"),"MQ200","MQ250"))) -> MQ250
A10: PC5 | B10: 21A3B | C10: 02A31136500S04 | D10: 09001448137118 | F10: 636 | G10: 0 | I10: =IF(OR(LEN(B10)=9,LEN(B10)=5),MID(B10,1,4),MID(B10,1,5)) -> 21A3 | J10: =IF(MID(I10,5,1)<>"",MID(I10,4,2),MID(I10,4,1))*1 -> 3 | K10: =+MID(B10,1,2)*1 -> 21 | L10: =+MID(B10,3,1) -> A | M10: =+IF(A10="1FO","D3",IF(A10="1CT","D4",IF(OR(A10="PC2",A10="RAB"),"MQ200","MQ250"))) -> MQ250
A11: PC5 | B11: 21A3C | C11: 02J31125500S07 | D11: 09001447522585 | F11: 378 | G11: 0 | I11: =IF(OR(LEN(B11)=9,LEN(B11)=5),MID(B11,1,4),MID(B11,1,5)) -> 21A3 | J11: =IF(MID(I11,5,1)<>"",MID(I11,4,2),MID(I11,4,1))*1 -> 3 | K11: =+MID(B11,1,2)*1 -> 21 | L11: =+MID(B11,3,1) -> A | M11: =+IF(A11="1FO","D3",IF(A11="1CT","D4",IF(OR(A11="PC2",A11="RAB"),"MQ200","MQ250"))) -> MQ250
A12: PC5 | B12: 21A4A | C12: 02A311291J0S02 | D12: 09001450677586 | F12: 700 | G12: 0 | I12: =IF(OR(LEN(B12)=9,LEN(B12)=5),MID(B12,1,4),MID(B12,1,5)) -> 21A4 | J12: =IF(MID(I12,5,1)<>"",MID(I12,4,2),MID(I12,4,1))*1 -> 4 | K12: =+MID(B12,1,2)*1 -> 21 | L12: =+MID(B12,3,1) -> A | M12: =+IF(A12="1FO","D3",IF(A12="1CT","D4",IF(OR(A12="PC2",A12="RAB"),"MQ200","MQ250"))) -> MQ250
A13: PC5 | B13: 21A4B | C13: 02A31136500S04 | D13: 09001447654956 | F13: 288 | G13: 0 | I13: =IF(OR(LEN(B13)=9,LEN(B13)=5),MID(B13,1,4),MID(B13,1,5)) -> 21A4 | J13: =IF(MID(I13,5,1)<>"",MID(I13,4,2),MID(I13,4,1))*1 -> 4 | K13: =+MID(B13,1,2)*1 -> 21 | L13: =+MID(B13,3,1) -> A | M13: =+IF(A13="1FO","D3",IF(A13="1CT","D4",IF(OR(A13="PC2",A13="RAB"),"MQ200","MQ250"))) -> MQ250
A14: PC5 | B14: 21A4C | C14: 02A31136500S04 | D14: 09001448160442 | F14: 600 | G14: 0 | I14: =IF(OR(LEN(B14)=9,LEN(B14)=5),MID(B14,1,4),MID(B14,1,5)) -> 21A4 | J14: =IF(MID(I14,5,1)<>"",MID(I14,4,2),MID(I14,4,1))*1 -> 4 | K14: =+MID(B14,1,2)*1 -> 21 | L14: =+MID(B14,3,1) -> A | M14: =+IF(A14="1FO","D3",IF(A14="1CT","D4",IF(OR(A14="PC2",A14="RAB"),"MQ200","MQ250"))) -> MQ250
A15: PC5 | B15: 21A5A | C15: 02A31136500S04 | D15: 09001448160443 | F15: 600 | G15: 0 | I15: =IF(OR(LEN(B15)=9,LEN(B15)=5),MID(B15,1,4),MID(B15,1,5)) -> 21A5 | J15: =IF(MID(I15,5,1)<>"",MID(I15,4,2),MID(I15,4,1))*1 -> 5 | K15: =+MID(B15,1,2)*1 -> 21 | L15: =+MID(B15,3,1) -> A | M15: =+IF(A15="1FO","D3",IF(A15="1CT","D4",IF(OR(A15="PC2",A15="RAB"),"MQ200","MQ250"))) -> MQ250
A16: RPK | B16: 21A5A | C16: << vacías >> | E16: X | F16: 0 | G16: 0 | H16: G | I16: =IF(OR(LEN(B16)=9,LEN(B16)=5),MID(B16,1,4),MID(B16,1,5)) -> 21A5 | J16: =IF(MID(I16,5,1)<>"",MID(I16,4,2),MID(I16,4,1))*1 -> 5 | K16: =+MID(B16,1,2)*1 -> 21 | L16: =+MID(B16,3,1) -> A | M16: =+IF(A16="1FO","D3",IF(A16="1CT","D4",IF(OR(A16="PC2",A16="RAB"),"MQ200","MQ250"))) -> MQ250
A17: PC5 | B17: 21A5B | C17: 02A311149AMS00 | D17: 09001450125550 | F17: 832 | G17: 0 | I17: =IF(OR(LEN(B17)=9,LEN(B17)=5),MID(B17,1,4),MID(B17,1,5)) -> 21A5 | J17: =IF(MID(I17,5,1)<>"",MID(I17,4,2),MID(I17,4,1))*1 -> 5 | K17: =+MID(B17,1,2)*1 -> 21 | L17: =+MID(B17,3,1) -> A | M17: =+IF(A17="1FO","D3",IF(A17="1CT","D4",IF(OR(A17="PC2",A17="RAB"),"MQ200","MQ250"))) -> MQ250
A18: PC5 | B18: 21A5C | C18: 02A311291J0S02 | D18: 09001450677587 | F18: 700 | G18: 0 | I18: =IF(OR(LEN(B18)=9,LEN(B18)=5),MID(B18,1,4),MID(B18,1,5)) -> 21A5 | J18: =IF(MID(I18,5,1)<>"",MID(I18,4,2),MID(I18,4,1))*1 -> 5 | K18: =+MID(B18,1,2)*1 -> 21 | L18: =+MID(B18,3,1) -> A | M18: =+IF(A18="1FO","D3",IF(A18="1CT","D4",IF(OR(A18="PC2",A18="RAB"),"MQ200","MQ250"))) -> MQ250
A19: PC5 | B19: 21A6A | C19: 02J31125500S07 | D19: 09001450358497 | F19: 0 | G19: 378 | I19: =IF(OR(LEN(B19)=9,LEN(B19)=5),MID(B19,1,4),MID(B19,1,5)) -> 21A6 | J19: =IF(MID(I19,5,1)<>"",MID(I19,4,2),MID(I19,4,1))*1 -> 6 | K19: =+MID(B19,1,2)*1 -> 21 | L19: =+MID(B19,3,1) -> A | M19: =+IF(A19="1FO","D3",IF(A19="1CT","D4",IF(OR(A19="PC2",A19="RAB"),"MQ200","MQ250"))) -> MQ250
A20: RPK | B20: 21A6A | C20: << vacías >> | E20: X | F20: 0 | G20: 0 | H20: G | I20: =IF(OR(LEN(B20)=9,LEN(B20)=5),MID(B20,1,4),MID(B20,1,5)) -> 21A6 | J20: =IF(MID(I20,5,1)<>"",MID(I20,4,2),MID(I20,4,1))*1 -> 6 | K20: =+MID(B20,1,2)*1 -> 21 | L20: =+MID(B20,3,1) -> A | M20: =+IF(A20="1FO","D3",IF(A20="1CT","D4",IF(OR(A20="PC2",A20="RAB"),"MQ200","MQ250"))) -> MQ250
A21: PC5 | B21: 21A6B | C21: 02J31125500S07 | D21: 09001450358498 | F21: 0 | G21: 378 | I21: =IF(OR(LEN(B21)=9,LEN(B21)=5),MID(B21,1,4),MID(B21,1,5)) -> 21A6 | J21: =IF(MID(I21,5,1)<>"",MID(I21,4,2),MID(I21,4,1))*1 -> 6 | K21: =+MID(B21,1,2)*1 -> 21 | L21: =+MID(B21,3,1) -> A | M21: =+IF(A21="1FO","D3",IF(A21="1CT","D4",IF(OR(A21="PC2",A21="RAB"),"MQ200","MQ250"))) -> MQ250
A22: RPK | B22: 21A6B | C22: << vacías >> | E22: X | F22: 0 | G22: 0 | H22: G | I22: =IF(OR(LEN(B22)=9,LEN(B22)=5),MID(B22,1,4),MID(B22,1,5)) -> 21A6 | J22: =IF(MID(I22,5,1)<>"",MID(I22,4,2),MID(I22,4,1))*1 -> 6 | K22: =+MID(B22,1,2)*1 -> 21 | L22: =+MID(B22,3,1) -> A | M22: =+IF(A22="1FO","D3",IF(A22="1CT","D4",IF(OR(A22="PC2",A22="RAB"),"MQ200","MQ250"))) -> MQ250
A23: PC5 | B23: 21A6C | C23: 02J31125500S07 | D23: 09001450385048 | F23: 0 | G23: 378 | I23: =IF(OR(LEN(B23)=9,LEN(B23)=5),MID(B23,1,4),MID(B23,1,5)) -> 21A6 | J23: =IF(MID(I23,5,1)<>"",MID(I23,4,2),MID(I23,4,1))*1 -> 6 | K23: =+MID(B23,1,2)*1 -> 21 | L23: =+MID(B23,3,1) -> A | M23: =+IF(A23="1FO","D3",IF(A23="1CT","D4",IF(OR(A23="PC2",A23="RAB"),"MQ200","MQ250"))) -> MQ250
A24: RPK | B24: 21A6C | C24: << vacías >> | E24: X | F24: 0 | G24: 0 | H24: G | I24: =IF(OR(LEN(B24)=9,LEN(B24)=5),MID(B24,1,4),MID(B24,1,5)) -> 21A6 | J24: =IF(MID(I24,5,1)<>"",MID(I24,4,2),MID(I24,4,1))*1 -> 6 | K24: =+MID(B24,1,2)*1 -> 21 | L24: =+MID(B24,3,1) -> A | M24: =+IF(A24="1FO","D3",IF(A24="1CT","D4",IF(OR(A24="PC2",A24="RAB"),"MQ200","MQ250"))) -> MQ250
A25: PC5 | B25: 21A7A | C25: 02A311149AMS00 | D25: 09001449915810 | F25: 832 | G25: 0 | I25: =IF(OR(LEN(B25)=9,LEN(B25)=5),MID(B25,1,4),MID(B25,1,5)) -> 21A7 | J25: =IF(MID(I25,5,1)<>"",MID(I25,4,2),MID(I25,4,1))*1 -> 7 | K25: =+MID(B25,1,2)*1 -> 21 | L25: =+MID(B25,3,1) -> A | M25: =+IF(A25="1FO","D3",IF(A25="1CT","D4",IF(OR(A25="PC2",A25="RAB"),"MQ200","MQ250"))) -> MQ250
A26: RPK | B26: 21A7A | C26: << vacías >> | E26: X | F26: 0 | G26: 0 | H26: G | I26: =IF(OR(LEN(B26)=9,LEN(B26)=5),MID(B26,1,4),MID(B26,1,5)) -> 21A7 | J26: =IF(MID(I26,5,1)<>"",MID(I26,4,2),MID(I26,4,1))*1 -> 7 | K26: =+MID(B26,1,2)*1 -> 21 | L26: =+MID(B26,3,1) -> A | M26: =+IF(A26="1FO","D3",IF(A26="1CT","D4",IF(OR(A26="PC2",A26="RAB"),"MQ200","MQ250"))) -> MQ250
A27: PC5 | B27: 21A7B | C27: 02A311291J0S02 | D27: 09001450420204 | F27: 700 | G27: 0 | I27: =IF(OR(LEN(B27)=9,LEN(B27)=5),MID(B27,1,4),MID(B27,1,5)) -> 21A7 | J27: =IF(MID(I27,5,1)<>"",MID(I27,4,2),MID(I27,4,1))*1 -> 7 | K27: =+MID(B27,1,2)*1 -> 21 | L27: =+MID(B27,3,1) -> A | M27: =+IF(A27="1FO","D3",IF(A27="1CT","D4",IF(OR(A27="PC2",A27="RAB"),"MQ200","MQ250"))) -> MQ250
A28: RPK | B28: 21A7B | C28: << vacías >> | E28: X | F28: 0 | G28: 0 | H28: G | I28: =IF(OR(LEN(B28)=9,LEN(B28)=5),MID(B28,1,4),MID(B28,1,5)) -> 21A7 | J28: =IF(MID(I28,5,1)<>"",MID(I28,4,2),MID(I28,4,1))*1 -> 7 | K28: =+MID(B28,1,2)*1 -> 21 | L28: =+MID(B28,3,1) -> A | M28: =+IF(A28="1FO","D3",IF(A28="1CT","D4",IF(OR(A28="PC2",A28="RAB"),"MQ200","MQ250"))) -> MQ250
A29: PC5 | B29: 21A7C | C29: 02A311291J0S02 | D29: 09001450501445 | F29: 700 | G29: 0 | I29: =IF(OR(LEN(B29)=9,LEN(B29)=5),MID(B29,1,4),MID(B29,1,5)) -> 21A7 | J29: =IF(MID(I29,5,1)<>"",MID(I29,4,2),MID(I29,4,1))*1 -> 7 | K29: =+MID(B29,1,2)*1 -> 21 | L29: =+MID(B29,3,1) -> A | M29: =+IF(A29="1FO","D3",IF(A29="1CT","D4",IF(OR(A29="PC2",A29="RAB"),"MQ200","MQ250"))) -> MQ250
A30: RPK | B30: 21A7C | C30: << vacías >> | E30: X | F30: 0 | G30: 0 | H30: G | I30: =IF(OR(LEN(B30)=9,LEN(B30)=5),MID(B30,1,4),MID(B30,1,5)) -> 21A7 | J30: =IF(MID(I30,5,1)<>"",MID(I30,4,2),MID(I30,4,1))*1 -> 7 | K30: =+MID(B30,1,2)*1 -> 21 | L30: =+MID(B30,3,1) -> A | M30: =+IF(A30="1FO","D3",IF(A30="1CT","D4",IF(OR(A30="PC2",A30="RAB"),"MQ200","MQ250"))) -> MQ250
A31: PC5 | B31: 21A8A | C31: 02J31125500S07 | D31: 09001450420051 | F31: 0 | G31: 378 | I31: =IF(OR(LEN(B31)=9,LEN(B31)=5),MID(B31,1,4),MID(B31,1,5)) -> 21A8 | J31: =IF(MID(I31,5,1)<>"",MID(I31,4,2),MID(I31,4,1))*1 -> 8 | K31: =+MID(B31,1,2)*1 -> 21 | L31: =+MID(B31,3,1) -> A | M31: =+IF(A31="1FO","D3",IF(A31="1CT","D4",IF(OR(A31="PC2",A31="RAB"),"MQ200","MQ250"))) -> MQ250
A32: RPK | B32: 21A8A | C32: << vacías >> | E32: X | F32: 0 | G32: 0 | H32: G | I32: =IF(OR(LEN(B32)=9,LEN(B32)=5),MID(B32,1,4),MID(B32,1,5)) -> 21A8 | J32: =IF(MID(I32,5,1)<>"",MID(I32,4,2),MID(I32,4,1))*1 -> 8 | K32: =+MID(B32,1,2)*1 -> 21 | L32: =+MID(B32,3,1) -> A | M32: =+IF(A32="1FO","D3",IF(A32="1CT","D4",IF(OR(A32="PC2",A32="RAB"),"MQ200","MQ250"))) -> MQ250
A33: PC5 | B33: 21A8B | C33: 02J311103C0S10 | D33: 09001449051504 | F33: 105 | G33: 0 | I33: =IF(OR(LEN(B33)=9,LEN(B33)=5),MID(B33,1,4),MID(B33,1,5)) -> 21A8 | J33: =IF(MID(I33,5,1)<>"",MID(I33,4,2),MID(I33,4,1))*1 -> 8 | K33: =+MID(B33,1,2)*1 -> 21 | L33: =+MID(B33,3,1) -> A | M33: =+IF(A33="1FO","D3",IF(A33="1CT","D4",IF(OR(A33="PC2",A33="RAB"),"MQ200","MQ250"))) -> MQ250
A34: RPK | B34: 21A8B | C34: << vacías >> | E34: X | F34: 0 | G34: 0 | H34: G | I34: =IF(OR(LEN(B34)=9,LEN(B34)=5),MID(B34,1,4),MID(B34,1,5)) -> 21A8 | J34: =IF(MID(I34,5,1)<>"",MID(I34,4,2),MID(I34,4,1))*1 -> 8 | K34: =+MID(B34,1,2)*1 -> 21 | L34: =+MID(B34,3,1) -> A | M34: =+IF(A34="1FO","D3",IF(A34="1CT","D4",IF(OR(A34="PC2",A34="RAB"),"MQ200","MQ250"))) -> MQ250
A35: PC5 | B35: 21A8C | C35: 02J311103C0S10 | D35: 09001449051505 | F35: 105 | G35: 0 | I35: =IF(OR(LEN(B35)=9,LEN(B35)=5),MID(B35,1,4),MID(B35,1,5)) -> 21A8 | J35: =IF(MID(I35,5,1)<>"",MID(I35,4,2),MID(I35,4,1))*1 -> 8 | K35: =+MID(B35,1,2)*1 -> 21 | L35: =+MID(B35,3,1) -> A | M35: =+IF(A35="1FO","D3",IF(A35="1CT","D4",IF(OR(A35="PC2",A35="RAB"),"MQ200","MQ250"))) -> MQ250
A36: RPK | B36: 21A8C | C36: << vacías >> | E36: X | F36: 0 | G36: 0 | H36: G | I36: =IF(OR(LEN(B36)=9,LEN(B36)=5),MID(B36,1,4),MID(B36,1,5)) -> 21A8 | J36: =IF(MID(I36,5,1)<>"",MID(I36,4,2),MID(I36,4,1))*1 -> 8 | K36: =+MID(B36,1,2)*1 -> 21 | L36: =+MID(B36,3,1) -> A | M36: =+IF(A36="1FO","D3",IF(A36="1CT","D4",IF(OR(A36="PC2",A36="RAB"),"MQ200","MQ250"))) -> MQ250
A37: PC5 | B37: 21A9A | C37: << vacías >> | F37: 0 | G37: 0 | I37: =IF(OR(LEN(B37)=9,LEN(B37)=5),MID(B37,1,4),MID(B37,1,5)) -> 21A9 | J37: =IF(MID(I37,5,1)<>"",MID(I37,4,2),MID(I37,4,1))*1 -> 9 | K37: =+MID(B37,1,2)*1 -> 21 | L37: =+MID(B37,3,1) -> A | M37: =+IF(A37="1FO","D3",IF(A37="1CT","D4",IF(OR(A37="PC2",A37="RAB"),"MQ200","MQ250"))) -> MQ250
A38: RPK | B38: 21A9A | C38: << vacías >> | E38: X | F38: 0 | G38: 0 | H38: T | I38: =IF(OR(LEN(B38)=9,LEN(B38)=5),MID(B38,1,4),MID(B38,1,5)) -> 21A9 | J38: =IF(MID(I38,5,1)<>"",MID(I38,4,2),MID(I38,4,1))*1 -> 9 | K38: =+MID(B38,1,2)*1 -> 21 | L38: =+MID(B38,3,1) -> A | M38: =+IF(A38="1FO","D3",IF(A38="1CT","D4",IF(OR(A38="PC2",A38="RAB"),"MQ200","MQ250"))) -> MQ250
A39: PC5 | B39: 21A9B | C39: << vacías >> | F39: 0 | G39: 0 | I39: =IF(OR(LEN(B39)=9,LEN(B39)=5),MID(B39,1,4),MID(B39,1,5)) -> 21A9 | J39: =IF(MID(I39,5,1)<>"",MID(I39,4,2),MID(I39,4,1))*1 -> 9 | K39: =+MID(B39,1,2)*1 -> 21 | L39: =+MID(B39,3,1) -> A | M39: =+IF(A39="1FO","D3",IF(A39="1CT","D4",IF(OR(A39="PC2",A39="RAB"),"MQ200","MQ250"))) -> MQ250
A40: RPK | B40: 21A9B | C40: << vacías >> | E40: X | F40: 0 | G40: 0 | H40: T | I40: =IF(OR(LEN(B40)=9,LEN(B40)=5),MID(B40,1,4),MID(B40,1,5)) -> 21A9 | J40: =IF(MID(I40,5,1)<>"",MID(I40,4,2),MID(I40,4,1))*1 -> 9 | K40: =+MID(B40,1,2)*1 -> 21 | L40: =+MID(B40,3,1) -> A | M40: =+IF(A40="1FO","D3",IF(A40="1CT","D4",IF(OR(A40="PC2",A40="RAB"),"MQ200","MQ250"))) -> MQ250
A41: PC5 | B41: 21A9C | C41: << vacías >> | F41: 0 | G41: 0 | I41: =IF(OR(LEN(B41)=9,LEN(B41)=5),MID(B41,1,4),MID(B41,1,5)) -> 21A9 | J41: =IF(MID(I41,5,1)<>"",MID(I41,4,2),MID(I41,4,1))*1 -> 9 | K41: =+MID(B41,1,2)*1 -> 21 | L41: =+MID(B41,3,1) -> A | M41: =+IF(A41="1FO","D3",IF(A41="1CT","D4",IF(OR(A41="PC2",A41="RAB"),"MQ200","MQ250"))) -> MQ250
A42: RPK | B42: 21A9C | C42: << vacías >> | E42: X | F42: 0 | G42: 0 | H42: T | I42: =IF(OR(LEN(B42)=9,LEN(B42)=5),MID(B42,1,4),MID(B42,1,5)) -> 21A9 | J42: =IF(MID(I42,5,1)<>"",MID(I42,4,2),MID(I42,4,1))*1 -> 9 | K42: =+MID(B42,1,2)*1 -> 21 | L42: =+MID(B42,3,1) -> A | M42: =+IF(A42="1FO","D3",IF(A42="1CT","D4",IF(OR(A42="PC2",A42="RAB"),"MQ200","MQ250"))) -> MQ250
A43: PC5 | B43: 21B1A | C43: 02A31136500S04 | D43: 09001450677589 | F43: 288 | G43: 0 | I43: =IF(OR(LEN(B43)=9,LEN(B43)=5),MID(B43,1,4),MID(B43,1,5)) -> 21B1 | J43: =IF(MID(I43,5,1)<>"",MID(I43,4,2),MID(I43,4,1))*1 -> 1 | K43: =+MID(B43,1,2)*1 -> 21 | L43: =+MID(B43,3,1) -> B | M43: =+IF(A43="1FO","D3",IF(A43="1CT","D4",IF(OR(A43="PC2",A43="RAB"),"MQ200","MQ250"))) -> MQ250
A44: PC5 | B44: 21B1B | C44: 02A311291J0S02 | D44: 09001450600568 | F44: 700 | G44: 0 | I44: =IF(OR(LEN(B44)=9,LEN(B44)=5),MID(B44,1,4),MID(B44,1,5)) -> 21B1 | J44: =IF(MID(I44,5,1)<>"",MID(I44,4,2),MID(I44,4,1))*1 -> 1 | K44: =+MID(B44,1,2)*1 -> 21 | L44: =+MID(B44,3,1) -> B | M44: =+IF(A44="1FO","D3",IF(A44="1CT","D4",IF(OR(A44="PC2",A44="RAB"),"MQ200","MQ250"))) -> MQ250
A45: PC5 | B45: 21B1C | C45: 02J311103M0S10 | D45: 09001450221608 | F45: 126 | G45: 0 | I45: =IF(OR(LEN(B45)=9,LEN(B45)=5),MID(B45,1,4),MID(B45,1,5)) -> 21B1 | J45: =IF(MID(I45,5,1)<>"",MID(I45,4,2),MID(I45,4,1))*1 -> 1 | K45: =+MID(B45,1,2)*1 -> 21 | L45: =+MID(B45,3,1) -> B | M45: =+IF(A45="1FO","D3",IF(A45="1CT","D4",IF(OR(A45="PC2",A45="RAB"),"MQ200","MQ250"))) -> MQ250
A46: PC5 | B46: 21B1C | C46: 02J311103M0S10 | D46: 09001450224482 | F46: 49 | G46: 0 | I46: =IF(OR(LEN(B46)=9,LEN(B46)=5),MID(B46,1,4),MID(B46,1,5)) -> 21B1 | J46: =IF(MID(I46,5,1)<>"",MID(I46,4,2),MID(I46,4,1))*1 -> 1 | K46: =+MID(B46,1,2)*1 -> 21 | L46: =+MID(B46,3,1) -> B | M46: =+IF(A46="1FO","D3",IF(A46="1CT","D4",IF(OR(A46="PC2",A46="RAB"),"MQ200","MQ250"))) -> MQ250
A47: PC5 | B47: 21B2A | C47: << vacías >> | E47: X | F47: 0 | G47: 0 | H47: T | I47: =IF(OR(LEN(B47)=9,LEN(B47)=5),MID(B47,1,4),MID(B47,1,5)) -> 21B2 | J47: =IF(MID(I47,5,1)<>"",MID(I47,4,2),MID(I47,4,1))*1 -> 2 | K47: =+MID(B47,1,2)*1 -> 21 | L47: =+MID(B47,3,1) -> B | M47: =+IF(A47="1FO","D3",IF(A47="1CT","D4",IF(OR(A47="PC2",A47="RAB"),"MQ200","MQ250"))) -> MQ250
A48: PC5 | B48: 21B2B | C48: << vacías >> | E48: X | F48: 0 | G48: 0 | H48: T | I48: =IF(OR(LEN(B48)=9,LEN(B48)=5),MID(B48,1,4),MID(B48,1,5)) -> 21B2 | J48: =IF(MID(I48,5,1)<>"",MID(I48,4,2),MID(I48,4,1))*1 -> 2 | K48: =+MID(B48,1,2)*1 -> 21 | L48: =+MID(B48,3,1) -> B | M48: =+IF(A48="1FO","D3",IF(A48="1CT","D4",IF(OR(A48="PC2",A48="RAB"),"MQ200","MQ250"))) -> MQ250
A49: PC5 | B49: 21B2C | C49: << vacías >> | E49: X | F49: 0 | G49: 0 | H49: T | I49: =IF(OR(LEN(B49)=9,LEN(B49)=5),MID(B49,1,4),MID(B49,1,5)) -> 21B2 | J49: =IF(MID(I49,5,1)<>"",MID(I49,4,2),MID(I49,4,1))*1 -> 2 | K49: =+MID(B49,1,2)*1 -> 21 | L49: =+MID(B49,3,1) -> B | M49: =+IF(A49="1FO","D3",IF(A49="1CT","D4",IF(OR(A49="PC2",A49="RAB"),"MQ200","MQ250"))) -> MQ250
A50: PC5 | B50: 21B3A | C50: 02A311149AMS00 | D50: 09001449915809 | F50: 832 | G50: 0 | I50: =IF(OR(LEN(B50)=9,LEN(B50)=5),MID(B50,1,4),MID(B50,1,5)) -> 21B3 | J50: =IF(MID(I50,5,1)<>"",MID(I50,4,2),MID(I50,4,1))*1 -> 3 | K50: =+MID(B50,1,2)*1 -> 21 | L50: =+MID(B50,3,1) -> B | M50: =+IF(A50="1FO","D3",IF(A50="1CT","D4",IF(OR(A50="PC2",A50="RAB"),"MQ200","MQ250"))) -> MQ250
A51: PC5 | B51: 21B3B | C51: 02A311291J0S02 | D51: 09001450501446 | F51: 700 | G51: 0 | I51: =IF(OR(LEN(B51)=9,LEN(B51)=5),MID(B51,1,4),MID(B51,1,5)) -> 21B3 | J51: =IF(MID(I51,5,1)<>"",MID(I51,4,2),MID(I51,4,1))*1 -> 3 | K51: =+MID(B51,1,2)*1 -> 21 | L51: =+MID(B51,3,1) -> B | M51: =+IF(A51="1FO","D3",IF(A51="1CT","D4",IF(OR(A51="PC2",A51="RAB"),"MQ200","MQ250"))) -> MQ250
A52: PC5 | B52: 21B3C | C52: 02A311291K0S02 | D52: 09001441738450 | F52: 600 | G52: 0 | I52: =IF(OR(LEN(B52)=9,LEN(B52)=5),MID(B52,1,4),MID(B52,1,5)) -> 21B3 | J52: =IF(MID(I52,5,1)<>"",MID(I52,4,2),MID(I52,4,1))*1 -> 3 | K52: =+MID(B52,1,2)*1 -> 21 | L52: =+MID(B52,3,1) -> B | M52: =+IF(A52="1FO","D3",IF(A52="1CT","D4",IF(OR(A52="PC2",A52="RAB"),"MQ200","MQ250"))) -> MQ250
A53: PC5 | B53: 21B4A | C53: 0A431150701S00 | D53: 09001442241747 | F53: 560 | G53: 0 | I53: =IF(OR(LEN(B53)=9,LEN(B53)=5),MID(B53,1,4),MID(B53,1,5)) -> 21B4 | J53: =IF(MID(I53,5,1)<>"",MID(I53,4,2),MID(I53,4,1))*1 -> 4 | K53: =+MID(B53,1,2)*1 -> 21 | L53: =+MID(B53,3,1) -> B | M53: =+IF(A53="1FO","D3",IF(A53="1CT","D4",IF(OR(A53="PC2",A53="RAB"),"MQ200","MQ250"))) -> MQ250
A54: PC5 | B54: 21B4B | C54: 02J311103C0S10 | D54: 09001449077032 | F54: 105 | G54: 0 | I54: =IF(OR(LEN(B54)=9,LEN(B54)=5),MID(B54,1,4),MID(B54,1,5)) -> 21B4 | J54: =IF(MID(I54,5,1)<>"",MID(I54,4,2),MID(I54,4,1))*1 -> 4 | K54: =+MID(B54,1,2)*1 -> 21 | L54: =+MID(B54,3,1) -> B | M54: =+IF(A54="1FO","D3",IF(A54="1CT","D4",IF(OR(A54="PC2",A54="RAB"),"MQ200","MQ250"))) -> MQ250
A55: PC5 | B55: 21B4C | C55: 02J311103C0S10 | D55: 09001449110131 | F55: 75 | G55: 0 | I55: =IF(OR(LEN(B55)=9,LEN(B55)=5),MID(B55,1,4),MID(B55,1,5)) -> 21B4 | J55: =IF(MID(I55,5,1)<>"",MID(I55,4,2),MID(I55,4,1))*1 -> 4 | K55: =+MID(B55,1,2)*1 -> 21 | L55: =+MID(B55,3,1) -> B | M55: =+IF(A55="1FO","D3",IF(A55="1CT","D4",IF(OR(A55="PC2",A55="RAB"),"MQ200","MQ250"))) -> MQ250
A56: PC5 | B56: 21B5A | C56: 02A311291J0S02 | D56: 09001450536703 | F56: 700 | G56: 0 | I56: =IF(OR(LEN(B56)=9,LEN(B56)=5),MID(B56,1,4),MID(B56,1,5)) -> 21B5 | J56: =IF(MID(I56,5,1)<>"",MID(I56,4,2),MID(I56,4,1))*1 -> 5 | K56: =+MID(B56,1,2)*1 -> 21 | L56: =+MID(B56,3,1) -> B | M56: =+IF(A56="1FO","D3",IF(A56="1CT","D4",IF(OR(A56="PC2",A56="RAB"),"MQ200","MQ250"))) -> MQ250
A57: RPK | B57: 21B5A | C57: << vacías >> | E57: X | F57: 0 | G57: 0 | H57: G | I57: =IF(OR(LEN(B57)=9,LEN(B57)=5),MID(B57,1,4),MID(B57,1,5)) -> 21B5 | J57: =IF(MID(I57,5,1)<>"",MID(I57,4,2),MID(I57,4,1))*1 -> 5 | K57: =+MID(B57,1,2)*1 -> 21 | L57: =+MID(B57,3,1) -> B | M57: =+IF(A57="1FO","D3",IF(A57="1CT","D4",IF(OR(A57="PC2",A57="RAB"),"MQ200","MQ250"))) -> MQ250
A58: PC5 | B58: 21B5B | C58: 02A31136500S04 | D58: 09001446700293 | F58: 288 | G58: 0 | I58: =IF(OR(LEN(B58)=9,LEN(B58)=5),MID(B58,1,4),MID(B58,1,5)) -> 21B5 | J58: =IF(MID(I58,5,1)<>"",MID(I58,4,2),MID(I58,4,1))*1 -> 5 | K58: =+MID(B58,1,2)*1 -> 21 | L58: =+MID(B58,3,1) -> B | M58: =+IF(A58="1FO","D3",IF(A58="1CT","D4",IF(OR(A58="PC2",A58="RAB"),"MQ200","MQ250"))) -> MQ250
A59: PC5 | B59: 21B5C | C59: 02J311103F0S10 | D59: 09001449164191 | F59: 105 | G59: 0 | I59: =IF(OR(LEN(B59)=9,LEN(B59)=5),MID(B59,1,4),MID(B59,1,5)) -> 21B5 | J59: =IF(MID(I59,5,1)<>"",MID(I59,4,2),MID(I59,4,1))*1 -> 5 | K59: =+MID(B59,1,2)*1 -> 21 | L59: =+MID(B59,3,1) -> B | M59: =+IF(A59="1FO","D3",IF(A59="1CT","D4",IF(OR(A59="PC2",A59="RAB"),"MQ200","MQ250"))) -> MQ250
A60: PC5 | B60: 21B6A | C60: 02A311291J0S02 | D60: 09001450571718 | F60: 700 | G60: 0 | I60: =IF(OR(LEN(B60)=9,LEN(B60)=5),MID(B60,1,4),MID(B60,1,5)) -> 21B6 | J60: =IF(MID(I60,5,1)<>"",MID(I60,4,2),MID(I60,4,1))*1 -> 6 | K60: =+MID(B60,1,2)*1 -> 21 | L60: =+MID(B60,3,1) -> B | M60: =+IF(A60="1FO","D3",IF(A60="1CT","D4",IF(OR(A60="PC2",A60="RAB"),"MQ200","MQ250"))) -> MQ250
A61: RPK | B61: 21B6A | C61: << vacías >> | E61: X | F61: 0 | G61: 0 | H61: G | I61: =IF(OR(LEN(B61)=9,LEN(B61)=5),MID(B61,1,4),MID(B61,1,5)) -> 21B6 | J61: =IF(MID(I61,5,1)<>"",MID(I61,4,2),MID(I61,4,1))*1 -> 6 | K61: =+MID(B61,1,2)*1 -> 21 | L61: =+MID(B61,3,1) -> B | M61: =+IF(A61="1FO","D3",IF(A61="1CT","D4",IF(OR(A61="PC2",A61="RAB"),"MQ200","MQ250"))) -> MQ250
A62: PC5 | B62: 21B6B | C62: 02A31136500S04 | D62: 09001447637507 | F62: 288 | G62: 0 | I62: =IF(OR(LEN(B62)=9,LEN(B62)=5),MID(B62,1,4),MID(B62,1,5)) -> 21B6 | J62: =IF(MID(I62,5,1)<>"",MID(I62,4,2),MID(I62,4,1))*1 -> 6 | K62: =+MID(B62,1,2)*1 -> 21 | L62: =+MID(B62,3,1) -> B | M62: =+IF(A62="1FO","D3",IF(A62="1CT","D4",IF(OR(A62="PC2",A62="RAB"),"MQ200","MQ250"))) -> MQ250
A63: RPK | B63: 21B6B | C63: << vacías >> | E63: X | F63: 0 | G63: 0 | H63: G | I63: =IF(OR(LEN(B63)=9,LEN(B63)=5),MID(B63,1,4),MID(B63,1,5)) -> 21B6 | J63: =IF(MID(I63,5,1)<>"",MID(I63,4,2),MID(I63,4,1))*1 -> 6 | K63: =+MID(B63,1,2)*1 -> 21 | L63: =+MID(B63,3,1) -> B | M63: =+IF(A63="1FO","D3",IF(A63="1CT","D4",IF(OR(A63="PC2",A63="RAB"),"MQ200","MQ250"))) -> MQ250
A64: PC5 | B64: 21B6C | C64: 02A311291J0S02 | D64: 09001450571719 | F64: 700 | G64: 0 | I64: =IF(OR(LEN(B64)=9,LEN(B64)=5),MID(B64,1,4),MID(B64,1,5)) -> 21B6 | J64: =IF(MID(I64,5,1)<>"",MID(I64,4,2),MID(I64,4,1))*1 -> 6 | K64: =+MID(B64,1,2)*1 -> 21 | L64: =+MID(B64,3,1) -> B | M64: =+IF(A64="1FO","D3",IF(A64="1CT","D4",IF(OR(A64="PC2",A64="RAB"),"MQ200","MQ250"))) -> MQ250
A65: RPK | B65: 21B6C | C65: << vacías >> | E65: X | F65: 0 | G65: 0 | H65: G | I65: =IF(OR(LEN(B65)=9,LEN(B65)=5),MID(B65,1,4),MID(B65,1,5)) -> 21B6 | J65: =IF(MID(I65,5,1)<>"",MID(I65,4,2),MID(I65,4,1))*1 -> 6 | K65: =+MID(B65,1,2)*1 -> 21 | L65: =+MID(B65,3,1) -> B | M65: =+IF(A65="1FO","D3",IF(A65="1CT","D4",IF(OR(A65="PC2",A65="RAB"),"MQ200","MQ250"))) -> MQ250
A66: PC5 | B66: 21B7A | C66: 02A31136500S04 | D66: 09001446700294 | F66: 288 | G66: 0 | I66: =IF(OR(LEN(B66)=9,LEN(B66)=5),MID(B66,1,4),MID(B66,1,5)) -> 21B7 | J66: =IF(MID(I66,5,1)<>"",MID(I66,4,2),MID(I66,4,1))*1 -> 7 | K66: =+MID(B66,1,2)*1 -> 21 | L66: =+MID(B66,3,1) -> B | M66: =+IF(A66="1FO","D3",IF(A66="1CT","D4",IF(OR(A66="PC2",A66="RAB"),"MQ200","MQ250"))) -> MQ250
A67: RPK | B67: 21B7A | C67: << vacías >> | E67: X | F67: 0 | G67: 0 | H67: G | I67: =IF(OR(LEN(B67)=9,LEN(B67)=5),MID(B67,1,4),MID(B67,1,5)) -> 21B7 | J67: =IF(MID(I67,5,1)<>"",MID(I67,4,2),MID(I67,4,1))*1 -> 7 | K67: =+MID(B67,1,2)*1 -> 21 | L67: =+MID(B67,3,1) -> B | M67: =+IF(A67="1FO","D3",IF(A67="1CT","D4",IF(OR(A67="PC2",A67="RAB"),"MQ200","MQ250"))) -> MQ250
A68: PC5 | B68: 21B7B | C68: << vacías >> | F68: 0 | G68: 0 | I68: =IF(OR(LEN(B68)=9,LEN(B68)=5),MID(B68,1,4),MID(B68,1,5)) -> 21B7 | J68: =IF(MID(I68,5,1)<>"",MID(I68,4,2),MID(I68,4,1))*1 -> 7 | K68: =+MID(B68,1,2)*1 -> 21 | L68: =+MID(B68,3,1) -> B | M68: =+IF(A68="1FO","D3",IF(A68="1CT","D4",IF(OR(A68="PC2",A68="RAB"),"MQ200","MQ250"))) -> MQ250
A69: RPK | B69: 21B7B | C69: << vacías >> | E69: X | F69: 0 | G69: 0 | H69: G | I69: =IF(OR(LEN(B69)=9,LEN(B69)=5),MID(B69,1,4),MID(B69,1,5)) -> 21B7 | J69: =IF(MID(I69,5,1)<>"",MID(I69,4,2),MID(I69,4,1))*1 -> 7 | K69: =+MID(B69,1,2)*1 -> 21 | L69: =+MID(B69,3,1) -> B | M69: =+IF(A69="1FO","D3",IF(A69="1CT","D4",IF(OR(A69="PC2",A69="RAB"),"MQ200","MQ250"))) -> MQ250
A70: PC5 | B70: 21B7C | C70: 02J311103F0S10 | D70: 09001449212521 | F70: 105 | G70: 0 | I70: =IF(OR(LEN(B70)=9,LEN(B70)=5),MID(B70,1,4),MID(B70,1,5)) -> 21B7 | J70: =IF(MID(I70,5,1)<>"",MID(I70,4,2),MID(I70,4,1))*1 -> 7 | K70: =+MID(B70,1,2)*1 -> 21 | L70: =+MID(B70,3,1) -> B | M70: =+IF(A70="1FO","D3",IF(A70="1CT","D4",IF(OR(A70="PC2",A70="RAB"),"MQ200","MQ250"))) -> MQ250
A71: RPK | B71: 21B7C | C71: << vacías >> | E71: X | F71: 0 | G71: 0 | H71: G | I71: =IF(OR(LEN(B71)=9,LEN(B71)=5),MID(B71,1,4),MID(B71,1,5)) -> 21B7 | J71: =IF(MID(I71,5,1)<>"",MID(I71,4,2),MID(I71,4,1))*1 -> 7 | K71: =+MID(B71,1,2)*1 -> 21 | L71: =+MID(B71,3,1) -> B | M71: =+IF(A71="1FO","D3",IF(A71="1CT","D4",IF(OR(A71="PC2",A71="RAB"),"MQ200","MQ250"))) -> MQ250
A72: PC5 | B72: 21B8A | C72: 02A311291K0S02 | D72: 09001442184731 | F72: 600 | G72: 0 | I72: =IF(OR(LEN(B72)=9,LEN(B72)=5),MID(B72,1,4),MID(B72,1,5)) -> 21B8 | J72: =IF(MID(I72,5,1)<>"",MID(I72,4,2),MID(I72,4,1))*1 -> 8 | K72: =+MID(B72,1,2)*1 -> 21 | L72: =+MID(B72,3,1) -> B | M72: =+IF(A72="1FO","D3",IF(A72="1CT","D4",IF(OR(A72="PC2",A72="RAB"),"MQ200","MQ250"))) -> MQ250
A73: RPK | B73: 21B8A | C73: << vacías >> | E73: X | F73: 0 | G73: 0 | H73: G | I73: =IF(OR(LEN(B73)=9,LEN(B73)=5),MID(B73,1,4),MID(B73,1,5)) -> 21B8 | J73: =IF(MID(I73,5,1)<>"",MID(I73,4,2),MID(I73,4,1))*1 -> 8 | K73: =+MID(B73,1,2)*1 -> 21 | L73: =+MID(B73,3,1) -> B | M73: =+IF(A73="1FO","D3",IF(A73="1CT","D4",IF(OR(A73="PC2",A73="RAB"),"MQ200","MQ250"))) -> MQ250
A74: PC5 | B74: 21B8B | C74: 02A311291K0S02 | D74: 09001442184732 | F74: 600 | G74: 0 | I74: =IF(OR(LEN(B74)=9,LEN(B74)=5),MID(B74,1,4),MID(B74,1,5)) -> 21B8 | J74: =IF(MID(I74,5,1)<>"",MID(I74,4,2),MID(I74,4,1))*1 -> 8 | K74: =+MID(B74,1,2)*1 -> 21 | L74: =+MID(B74,3,1) -> B | M74: =+IF(A74="1FO","D3",IF(A74="1CT","D4",IF(OR(A74="PC2",A74="RAB"),"MQ200","MQ250"))) -> MQ250
A75: RPK | B75: 21B8B | C75: << vacías >> | E75: X | F75: 0 | G75: 0 | H75: G | I75: =IF(OR(LEN(B75)=9,LEN(B75)=5),MID(B75,1,4),MID(B75,1,5)) -> 21B8 | J75: =IF(MID(I75,5,1)<>"",MID(I75,4,2),MID(I75,4,1))*1 -> 8 | K75: =+MID(B75,1,2)*1 -> 21 | L75: =+MID(B75,3,1) -> B | M75: =+IF(A75="1FO","D3",IF(A75="1CT","D4",IF(OR(A75="PC2",A75="RAB"),"MQ200","MQ250"))) -> MQ250
A76: PC5 | B76: 21B8C | C76: << vacías >> | F76: 0 | G76: 0 | I76: =IF(OR(LEN(B76)=9,LEN(B76)=5),MID(B76,1,4),MID(B76,1,5)) -> 21B8 | J76: =IF(MID(I76,5,1)<>"",MID(I76,4,2),MID(I76,4,1))*1 -> 8 | K76: =+MID(B76,1,2)*1 -> 21 | L76: =+MID(B76,3,1) -> B | M76: =+IF(A76="1FO","D3",IF(A76="1CT","D4",IF(OR(A76="PC2",A76="RAB"),"MQ200","MQ250"))) -> MQ250
A77: RPK | B77: 21B8C | C77: << vacías >> | E77: X | F77: 0 | G77: 0 | H77: G | I77: =IF(OR(LEN(B77)=9,LEN(B77)=5),MID(B77,1,4),MID(B77,1,5)) -> 21B8 | J77: =IF(MID(I77,5,1)<>"",MID(I77,4,2),MID(I77,4,1))*1 -> 8 | K77: =+MID(B77,1,2)*1 -> 21 | L77: =+MID(B77,3,1) -> B | M77: =+IF(A77="1FO","D3",IF(A77="1CT","D4",IF(OR(A77="PC2",A77="RAB"),"MQ200","MQ250"))) -> MQ250
A78: PC5 | B78: 21B9A | C78: << vacías >> | F78: 0 | G78: 0 | I78: =IF(OR(LEN(B78)=9,LEN(B78)=5),MID(B78,1,4),MID(B78,1,5)) -> 21B9 | J78: =IF(MID(I78,5,1)<>"",MID(I78,4,2),MID(I78,4,1))*1 -> 9 | K78: =+MID(B78,1,2)*1 -> 21 | L78: =+MID(B78,3,1) -> B | M78: =+IF(A78="1FO","D3",IF(A78="1CT","D4",IF(OR(A78="PC2",A78="RAB"),"MQ200","MQ250"))) -> MQ250
A79: RPK | B79: 21B9A | C79: << vacías >> | E79: X | F79: 0 | G79: 0 | H79: G | I79: =IF(OR(LEN(B79)=9,LEN(B79)=5),MID(B79,1,4),MID(B79,1,5)) -> 21B9 | J79: =IF(MID(I79,5,1)<>"",MID(I79,4,2),MID(I79,4,1))*1 -> 9 | K79: =+MID(B79,1,2)*1 -> 21 | L79: =+MID(B79,3,1) -> B | M79: =+IF(A79="1FO","D3",IF(A79="1CT","D4",IF(OR(A79="PC2",A79="RAB"),"MQ200","MQ250"))) -> MQ250
A80: PC5 | B80: 21B9B | C80: << vacías >> | F80: 0 | G80: 0 | I80: =IF(OR(LEN(B80)=9,LEN(B80)=5),MID(B80,1,4),MID(B80,1,5)) -> 21B9 | J80: =IF(MID(I80,5,1)<>"",MID(I80,4,2),MID(I80,4,1))*1 -> 9 | K80: =+MID(B80,1,2)*1 -> 21 | L80: =+MID(B80,3,1) -> B | M80: =+IF(A80="1FO","D3",IF(A80="1CT","D4",IF(OR(A80="PC2",A80="RAB"),"MQ200","MQ250"))) -> MQ250
A81: RPK | B81: 21B9B | C81: << vacías >> | E81: X | F81: 0 | G81: 0 | H81: G | I81: =IF(OR(LEN(B81)=9,LEN(B81)=5),MID(B81,1,4),MID(B81,1,5)) -> 21B9 | J81: =IF(MID(I81,5,1)<>"",MID(I81,4,2),MID(I81,4,1))*1 -> 9 | K81: =+MID(B81,1,2)*1 -> 21 | L81: =+MID(B81,3,1) -> B | M81: =+IF(A81="1FO","D3",IF(A81="1CT","D4",IF(OR(A81="PC2",A81="RAB"),"MQ200","MQ250"))) -> MQ250
A82: PC5 | B82: 21B9C | C82: << vacías >> | F82: 0 | G82: 0 | I82: =IF(OR(LEN(B82)=9,LEN(B82)=5),MID(B82,1,4),MID(B82,1,5)) -> 21B9 | J82: =IF(MID(I82,5,1)<>"",MID(I82,4,2),MID(I82,4,1))*1 -> 9 | K82: =+MID(B82,1,2)*1 -> 21 | L82: =+MID(B82,3,1) -> B | M82: =+IF(A82="1FO","D3",IF(A82="1CT","D4",IF(OR(A82="PC2",A82="RAB"),"MQ200","MQ250"))) -> MQ250
A83: RPK | B83: 21B9C | C83: << vacías >> | E83: X | F83: 0 | G83: 0 | H83: G | I83: =IF(OR(LEN(B83)=9,LEN(B83)=5),MID(B83,1,4),MID(B83,1,5)) -> 21B9 | J83: =IF(MID(I83,5,1)<>"",MID(I83,4,2),MID(I83,4,1))*1 -> 9 | K83: =+MID(B83,1,2)*1 -> 21 | L83: =+MID(B83,3,1) -> B | M83: =+IF(A83="1FO","D3",IF(A83="1CT","D4",IF(OR(A83="PC2",A83="RAB"),"MQ200","MQ250"))) -> MQ250
A84: PC5 | B84: 21C10A | C84: 02A31136500S04 | D84: 09001447681070 | F84: 288 | G84: 0 | I84: =IF(OR(LEN(B84)=9,LEN(B84)=5),MID(B84,1,4),MID(B84,1,5)) -> 21C10 | J84: =IF(MID(I84,5,1)<>"",MID(I84,4,2),MID(I84,4,1))*1 -> 10 | K84: =+MID(B84,1,2)*1 -> 21 | L84: =+MID(B84,3,1) -> C | M84: =+IF(A84="1FO","D3",IF(A84="1CT","D4",IF(OR(A84="PC2",A84="RAB"),"MQ200","MQ250"))) -> MQ250
A85: RPK | B85: 21C10A | C85: << vacías >> | E85: X | F85: 0 | G85: 0 | H85: G | I85: =IF(OR(LEN(B85)=9,LEN(B85)=5),MID(B85,1,4),MID(B85,1,5)) -> 21C10 | J85: =IF(MID(I85,5,1)<>"",MID(I85,4,2),MID(I85,4,1))*1 -> 10 | K85: =+MID(B85,1,2)*1 -> 21 | L85: =+MID(B85,3,1) -> C | M85: =+IF(A85="1FO","D3",IF(A85="1CT","D4",IF(OR(A85="PC2",A85="RAB"),"MQ200","MQ250"))) -> MQ250
A86: PC5 | B86: 21C10B | C86: 02A311531Q0S00 | D86: 09001441771295 | F86: 675 | G86: 0 | I86: =IF(OR(LEN(B86)=9,LEN(B86)=5),MID(B86,1,4),MID(B86,1,5)) -> 21C10 | J86: =IF(MID(I86,5,1)<>"",MID(I86,4,2),MID(I86,4,1))*1 -> 10 | K86: =+MID(B86,1,2)*1 -> 21 | L86: =+MID(B86,3,1) -> C | M86: =+IF(A86="1FO","D3",IF(A86="1CT","D4",IF(OR(A86="PC2",A86="RAB"),"MQ200","MQ250"))) -> MQ250
A87: RPK | B87: 21C10B | C87: << vacías >> | E87: X | F87: 0 | G87: 0 | H87: G | I87: =IF(OR(LEN(B87)=9,LEN(B87)=5),MID(B87,1,4),MID(B87,1,5)) -> 21C10 | J87: =IF(MID(I87,5,1)<>"",MID(I87,4,2),MID(I87,4,1))*1 -> 10 | K87: =+MID(B87,1,2)*1 -> 21 | L87: =+MID(B87,3,1) -> C | M87: =+IF(A87="1FO","D3",IF(A87="1CT","D4",IF(OR(A87="PC2",A87="RAB"),"MQ200","MQ250"))) -> MQ250
A88: PC5 | B88: 21C10C | C88: 02J311103M0S10 | D88: 09001448511856 | F88: 27 | G88: 0 | I88: =IF(OR(LEN(B88)=9,LEN(B88)=5),MID(B88,1,4),MID(B88,1,5)) -> 21C10 | J88: =IF(MID(I88,5,1)<>"",MID(I88,4,2),MID(I88,4,1))*1 -> 10 | K88: =+MID(B88,1,2)*1 -> 21 | L88: =+MID(B88,3,1) -> C | M88: =+IF(A88="1FO","D3",IF(A88="1CT","D4",IF(OR(A88="PC2",A88="RAB"),"MQ200","MQ250"))) -> MQ250
A89: RPK | B89: 21C10C | C89: << vacías >> | E89: X | F89: 0 | G89: 0 | H89: G | I89: =IF(OR(LEN(B89)=9,LEN(B89)=5),MID(B89,1,4),MID(B89,1,5)) -> 21C10 | J89: =IF(MID(I89,5,1)<>"",MID(I89,4,2),MID(I89,4,1))*1 -> 10 | K89: =+MID(B89,1,2)*1 -> 21 | L89: =+MID(B89,3,1) -> C | M89: =+IF(A89="1FO","D3",IF(A89="1CT","D4",IF(OR(A89="PC2",A89="RAB"),"MQ200","MQ250"))) -> MQ250
A90: PC5 | B90: 21C11A | C90: 02T409169A0S02 | D90: 09001450536867 | F90: 741 | G90: 0 | I90: =IF(OR(LEN(B90)=9,LEN(B90)=5),MID(B90,1,4),MID(B90,1,5)) -> 21C11 | J90: =IF(MID(I90,5,1)<>"",MID(I90,4,2),MID(I90,4,1))*1 -> 11 | K90: =+MID(B90,1,2)*1 -> 21 | L90: =+MID(B90,3,1) -> C | M90: =+IF(A90="1FO","D3",IF(A90="1CT","D4",IF(OR(A90="PC2",A90="RAB"),"MQ200","MQ250"))) -> MQ250
A91: RPK | B91: 21C11A | C91: << vacías >> | E91: X | F91: 0 | G91: 0 | H91: G | I91: =IF(OR(LEN(B91)=9,LEN(B91)=5),MID(B91,1,4),MID(B91,1,5)) -> 21C11 | J91: =IF(MID(I91,5,1)<>"",MID(I91,4,2),MID(I91,4,1))*1 -> 11 | K91: =+MID(B91,1,2)*1 -> 21 | L91: =+MID(B91,3,1) -> C | M91: =+IF(A91="1FO","D3",IF(A91="1CT","D4",IF(OR(A91="PC2",A91="RAB"),"MQ200","MQ250"))) -> MQ250
A92: PC5 | B92: 21C11B | C92: 02T409169A0S02 | D92: 09001450495133 | F92: 0 | G92: 741 | I92: =IF(OR(LEN(B92)=9,LEN(B92)=5),MID(B92,1,4),MID(B92,1,5)) -> 21C11 | J92: =IF(MID(I92,5,1)<>"",MID(I92,4,2),MID(I92,4,1))*1 -> 11 | K92: =+MID(B92,1,2)*1 -> 21 | L92: =+MID(B92,3,1) -> C | M92: =+IF(A92="1FO","D3",IF(A92="1CT","D4",IF(OR(A92="PC2",A92="RAB"),"MQ200","MQ250"))) -> MQ250
A93: RPK | B93: 21C11B | C93: << vacías >> | E93: X | F93: 0 | G93: 0 | H93: G | I93: =IF(OR(LEN(B93)=9,LEN(B93)=5),MID(B93,1,4),MID(B93,1,5)) -> 21C11 | J93: =IF(MID(I93,5,1)<>"",MID(I93,4,2),MID(I93,4,1))*1 -> 11 | K93: =+MID(B93,1,2)*1 -> 21 | L93: =+MID(B93,3,1) -> C | M93: =+IF(A93="1FO","D3",IF(A93="1CT","D4",IF(OR(A93="PC2",A93="RAB"),"MQ200","MQ250"))) -> MQ250
A94: PC5 | B94: 21C11C | C94: 0DF409159C0S01 | D94: 09001450568717 | F94: 0 | G94: 585 | I94: =IF(OR(LEN(B94)=9,LEN(B94)=5),MID(B94,1,4),MID(B94,1,5)) -> 21C11 | J94: =IF(MID(I94,5,1)<>"",MID(I94,4,2),MID(I94,4,1))*1 -> 11 | K94: =+MID(B94,1,2)*1 -> 21 | L94: =+MID(B94,3,1) -> C | M94: =+IF(A94="1FO","D3",IF(A94="1CT","D4",IF(OR(A94="PC2",A94="RAB"),"MQ200","MQ250"))) -> MQ250
A95: RPK | B95: 21C11C | C95: << vacías >> | E95: X | F95: 0 | G95: 0 | H95: G | I95: =IF(OR(LEN(B95)=9,LEN(B95)=5),MID(B95,1,4),MID(B95,1,5)) -> 21C11 | J95: =IF(MID(I95,5,1)<>"",MID(I95,4,2),MID(I95,4,1))*1 -> 11 | K95: =+MID(B95,1,2)*1 -> 21 | L95: =+MID(B95,3,1) -> C | M95: =+IF(A95="1FO","D3",IF(A95="1CT","D4",IF(OR(A95="PC2",A95="RAB"),"MQ200","MQ250"))) -> MQ250
A96: PC5 | B96: 21C12A | C96: 0DF409159C0S01 | D96: 09001450568718 | F96: 0 | G96: 585 | I96: =IF(OR(LEN(B96)=9,LEN(B96)=5),MID(B96,1,4),MID(B96,1,5)) -> 21C12 | J96: =IF(MID(I96,5,1)<>"",MID(I96,4,2),MID(I96,4,1))*1 -> 12 | K96: =+MID(B96,1,2)*1 -> 21 | L96: =+MID(B96,3,1) -> C | M96: =+IF(A96="1FO","D3",IF(A96="1CT","D4",IF(OR(A96="PC2",A96="RAB"),"MQ200","MQ250"))) -> MQ250
A97: RPK | B97: 21C12A | C97: << vacías >> | E97: X | F97: 0 | G97: 0 | H97: G | I97: =IF(OR(LEN(B97)=9,LEN(B97)=5),MID(B97,1,4),MID(B97,1,5)) -> 21C12 | J97: =IF(MID(I97,5,1)<>"",MID(I97,4,2),MID(I97,4,1))*1 -> 12 | K97: =+MID(B97,1,2)*1 -> 21 | L97: =+MID(B97,3,1) -> C | M97: =+IF(A97="1FO","D3",IF(A97="1CT","D4",IF(OR(A97="PC2",A97="RAB"),"MQ200","MQ250"))) -> MQ250
A98: PC5 | B98: 21C12B | C98: 0DF409159C0S01 | D98: 09001450568719 | F98: 0 | G98: 585 | I98: =IF(OR(LEN(B98)=9,LEN(B98)=5),MID(B98,1,4),MID(B98,1,5)) -> 21C12 | J98: =IF(MID(I98,5,1)<>"",MID(I98,4,2),MID(I98,4,1))*1 -> 12 | K98: =+MID(B98,1,2)*1 -> 21 | L98: =+MID(B98,3,1) -> C | M98: =+IF(A98="1FO","D3",IF(A98="1CT","D4",IF(OR(A98="PC2",A98="RAB"),"MQ200","MQ250"))) -> MQ250
A99: RPK | B99: 21C12B | C99: << vacías >> | E99: X | F99: 0 | G99: 0 | H99: G | I99: =IF(OR(LEN(B99)=9,LEN(B99)=5),MID(B99,1,4),MID(B99,1,5)) -> 21C12 | J99: =IF(MID(I99,5,1)<>"",MID(I99,4,2),MID(I99,4,1))*1 -> 12 | K99: =+MID(B99,1,2)*1 -> 21 | L99: =+MID(B99,3,1) -> C | M99: =+IF(A99="1FO","D3",IF(A99="1CT","D4",IF(OR(A99="PC2",A99="RAB"),"MQ200","MQ250"))) -> MQ250
A100: PC5 | B100: 21C12C | C100: 0DF409159C0S01 | D100: 09001450568720 | F100: 0 | G100: 585 | I100: =IF(OR(LEN(B100)=9,LEN(B100)=5),MID(B100,1,4),MID(B100,1,5)) -> 21C12 | J100: =IF(MID(I100,5,1)<>"",MID(I100,4,2),MID(I100,4,1))*1 -> 12 | K100: =+MID(B100,1,2)*1 -> 21 | L100: =+MID(B100,3,1) -> C | M100: =+IF(A100="1FO","D3",IF(A100="1CT","D4",IF(OR(A100="PC2",A100="RAB"),"MQ200","MQ250"))) -> MQ250
...

Sheet dias
A1: fecha | B1: semana | C1: dia | D1: Cuenta | E1: mes | F1: conto? | H1: Feriados | K1: Cuenta | L1: (Todas) | P1: Etiquetas de fila | Q1: Sum of Cuenta | U1: Etiquetas de fila | V1: Sum of Cuenta
A2: 44927 | B2: =+WEEKNUM(A2) -> 1 | C2: =+WEEKDAY(A2,2) -> 7 | D2: =IF(AND(C2>=1,C2<=5,IFERROR(VLOOKUP(A2,$H$2:$H$10,1,0),0)=0),1,0) -> 0 | E2: =MONTH(A2) -> 1 | F2: =IF(IFERROR(VLOOKUP(A2,'Planilla de control'!#REF!,1,0),0)>0,1,0) -> 0 | P2: 8 | Q2: 23 | U2: 8 | V2: 23
A3: 44928 | B3: =+WEEKNUM(A3) -> 1 | C3: =+WEEKDAY(A3,2) -> 1 | D3: =IF(AND(C3>=1,C3<=5,IFERROR(VLOOKUP(A3,$H$2:$H$10,1,0),0)=0),1,0) -> 1 | E3: =MONTH(A3) -> 1 | F3: =IF(IFERROR(VLOOKUP(A3,'Planilla de control'!#REF!,1,0),0)>0,1,0) -> 0 | H3: 44977 | K3: Etiquetas de fila | L3: Sum of conto? | P3: 9 | Q3: 21 | U3: 32 | V3: 5
A4: 44929 | B4: =+WEEKNUM(A4) -> 1 | C4: =+WEEKDAY(A4,2) -> 2 | D4: =IF(AND(C4>=1,C4<=5,IFERROR(VLOOKUP(A4,$H$2:$H$10,1,0),0)=0),1,0) -> 1 | E4: =MONTH(A4) -> 1 | F4: =IF(IFERROR(VLOOKUP(A4,'Planilla de control'!#REF!,1,0),0)>0,1,0) -> 0 | H4: 44978 | K4: 8 | L4: 2 | P4: 10 | Q4: 22 | U4: 33 | V4: 5
A5: 44930 | B5: =+WEEKNUM(A5) -> 1 | C5: =+WEEKDAY(A5,2) -> 3 | D5: =IF(AND(C5>=1,C5<=5,IFERROR(VLOOKUP(A5,$H$2:$H$10,1,0),0)=0),1,0) -> 1 | E5: =MONTH(A5) -> 1 | F5: =IF(IFERROR(VLOOKUP(A5,'Planilla de control'!#REF!,1,0),0)>0,1,0) -> 0 | H5: 44981 | K5: 32 | L5: 0 | P5: 11 | Q5: 22 | U5: 34 | V5: 5
A6: 44931 | B6: =+WEEKNUM(A6) -> 1 | C6: =+WEEKDAY(A6,2) -> 4 | D6: =IF(AND(C6>=1,C6<=5,IFERROR(VLOOKUP(A6,$H$2:$H$10,1,0),0)=0),1,0) -> 1 | E6: =MONTH(A6) -> 1 | F6: =IF(IFERROR(VLOOKUP(A6,'Planilla de control'!#REF!,1,0),0)>0,1,0) -> 0 | H6: 45009 | K6: 33 | L6: 0 | P6: 12 | Q6: 21 | U6: 35 | V6: 4
A7: 44932 | B7: =+WEEKNUM(A7) -> 1 | C7: =+WEEKDAY(A7,2) -> 5 | D7: =IF(AND(C7>=1,C7<=5,IFERROR(VLOOKUP(A7,$H$2:$H$10,1,0),0)=0),1,0) -> 1 | E7: =MONTH(A7) -> 1 | F7: =IF(IFERROR(VLOOKUP(A7,'Planilla de control'!#REF!,1,0),0)>0,1,0) -> 0 | H7: 45023 | K7: 34 | L7: 0 | P7: (en blanco) | U7: 31 | V7: 4
A8: 44933 | B8: =+WEEKNUM(A8) -> 1 | C8: =+WEEKDAY(A8,2) -> 6 | D8: =IF(AND(C8>=1,C8<=5,IFERROR(VLOOKUP(A8,$H$2:$H$10,1,0),0)=0),1,0) -> 0 | E8: =MONTH(A8) -> 1 | F8: =IF(IFERROR(VLOOKUP(A8,'Planilla de control'!#REF!,1,0),0)>0,1,0) -> 0 | H8: 45047 | K8: 35 | L8: 2 | P8: 1 | Q8: 22 | U8: 9 | V8: 21
A9: 44934 | B9: =+WEEKNUM(A9) -> 2 | C9: =+WEEKDAY(A9,2) -> 7 | D9: =IF(AND(C9>=1,C9<=5,IFERROR(VLOOKUP(A9,$H$2:$H$10,1,0),0)=0),1,0) -> 0 | E9: =MONTH(A9) -> 1 | F9: =IF(IFERROR(VLOOKUP(A9,'Planilla de control'!#REF!,1,0),0)>0,1,0) -> 0 | H9: 45071 | K9: 31 | L9: 0 | P9: 2 | Q9: 17 | U9: 35 | V9: 1
A10: 44935 | B10: =+WEEKNUM(A10) -> 2 | C10: =+WEEKDAY(A10,2) -> 1 | D10: =IF(AND(C10>=1,C10<=5,IFERROR(VLOOKUP(A10,$H$2:$H$10,1,0),0)=0),1,0) -> 1 | E10: =MONTH(A10) -> 1 | F10: =IF(IFERROR(VLOOKUP(A10,'Planilla de control'!#REF!,1,0),0)>0,1,0) -> 0 | H10: 45072 | K10: 9 | L10: 1 | P10: 3 | Q10: 22 | U10: 36 | V10: 5
A11: 44936 | B11: =+WEEKNUM(A11) -> 2 | C11: =+WEEKDAY(A11,2) -> 2 | D11: =IF(AND(C11>=1,C11<=5,IFERROR(VLOOKUP(A11,$H$2:$H$10,1,0),0)=0),1,0) -> 1 | E11: =MONTH(A11) -> 1 | F11: =IF(IFERROR(VLOOKUP(A11,'Planilla de control'!#REF!,1,0),0)>0,1,0) -> 0 | H11: 45096 | K11: 35 | L11: 1 | P11: 4 | Q11: 19 | U11: 37 | V11: 5
A12: 44937 | B12: =+WEEKNUM(A12) -> 2 | C12: =+WEEKDAY(A12,2) -> 3 | D12: =IF(AND(C12>=1,C12<=5,IFERROR(VLOOKUP(A12,$H$2:$H$10,1,0),0)=0),1,0) -> 1 | E12: =MONTH(A12) -> 1 | F12: =IF(IFERROR(VLOOKUP(A12,'Planilla de control'!#REF!,1,0),0)>0,1,0) -> 0 | H12: 45097 | K12: 36 | L12: 0 | P12: 5 | Q12: 20 | U12: 38 | V12: 5
A13: 44938 | B13: =+WEEKNUM(A13) -> 2 | C13: =+WEEKDAY(A13,2) -> 4 | D13: =IF(AND(C13>=1,C13<=5,IFERROR(VLOOKUP(A13,$H$2:$H$10,1,0),0)=0),1,0) -> 1 | E13: =MONTH(A13) -> 1 | F13: =IF(IFERROR(VLOOKUP(A13,'Planilla de control'!#REF!,1,0),0)>0,1,0) -> 0 | K13: 37 | L13: 0 | P13: 6 | Q13: 22 | U13: 39 | V13: 5
A14: 44939 | B14: =+WEEKNUM(A14) -> 2 | C14: =+WEEKDAY(A14,2) -> 5 | D14: =IF(AND(C14>=1,C14<=5,IFERROR(VLOOKUP(A14,$H$2:$H$10,1,0),0)=0),1,0) -> 1 | E14: =MONTH(A14) -> 1 | F14: =IF(IFERROR(VLOOKUP(A14,'Planilla de control'!#REF!,1,0),0)>0,1,0) -> 0 | K14: 38 | L14: 0 | P14: 7 | Q14: 21 | U14: 10 | V14: 22
A15: 44940 | B15: =+WEEKNUM(A15) -> 2 | C15: =+WEEKDAY(A15,2) -> 6 | D15: =IF(AND(C15>=1,C15<=5,IFERROR(VLOOKUP(A15,$H$2:$H$10,1,0),0)=0),1,0) -> 0 | E15: =MONTH(A15) -> 1 | F15: =IF(IFERROR(VLOOKUP(A15,'Planilla de control'!#REF!,1,0),0)>0,1,0) -> 0 | K15: 39 | L15: 0 | P15: Total general | Q15: 252 | U15: 40 | V15: 5
A16: 44941 | B16: =+WEEKNUM(A16) -> 3 | C16: =+WEEKDAY(A16,2) -> 7 | D16: =IF(AND(C16>=1,C16<=5,IFERROR(VLOOKUP(A16,$H$2:$H$10,1,0),0)=0),1,0) -> 0 | E16: =MONTH(A16) -> 1 | F16: =IF(IFERROR(VLOOKUP(A16,'Planilla de control'!#REF!,1,0),0)>0,1,0) -> 0 | K16: 10 | L16: 0 | U16: 41 | V16: 5
A17: 44942 | B17: =+WEEKNUM(A17) -> 3 | C17: =+WEEKDAY(A17,2) -> 1 | D17: =IF(AND(C17>=1,C17<=5,IFERROR(VLOOKUP(A17,$H$2:$H$10,1,0),0)=0),1,0) -> 1 | E17: =MONTH(A17) -> 1 | F17: =IF(IFERROR(VLOOKUP(A17,'Planilla de control'!#REF!,1,0),0)>0,1,0) -> 0 | K17: 40 | L17: 0 | U17: 42 | V17: 5
A18: 44943 | B18: =+WEEKNUM(A18) -> 3 | C18: =+WEEKDAY(A18,2) -> 2 | D18: =IF(AND(C18>=1,C18<=5,IFERROR(VLOOKUP(A18,$H$2:$H$10,1,0),0)=0),1,0) -> 1 | E18: =MONTH(A18) -> 1 | F18: =IF(IFERROR(VLOOKUP(A18,'Planilla de control'!#REF!,1,0),0)>0,1,0) -> 0 | K18: 41 | L18: 0 | U18: 43 | V18: 5
A19: 44944 | B19: =+WEEKNUM(A19) -> 3 | C19: =+WEEKDAY(A19,2) -> 3 | D19: =IF(AND(C19>=1,C19<=5,IFERROR(VLOOKUP(A19,$H$2:$H$10,1,0),0)=0),1,0) -> 1 | E19: =MONTH(A19) -> 1 | F19: =IF(IFERROR(VLOOKUP(A19,'Planilla de control'!#REF!,1,0),0)>0,1,0) -> 0 | K19: 42 | L19: 0 | U19: 44 | V19: 2
A20: 44945 | B20: =+WEEKNUM(A20) -> 3 | C20: =+WEEKDAY(A20,2) -> 4 | D20: =IF(AND(C20>=1,C20<=5,IFERROR(VLOOKUP(A20,$H$2:$H$10,1,0),0)=0),1,0) -> 1 | E20: =MONTH(A20) -> 1 | F20: =IF(IFERROR(VLOOKUP(A20,'Planilla de control'!#REF!,1,0),0)>0,1,0) -> 0 | K20: 43 | L20: 0 | U20: 11 | V20: 22
A21: 44946 | B21: =+WEEKNUM(A21) -> 3 | C21: =+WEEKDAY(A21,2) -> 5 | D21: =IF(AND(C21>=1,C21<=5,IFERROR(VLOOKUP(A21,$H$2:$H$10,1,0),0)=0),1,0) -> 1 | E21: =MONTH(A21) -> 1 | F21: =IF(IFERROR(VLOOKUP(A21,'Planilla de control'!#REF!,1,0),0)>0,1,0) -> 0 | K21: 44 | L21: 0 | U21: 44 | V21: 3
A22: 44947 | B22: =+WEEKNUM(A22) -> 3 | C22: =+WEEKDAY(A22,2) -> 6 | D22: =IF(AND(C22>=1,C22<=5,IFERROR(VLOOKUP(A22,$H$2:$H$10,1,0),0)=0),1,0) -> 0 | E22: =MONTH(A22) -> 1 | F22: =IF(IFERROR(VLOOKUP(A22,'Planilla de control'!#REF!,1,0),0)>0,1,0) -> 0 | K22: 11 | L22: 0 | U22: 45 | V22: 5
A23: 44948 | B23: =+WEEKNUM(A23) -> 4 | C23: =+WEEKDAY(A23,2) -> 7 | D23: =IF(AND(C23>=1,C23<=5,IFERROR(VLOOKUP(A23,$H$2:$H$10,1,0),0)=0),1,0) -> 0 | E23: =MONTH(A23) -> 1 | F23: =IF(IFERROR(VLOOKUP(A23,'Planilla de control'!#REF!,1,0),0)>0,1,0) -> 0 | K23: 44 | L23: 0 | U23: 46 | V23: 5
A24: 44949 | B24: =+WEEKNUM(A24) -> 4 | C24: =+WEEKDAY(A24,2) -> 1 | D24: =IF(AND(C24>=1,C24<=5,IFERROR(VLOOKUP(A24,$H$2:$H$10,1,0),0)=0),1,0) -> 1 | E24: =MONTH(A24) -> 1 | F24: =IF(IFERROR(VLOOKUP(A24,'Planilla de control'!#REF!,1,0),0)>0,1,0) -> 0 | K24: 45 | L24: 0 | U24: 47 | V24: 5
A25: 44950 | B25: =+WEEKNUM(A25) -> 4 | C25: =+WEEKDAY(A25,2) -> 2 | D25: =IF(AND(C25>=1,C25<=5,IFERROR(VLOOKUP(A25,$H$2:$H$10,1,0),0)=0),1,0) -> 1 | E25: =MONTH(A25) -> 1 | F25: =IF(IFERROR(VLOOKUP(A25,'Planilla de control'!#REF!,1,0),0)>0,1,0) -> 0 | K25: 46 | L25: 0 | U25: 48 | V25: 4
A26: 44951 | B26: =+WEEKNUM(A26) -> 4 | C26: =+WEEKDAY(A26,2) -> 3 | D26: =IF(AND(C26>=1,C26<=5,IFERROR(VLOOKUP(A26,$H$2:$H$10,1,0),0)=0),1,0) -> 1 | E26: =MONTH(A26) -> 1 | F26: =IF(IFERROR(VLOOKUP(A26,'Planilla de control'!#REF!,1,0),0)>0,1,0) -> 0 | K26: 47 | L26: 0 | U26: 12 | V26: 21
A27: 44952 | B27: =+WEEKNUM(A27) -> 4 | C27: =+WEEKDAY(A27,2) -> 4 | D27: =IF(AND(C27>=1,C27<=5,IFERROR(VLOOKUP(A27,$H$2:$H$10,1,0),0)=0),1,0) -> 1 | E27: =MONTH(A27) -> 1 | F27: =IF(IFERROR(VLOOKUP(A27,'Planilla de control'!#REF!,1,0),0)>0,1,0) -> 0 | K27: 48 | L27: 0 | U27: 48 | V27: 1
... A32: 44957 | B32: =+WEEKNUM(A32) -> 5 | C32: =+WEEKDAY(A32,2) -> 2 | D32: =IF(AND(C32>=1,C32<=5,IFERROR(VLOOKUP(A32,$H$2:$H$10,1,0),0)=0),1,0) -> 1 | E32: =MONTH(A32) -> 1 | F32: =IF(IFERROR(VLOOKUP(A32,'Planilla de control'!#REF!,1,0),0)>0,1,0) -> 0 | K32: 51 | L32: 0 | U32: 53 | V32: 0
A33: 44958 | B33: =+WEEKNUM(A33) -> 5 | C33: =+WEEKDAY(A33,2) -> 3 | D33: =IF(AND(C33>=1,C33<=5,IFERROR(VLOOKUP(A33,$H$2:$H$10,1,0),0)=0),1,0) -> 1 | E33: =MONTH(A33) -> 2 | F33: =IF(IFERROR(VLOOKUP(A33,'Planilla de control'!#REF!,1,0),0)>0,1,0) -> 0 | K33: 52 | L33: 0 | U33: (en blanco)
A34: 44959 | B34: =+WEEKNUM(A34) -> 5 | C34: =+WEEKDAY(A34,2) -> 4 | D34: =IF(AND(C34>=1,C34<=5,IFERROR(VLOOKUP(A34,$H$2:$H$10,1,0),0)=0),1,0) -> 1 | E34: =MONTH(A34) -> 2 | F34: =IF(IFERROR(VLOOKUP(A34,'Planilla de control'!#REF!,1,0),0)>0,1,0) -> 0 | K34: 53 | L34: 0 | U34: (en blanco)
A35: 44960 | B35: =+WEEKNUM(A35) -> 5 | C35: =+WEEKDAY(A35,2) -> 5 | D35: =IF(AND(C35>=1,C35<=5,IFERROR(VLOOKUP(A35,$H$2:$H$10,1,0),0)=0),1,0) -> 1 | E35: =MONTH(A35) -> 2 | F35: =IF(IFERROR(VLOOKUP(A35,'Planilla de control'!#REF!,1,0),0)>0,1,0) -> 0 | K35: (en blanco) | U35: 1 | V35: 22
A36: 44961 | B36: =+WEEKNUM(A36) -> 5 | C36: =+WEEKDAY(A36,2) -> 6 | D36: =IF(AND(C36>=1,C36<=5,IFERROR(VLOOKUP(A36,$H$2:$H$10,1,0),0)=0),1,0) -> 0 | E36: =MONTH(A36) -> 2 | F36: =IF(IFERROR(VLOOKUP(A36,'Planilla de control'!#REF!,1,0),0)>0,1,0) -> 0 | K36: (en blanco) | U36: 1 | V36: 5
A37: 44962 | B37: =+WEEKNUM(A37) -> 6 | C37: =+WEEKDAY(A37,2) -> 7 | D37: =IF(AND(C37>=1,C37<=5,IFERROR(VLOOKUP(A37,$H$2:$H$10,1,0),0)=0),1,0) -> 0 | E37: =MONTH(A37) -> 2 | F37: =IF(IFERROR(VLOOKUP(A37,'Planilla de control'!#REF!,1,0),0)>0,1,0) -> 0 | K37: 1 | L37: 0 | U37: 2 | V37: 5
A38: 44963 | B38: =+WEEKNUM(A38) -> 6 | C38: =+WEEKDAY(A38,2) -> 1 | D38: =IF(AND(C38>=1,C38<=5,IFERROR(VLOOKUP(A38,$H$2:$H$10,1,0),0)=0),1,0) -> 1 | E38: =MONTH(A38) -> 2 | F38: =IF(IFERROR(VLOOKUP(A38,'Planilla de control'!#REF!,1,0),0)>0,1,0) -> 0 | K38: 1 | L38: 0 | U38: 3 | V38: 5
A39: 44964 | B39: =+WEEKNUM(A39) -> 6 | C39: =+WEEKDAY(A39,2) -> 2 | D39: =IF(AND(C39>=1,C39<=5,IFERROR(VLOOKUP(A39,$H$2:$H$10,1,0),0)=0),1,0) -> 1 | E39: =MONTH(A39) -> 2 | F39: =IF(IFERROR(VLOOKUP(A39,'Planilla de control'!#REF!,1,0),0)>0,1,0) -> 0 | K39: 2 | L39: 0 | U39: 4 | V39: 5
A40: 44965 | B40: =+WEEKNUM(A40) -> 6 | C40: =+WEEKDAY(A40,2) -> 3 | D40: =IF(AND(C40>=1,C40<=5,IFERROR(VLOOKUP(A40,$H$2:$H$10,1,0),0)=0),1,0) -> 1 | E40: =MONTH(A40) -> 2 | F40: =IF(IFERROR(VLOOKUP(A40,'Planilla de control'!#REF!,1,0),0)>0,1,0) -> 0 | K40: 3 | L40: 0 | U40: 5 | V40: 2
A41: 44966 | B41: =+WEEKNUM(A41) -> 6 | C41: =+WEEKDAY(A41,2) -> 4 | D41: =IF(AND(C41>=1,C41<=5,IFERROR(VLOOKUP(A41,$H$2:$H$10,1,0),0)=0),1,0) -> 1 | E41: =MONTH(A41) -> 2 | F41: =IF(IFERROR(VLOOKUP(A41,'Planilla de control'!#REF!,1,0),0)>0,1,0) -> 0 | K41: 4 | L41: 0 | U41: 2 | V41: 17
A42: 44967 | B42: =+WEEKNUM(A42) -> 6 | C42: =+WEEKDAY(A42,2) -> 5 | D42: =IF(AND(C42>=1,C42<=5,IFERROR(VLOOKUP(A42,$H$2:$H$10,1,0),0)=0),1,0) -> 1 | E42: =MONTH(A42) -> 2 | F42: =IF(IFERROR(VLOOKUP(A42,'Planilla de control'!#REF!,1,0),0)>0,1,0) -> 0 | K42: 5 | L42: 0 | U42: 5 | V42: 3
A43: 44968 | B43: =+WEEKNUM(A43) -> 6 | C43: =+WEEKDAY(A43,2) -> 6 | D43: =IF(AND(C43>=1,C43<=5,IFERROR(VLOOKUP(A43,$H$2:$H$10,1,0),0)=0),1,0) -> 0 | E43: =MONTH(A43) -> 2 | F43: =IF(IFERROR(VLOOKUP(A43,'Planilla de control'!#REF!,1,0),0)>0,1,0) -> 0 | K43: 2 | L43: 0 | U43: 6 | V43: 5
A44: 44969 | B44: =+WEEKNUM(A44) -> 7 | C44: =+WEEKDAY(A44,2) -> 7 | D44: =IF(AND(C44>=1,C44<=5,IFERROR(VLOOKUP(A44,$H$2:$H$10,1,0),0)=0),1,0) -> 0 | E44: =MONTH(A44) -> 2 | F44: =IF(IFERROR(VLOOKUP(A44,'Planilla de control'!#REF!,1,0),0)>0,1,0) -> 0 | K44: 5 | L44: 0 | U44: 7 | V44: 5
A45: 44970 | B45: =+WEEKNUM(A45) -> 7 | C45: =+WEEKDAY(A45,2) -> 1 | D45: =IF(AND(C45>=1,C45<=5,IFERROR(VLOOKUP(A45,$H$2:$H$10,1,0),0)=0),1,0) -> 1 | E45: =MONTH(A45) -> 2 | F45: =IF(IFERROR(VLOOKUP(A45,'Planilla de control'!#REF!,1,0),0)>0,1,0) -> 0 | K45: 6 | L45: 0 | U45: 8 | V45: 2
A46: 44971 | B46: =+WEEKNUM(A46) -> 7 | C46: =+WEEKDAY(A46,2) -> 2 | D46: =IF(AND(C46>=1,C46<=5,IFERROR(VLOOKUP(A46,$H$2:$H$10,1,0),0)=0),1,0) -> 1 | E46: =MONTH(A46) -> 2 | F46: =IF(IFERROR(VLOOKUP(A46,'Planilla de control'!#REF!,1,0),0)>0,1,0) -> 0 | K46: 7 | L46: 0 | U46: 9 | V46: 2
A47: 44972 | B47: =+WEEKNUM(A47) -> 7 | C47: =+WEEKDAY(A47,2) -> 3 | D47: =IF(AND(C47>=1,C47<=5,IFERROR(VLOOKUP(A47,$H$2:$H$10,1,0),0)=0),1,0) -> 1 | E47: =MONTH(A47) -> 2 | F47: =IF(IFERROR(VLOOKUP(A47,'Planilla de control'!#REF!,1,0),0)>0,1,0) -> 0 | K47: 8 | L47: 0 | U47: 3 | V47: 22
A48: 44973 | B48: =+WEEKNUM(A48) -> 7 | C48: =+WEEKDAY(A48,2) -> 4 | D48: =IF(AND(C48>=1,C48<=5,IFERROR(VLOOKUP(A48,$H$2:$H$10,1,0),0)=0),1,0) -> 1 | E48: =MONTH(A48) -> 2 | F48: =IF(IFERROR(VLOOKUP(A48,'Planilla de control'!#REF!,1,0),0)>0,1,0) -> 0 | K48: 9 | L48: 0 | U48: 9 | V48: 3
... A51: 44976 | B51: =+WEEKNUM(A51) -> 8 | C51: =+WEEKDAY(A51,2) -> 7 | D51: =IF(AND(C51>=1,C51<=5,IFERROR(VLOOKUP(A51,$H$2:$H$10,1,0),0)=0),1,0) -> 0 | E51: =MONTH(A51) -> 2 | F51: =IF(IFERROR(VLOOKUP(A51,'Planilla de control'!#REF!,1,0),0)>0,1,0) -> 0 | K51: 10 | L51: 0 | U51: 12 | V51: 4
A52: 44977 | B52: =+WEEKNUM(A52) -> 8 | C52: 8 | D52: =IF(AND(C52>=1,C52<=5,IFERROR(VLOOKUP(A52,$H$2:$H$10,1,0),0)=0),1,0) -> 0 | E52: =MONTH(A52) -> 2 | F52: =IF(IFERROR(VLOOKUP(A52,'Planilla de control'!#REF!,1,0),0)>0,1,0) -> 0 | K52: 11 | L52: 0 | U52: 13 | V52: 5
A53: 44978 | B53: =+WEEKNUM(A53) -> 8 | C53: =+WEEKDAY(A53,2) -> 2 | D53: =IF(AND(C53>=1,C53<=5,IFERROR(VLOOKUP(A53,$H$2:$H$10,1,0),0)=0),1,0) -> 0 | E53: =MONTH(A53) -> 2 | F53: =IF(IFERROR(VLOOKUP(A53,'Planilla de control'!#REF!,1,0),0)>0,1,0) -> 0 | K53: 12 | L53: 0 | U53: 4 | V53: 19
A54: 44979 | B54: =+WEEKNUM(A54) -> 8 | C54: =+WEEKDAY(A54,2) -> 3 | D54: =IF(AND(C54>=1,C54<=5,IFERROR(VLOOKUP(A54,$H$2:$H$10,1,0),0)=0),1,0) -> 1 | E54: =MONTH(A54) -> 2 | F54: =IF(IFERROR(VLOOKUP(A54,'Planilla de control'!#REF!,1,0),0)>0,1,0) -> 0 | K54: 13 | L54: 0 | U54: 13 | V54: 0
A55: 44980 | B55: =+WEEKNUM(A55) -> 8 | C55: =+WEEKDAY(A55,2) -> 4 | D55: =IF(AND(C55>=1,C55<=5,IFERROR(VLOOKUP(A55,$H$2:$H$10,1,0),0)=0),1,0) -> 1 | E55: =MONTH(A55) -> 2 | F55: =IF(IFERROR(VLOOKUP(A55,'Planilla de control'!#REF!,1,0),0)>0,1,0) -> 0 | K55: 4 | L55: 0 | U55: 14 | V55: 4
A56: 44981 | B56: =+WEEKNUM(A56) -> 8 | C56: =+WEEKDAY(A56,2) -> 5 | D56: =IF(AND(C56>=1,C56<=5,IFERROR(VLOOKUP(A56,$H$2:$H$10,1,0),0)=0),1,0) -> 0 | E56: =MONTH(A56) -> 2 | F56: =IF(IFERROR(VLOOKUP(A56,'Planilla de control'!#REF!,1,0),0)>0,1,0) -> 0 | K56: 13 | L56: 0 | U56: 15 | V56: 5
A57: 44982 | B57: =+WEEKNUM(A57) -> 8 | C57: =+WEEKDAY(A57,2) -> 6 | D57: =IF(AND(C57>=1,C57<=5,IFERROR(VLOOKUP(A57,$H$2:$H$10,1,0),0)=0),1,0) -> 0 | E57: =MONTH(A57) -> 2 | F57: =IF(IFERROR(VLOOKUP(A57,'Planilla de control'!#REF!,1,0),0)>0,1,0) -> 0 | K57: 14 | L57: 0 | U57: 16 | V57: 5
A58: 44983 | B58: =+WEEKNUM(A58) -> 9 | C58: =+WEEKDAY(A58,2) -> 7 | D58: =IF(AND(C58>=1,C58<=5,IFERROR(VLOOKUP(A58,$H$2:$H$10,1,0),0)=0),1,0) -> 0 | E58: =MONTH(A58) -> 2 | F58: =IF(IFERROR(VLOOKUP(A58,'Planilla de control'!#REF!,1,0),0)>0,1,0) -> 0 | K58: 15 | L58: 0 | U58: 17 | V58: 5
A59: 44984 | B59: =+WEEKNUM(A59) -> 9 | C59: =+WEEKDAY(A59,2) -> 1 | D59: =IF(AND(C59>=1,C59<=5,IFERROR(VLOOKUP(A59,$H$2:$H$10,1,0),0)=0),1,0) -> 1 | E59: =MONTH(A59) -> 2 | F59: =IF(IFERROR(VLOOKUP(A59,'Planilla de control'!#REF!,1,0),0)>0,1,0) -> 0 | K59: 16 | L59: 0 | U59: 18 | V59: 0
A60: 44985 | B60: =+WEEKNUM(A60) -> 9 | C60: =+WEEKDAY(A60,2) -> 2 | D60: =IF(AND(C60>=1,C60<=5,IFERROR(VLOOKUP(A60,$H$2:$H$10,1,0),0)=0),1,0) -> 1 | E60: =MONTH(A60) -> 2 | F60: =IF(IFERROR(VLOOKUP(A60,'Planilla de control'!#REF!,1,0),0)>0,1,0) -> 0 | K60: 17 | L60: 0 | U60: 5 | V60: 20
A61: 44986 | B61: =+WEEKNUM(A61) -> 9 | C61: =+WEEKDAY(A61,2) -> 3 | D61: =IF(AND(C61>=1,C61<=5,IFERROR(VLOOKUP(A61,$H$2:$H$10,1,0),0)=0),1,0) -> 1 | E61: =MONTH(A61) -> 3 | F61: =IF(IFERROR(VLOOKUP(A61,'Planilla de control'!#REF!,1,0),0)>0,1,0) -> 0 | K61: 18 | L61: 0 | U61: 18 | V61: 4
A62: 44987 | B62: =+WEEKNUM(A62) -> 9 | C62: =+WEEKDAY(A62,2) -> 4 | D62: =IF(AND(C62>=1,C62<=5,IFERROR(VLOOKUP(A62,$H$2:$H$10,1,0),0)=0),1,0) -> 1 | E62: =MONTH(A62) -> 3 | F62: =IF(IFERROR(VLOOKUP(A62,'Planilla de control'!#REF!,1,0),0)>0,1,0) -> 0 | K62: 5 | L62: 0 | U62: 19 | V62: 5
A63: 44988 | B63: =+WEEKNUM(A63) -> 9 | C63: =+WEEKDAY(A63,2) -> 5 | D63: =IF(AND(C63>=1,C63<=5,IFERROR(VLOOKUP(A63,$H$2:$H$10,1,0),0)=0),1,0) -> 1 | E63: =MONTH(A63) -> 3 | F63: =IF(IFERROR(VLOOKUP(A63,'Planilla de control'!#REF!,1,0),0)>0,1,0) -> 0 | K63: 18 | L63: 0 | U63: 20 | V63: 5
A64: 44989 | B64: =+WEEKNUM(A64) -> 9 | C64: =+WEEKDAY(A64,2) -> 6 | D64: =IF(AND(C64>=1,C64<=5,IFERROR(VLOOKUP(A64,$H$2:$H$10,1,0),0)=0),1,0) -> 0 | E64: =MONTH(A64) -> 3 | F64: =IF(IFERROR(VLOOKUP(A64,'Planilla de control'!#REF!,1,0),0)>0,1,0) -> 0 | K64: 19 | L64: 0 | U64: 21 | V64: 3
... A78: 45003 | B78: =+WEEKNUM(A78) -> 11 | C78: =+WEEKDAY(A78,2) -> 6 | D78: =IF(AND(C78>=1,C78<=5,IFERROR(VLOOKUP(A78,$H$2:$H$10,1,0),0)=0),1,0) -> 0 | E78: =MONTH(A78) -> 3 | F78: =IF(IFERROR(VLOOKUP(A78,'Planilla de control'!#REF!,1,0),0)>0,1,0) -> 0 | K78: 29 | L78: 0 | U78: 31 | V78: 1
A79: 45004 | B79: =+WEEKNUM(A79) -> 12 | C79: =+WEEKDAY(A79,2) -> 7 | D79: =IF(AND(C79>=1,C79<=5,IFERROR(VLOOKUP(A79,$H$2:$H$10,1,0),0)=0),1,0) -> 0 | E79: =MONTH(A79) -> 3 | F79: =IF(IFERROR(VLOOKUP(A79,'Planilla de control'!#REF!,1,0),0)>0,1,0) -> 0 | K79: 30 | L79: 0 | U79: Total general | V79: 252
A80: 45005 | B80: =+WEEKNUM(A80) -> 12 | C80: =+WEEKDAY(A80,2) -> 1 | D80: =IF(AND(C80>=1,C80<=5,IFERROR(VLOOKUP(A80,$H$2:$H$10,1,0),0)=0),1,0) -> 1 | E80: =MONTH(A80) -> 3 | F80: =IF(IFERROR(VLOOKUP(A80,'Planilla de control'!#REF!,1,0),0)>0,1,0) -> 0 | K80: 31 | L80: 0
A81: 45006 | B81: =+WEEKNUM(A81) -> 12 | C81: =+WEEKDAY(A81,2) -> 2 | D81: =IF(AND(C81>=1,C81<=5,IFERROR(VLOOKUP(A81,$H$2:$H$10,1,0),0)=0),1,0) -> 1 | E81: =MONTH(A81) -> 3 | F81: =IF(IFERROR(VLOOKUP(A81,'Planilla de control'!#REF!,1,0),0)>0,1,0) -> 0 | K81: Total general | L81: 3
A82: 45007 | B82: =+WEEKNUM(A82) -> 12 | C82: =+WEEKDAY(A82,2) -> 3 | D82: =IF(AND(C82>=1,C82<=5,IFERROR(VLOOKUP(A82,$H$2:$H$10,1,0),0)=0),1,0) -> 1 | E82: =MONTH(A82) -> 3 | F82: =IF(IFERROR(VLOOKUP(A82,'Planilla de control'!#REF!,1,0),0)>0,1,0) -> 0
A83: 45008 | B83: =+WEEKNUM(A83) -> 12 | C83: =+WEEKDAY(A83,2) -> 4 | D83: =IF(AND(C83>=1,C83<=5,IFERROR(VLOOKUP(A83,$H$2:$H$10,1,0),0)=0),1,0) -> 1 | E83: =MONTH(A83) -> 3 | F83: =IF(IFERROR(VLOOKUP(A83,'Planilla de control'!#REF!,1,0),0)>0,1,0) -> 0
A84: 45009 | B84: =+WEEKNUM(A84) -> 12 | C84: =+WEEKDAY(A84,2) -> 5 | D84: =IF(AND(C84>=1,C84<=5,IFERROR(VLOOKUP(A84,$H$2:$H$10,1,0),0)=0),1,0) -> 0 | E84: =MONTH(A84) -> 3 | F84: =IF(IFERROR(VLOOKUP(A84,'Planilla de control'!#REF!,1,0),0)>0,1,0) -> 0
A85: 45010 | B85: =+WEEKNUM(A85) -> 12 | C85: =+WEEKDAY(A85,2) -> 6 | D85: =IF(AND(C85>=1,C85<=5,IFERROR(VLOOKUP(A85,$H$2:$H$10,1,0),0)=0),1,0) -> 0 | E85: =MONTH(A85) -> 3 | F85: =IF(IFERROR(VLOOKUP(A85,'Planilla de control'!#REF!,1,0),0)>0,1,0) -> 0
A86: 45011 | B86: =+WEEKNUM(A86) -> 13 | C86: =+WEEKDAY(A86,2) -> 7 | D86: =IF(AND(C86>=1,C86<=5,IFERROR(VLOOKUP(A86,$H$2:$H$10,1,0),0)=0),1,0) -> 0 | E86: =MONTH(A86) -> 3 | F86: =IF(IFERROR(VLOOKUP(A86,'Planilla de control'!#REF!,1,0),0)>0,1,0) -> 0
A87: 45012 | B87: =+WEEKNUM(A87) -> 13 | C87: =+WEEKDAY(A87,2) -> 1 | D87: =IF(AND(C87>=1,C87<=5,IFERROR(VLOOKUP(A87,$H$2:$H$10,1,0),0)=0),1,0) -> 1 | E87: =MONTH(A87) -> 3 | F87: =IF(IFERROR(VLOOKUP(A87,'Planilla de control'!#REF!,1,0),0)>0,1,0) -> 0
A88: 45013 | B88: =+WEEKNUM(A88) -> 13 | C88: =+WEEKDAY(A88,2) -> 2 | D88: =IF(AND(C88>=1,C88<=5,IFERROR(VLOOKUP(A88,$H$2:$H$10,1,0),0)=0),1,0) -> 1 | E88: =MONTH(A88) -> 3 | F88: =IF(IFERROR(VLOOKUP(A88,'Planilla de control'!#REF!,1,0),0)>0,1,0) -> 0
A89: 45014 | B89: =+WEEKNUM(A89) -> 13 | C89: =+WEEKDAY(A89,2) -> 3 | D89: =IF(AND(C89>=1,C89<=5,IFERROR(VLOOKUP(A89,$H$2:$H$10,1,0),0)=0),1,0) -> 1 | E89: =MONTH(A89) -> 3 | F89: =IF(IFERROR(VLOOKUP(A89,'Planilla de control'!#REF!,1,0),0)>0,1,0) -> 0
A90: 45015 | B90: =+WEEKNUM(A90) -> 13 | C90: =+WEEKDAY(A90,2) -> 4 | D90: =IF(AND(C90>=1,C90<=5,IFERROR(VLOOKUP(A90,$H$2:$H$10,1,0),0)=0),1,0) -> 1 | E90: =MONTH(A90) -> 3 | F90: =IF(IFERROR(VLOOKUP(A90,'Planilla de control'!#REF!,1,0),0)>0,1,0) -> 0
A91: 45016 | B91: =+WEEKNUM(A91) -> 13 | C91: =+WEEKDAY(A91,2) -> 5 | D91: =IF(AND(C91>=1,C91<=5,IFERROR(VLOOKUP(A91,$H$2:$H$10,1,0),0)=0),1,0) -> 1 | E91: =MONTH(A91) -> 3 | F91: =IF(IFERROR(VLOOKUP(A91,'Planilla de control'!#REF!,1,0),0)>0,1,0) -> 0
A92: 45017 | B92: =+WEEKNUM(A92) -> 13 | C92: =+WEEKDAY(A92,2) -> 6 | D92: =IF(AND(C92>=1,C92<=5,IFERROR(VLOOKUP(A92,$H$2:$H$10,1,0),0)=0),1,0) -> 0 | E92: =MONTH(A92) -> 4 | F92: =IF(IFERROR(VLOOKUP(A92,'Planilla de control'!#REF!,1,0),0)>0,1,0) -> 0
A93: 45018 | B93: =+WEEKNUM(A93) -> 14 | C93: =+WEEKDAY(A93,2) -> 7 | D93: =IF(AND(C93>=1,C93<=5,IFERROR(VLOOKUP(A93,$H$2:$H$10,1,0),0)=0),1,0) -> 0 | E93: =MONTH(A93) -> 4 | F93: =IF(IFERROR(VLOOKUP(A93,'Planilla de control'!#REF!,1,0),0)>0,1,0) -> 0
... A366: 45291 | B366: =+WEEKNUM(A366) -> 53 | C366: =+WEEKDAY(A366,2) -> 7 | D366: =IF(AND(C366>=1,C366<=5,IFERROR(VLOOKUP(A366,$H$2:$H$10,1,0),0)=0),1,0) -> 0 | E366: =MONTH(A366) -> 12 | F366: =IF(IFERROR(VLOOKUP(A366,'Planilla de control'!#REF!,1,0),0)>0,1,0) -> 0

Sheet TD
A3: Mes | B3: Deposito | C3: Semana | D3: Fecha control | E3: Ubicación | F3: Count of OK | G3: Count of A -Ub vacia - sap ocup | H3: Count of B -Ub ocup- sap vacía | I3: Count of C -Dif HU | J3: Count of D -Error cant | K3: corregir
A4: ENERO | B4: D3 | C4: 2 | D4: 46027 | E4: 54A1A | F4: 1 | G4: 1 | H4: 1 | I4: 1 | J4: 1 | K4: =+COUNT(F4:J4) -> 5
A5: ENERO | B5: D3 | C5: 2 | D5: 46027 | E5: 54A2A | F5: 1 | G5: 1 | H5: 1 | I5: 1 | J5: 1 | K5: =+COUNT(F5:J5) -> 5
A6: ENERO | B6: D3 | C6: 2 | D6: 46027 | E6: 54A2B | F6: 1 | G6: 1 | H6: 1 | I6: 1 | J6: 1 | K6: =+COUNT(F6:J6) -> 5
A7: ENERO | B7: D3 | C7: 2 | D7: 46027 | E7: 54B1A | F7: 1 | G7: 1 | H7: 1 | I7: 1 | J7: 1 | K7: =+COUNT(F7:J7) -> 5
A8: ENERO | B8: D3 | C8: 2 | D8: 46027 | E8: 54B2A | F8: 1 | G8: 1 | H8: 1 | I8: 1 | J8: 1 | K8: =+COUNT(F8:J8) -> 5
A9: ENERO | B9: D3 | C9: 2 | D9: 46027 | E9: 54B2B | F9: 1 | G9: 1 | H9: 1 | I9: 1 | J9: 1 | K9: =+COUNT(F9:J9) -> 5
A10: ENERO | B10: D3 | C10: 2 | D10: 46027 | E10: 54C1A | F10: 1 | G10: 1 | H10: 1 | I10: 1 | J10: 1 | K10: =+COUNT(F10:J10) -> 5
A11: ENERO | B11: D3 | C11: 2 | D11: 46027 | E11: 54C2A | F11: 1 | G11: 1 | H11: 1 | I11: 1 | J11: 1 | K11: =+COUNT(F11:J11) -> 5
A12: ENERO | B12: D3 | C12: 2 | D12: 46027 | E12: 54C2B | F12: 1 | G12: 1 | H12: 1 | I12: 1 | J12: 1 | K12: =+COUNT(F12:J12) -> 5
A13: ENERO | B13: D3 | C13: 2 | D13: 46027 | E13: 54D1A | F13: 1 | G13: 1 | H13: 1 | I13: 1 | J13: 1 | K13: =+COUNT(F13:J13) -> 5
A14: ENERO | B14: D3 | C14: 2 | D14: 46027 | E14: 54D2A | F14: 1 | G14: 1 | H14: 1 | I14: 1 | J14: 1 | K14: =+COUNT(F14:J14) -> 5
A15: ENERO | B15: D3 | C15: 2 | D15: 46027 | E15: 54D2B | F15: 1 | G15: 1 | H15: 1 | I15: 1 | J15: 1 | K15: =+COUNT(F15:J15) -> 5
... A1408: ENERO | B1408: D3 | C1408: 2 | D1408: 46031 | E1408: 57N7B | F1408: 1 | G1408: 1 | H1408: 1 | I1408: 1 | J1408: 1 | K1408: =+COUNT(F1408:J1408) -> 5
K1409: =+COUNT(F1409:J1409) -> 0
K1410: =+COUNT(F1410:J1410) -> 0
K1411: =+COUNT(F1411:J1411) -> 0
K1412: =+COUNT(F1412:J1412) -> 0
K1413: =+COUNT(F1413:J1413) -> 0
K1414: =+COUNT(F1414:J1414) -> 0
K1415: =+COUNT(F1415:J1415) -> 0
K1416: =+COUNT(F1416:J1416) -> 0
K1417: =+COUNT(F1417:J1417) -> 0
K1418: =+COUNT(F1418:J1418) -> 0
K1419: =+COUNT(F1419:J1419) -> 0
K1420: =+COUNT(F1420:J1420) -> 0
... K8202: =+COUNT(F8202:J8202) -> 0

Sheet TD errores
A1: OK | B1: (Todas)
A3: Mes | B3: Deposito | C3: Ubicación | D3: Suma de Material en otro lugar | E3: Average of Material pagado sin dar de baja | F3: Average of Error de cantidad | G3: Average of Material mal identificado | H3: Average of Material dado de baja | I3: Average of Material no confirmado
A4: (en blanco)
A5: ENERO | B5: D3 | C5: 54A1A
A6: ENERO | B6: D3 | C6: 54A2A
A7: ENERO | B7: D3 | C7: 54A2B
A8: ENERO | B8: D3 | C8: 54A3A
A9: ENERO | B9: D3 | C9: 54A3B
A10: ENERO | B10: D3 | C10: 54B1A
A11: ENERO | B11: D3 | C11: 54B2A
A12: ENERO | B12: D3 | C12: 54B2B
A13: ENERO | B13: D3 | C13: 54B3A
A14: ENERO | B14: D3 | C14: 54B3B
A15: ENERO | B15: D3 | C15: 54C1A
A16: ENERO | B16: D3 | C16: 54C2A
... A658: ENERO | B658: D3 | C658: 54D1B
A659: ENERO | B659: D3 | C659: 54D1D BIS | E659: 1
A660: ENERO | B660: D3 | C660: 54E1B
A661: ENERO | B661: D3 | C661: 54E1D BIS
A662: ENERO | B662: D3 | C662: 54F1B
A663: ENERO | B663: D3 | C663: 54F1D BIS
A664: ENERO | B664: D3 | C664: 54G1B
A665: ENERO | B665: D3 | C665: 54G1D BIS
A666: ENERO | B666: D3 | C666: 54H1B
A667: ENERO | B667: D3 | C667: 54H1D BIS
A668: ENERO | B668: D3 | C668: 54I1B
A669: ENERO | B669: D3 | C669: 54I1D BIS
A670: ENERO | B670: D3 | C670: 54J1B
A671: ENERO | B671: D3 | C671: 54J1D BIS
... A766: ENERO | B766: D3 | C766: 54B1C BIS
A767: ENERO | B767: D3 | C767: 54B1D | F767: 1
A768: ENERO | B768: D3 | C768: 54B2C
A769: ENERO | B769: D3 | C769: 54B2D
A770: ENERO | B770: D3 | C770: 54B3C
A771: ENERO | B771: D3 | C771: 54B3D
A772: ENERO | B772: D3 | C772: 54B4C
A773: ENERO | B773: D3 | C773: 54B4D
A774: ENERO | B774: D3 | C774: 54B5C
A775: ENERO | B775: D3 | C775: 54B5D
A776: ENERO | B776: D3 | C776: 54C1A BIS
A777: ENERO | B777: D3 | C777: 54C1B BIS
A778: ENERO | B778: D3 | C778: 54C1C
A779: ENERO | B779: D3 | C779: 54C1C BIS
... A1409: ENERO | B1409: D3 | C1409: 55I6B

Sheet Planilla de control
A1: Tipo almacén | B1: Ubicación | C1: Material | D1: Unidad almacén | E1: Bloqueo de entradas | F1: Stock disponible | G1: Stock a entrar | H1: OK | I1: A -Ub vacia - SAP ocup | J1: B -Ub ocup- SAP vacía | K1: C -Dif HU | L1: D -Error cant | M1: COMENTARIO / OTRO | N1: STATUS_APPSHEET
A2: 1FO | B2: 54A2A | C2: 02T409155G0R01 | D2: 09001467827484 | F2: 120 | G2: 0 | H2: X | N2: OK

Sheet PARA MIX CAMIONES
A1: Tipo almacén | B1: Ubicación | C1: Material | D1: Unidad almacén | E1: Bloqueo de entradas | F1: Stock disponible | G1: Stock a entrar | H1: Último movimiento | I1: Motivo bloqueo | J1: CONCATENAR
A2: PCA | B2: 71A1A | C2: 2T2601011P | D2: 09001467086529 | F2: 4 | G2: 0 | H2: 45972 | J2: =CONCATENATE(B2,D2) -> 71A1A09001467086529
A3: PCA | B3: 71A1B | C3: 2T2601011P | D3: 09001467086495 | F3: 4 | G3: 0 | H3: 45972 | J3: =CONCATENATE(B3,D3) -> 71A1B09001467086495
A4: PCA | B4: 71A2A | C4: 23H121333 | D4: 09001460806945 | F4: 1 | G4: 0 | H4: 45972 | J4: =CONCATENATE(B4,D4) -> 71A2A09001460806945
A5: PCA | B5: 71A2A BIS | C5: 2T2411102D | D5: 09001463582331 | F5: 1 | G5: 0 | H5: 45919 | J5: =CONCATENATE(B5,D5) -> 71A2A BIS09001463582331
A6: PCA | B6: 71A3A | C6: << vacías >> | F6: 0 | G6: 0 | J6: =CONCATENATE(B6,D6) -> 71A3A
A7: PCA | B7: 71A4A | C7: 23H121333 | D7: 09001466522721 | F7: 1 | G7: 0 | H7: 46001 | J7: =CONCATENATE(B7,D7) -> 71A4A09001466522721
A8: PCA | B8: 71A5A | C8: 23B400019C | D8: 09001462604722 | F8: 1 | G8: 0 | H8: 45952 | J8: =CONCATENATE(B8,D8) -> 71A5A09001462604722
A9: PCA | B9: 71A6A | C9: 2T2400019AD | D9: 09001461813119 | F9: 1 | G9: 0 | H9: 45881 | J9: =CONCATENATE(B9,D9) -> 71A6A09001461813119
A10: PCA | B10: 71B1A | C10: << vacías >> | F10: 0 | G10: 0 | J10: =CONCATENATE(B10,D10) -> 71B1A
A11: PCA | B11: 71B1B | C11: << vacías >> | F11: 0 | G11: 0 | J11: =CONCATENATE(B11,D11) -> 71B1B
A12: PCA | B12: 71B1C | C12: << vacías >> | F12: 0 | G12: 0 | J12: =CONCATENATE(B12,D12) -> 71B1C
A13: PCA | B13: 71B2A | C13: << vacías >> | F13: 0 | G13: 0 | J13: =CONCATENATE(B13,D13) -> 71B2A
A14: PCA | B14: 71B2A BIS | C14: 23H121333 | D14: 09001467303638 | F14: 1 | G14: 0 | H14: 46002 | J14: =CONCATENATE(B14,D14) -> 71B2A BIS09001467303638
A15: PCA | B15: 71B2A BIS | C15: 23H121333 | D15: 09001467303639 | F15: 1 | G15: 0 | H15: 46002 | J15: =CONCATENATE(B15,D15) -> 71B2A BIS09001467303639
A16: PCA | B16: 71B3A | C16: << vacías >> | F16: 0 | G16: 0 | J16: =CONCATENATE(B16,D16) -> 71B3A
A17: PCA | B17: 71B4A | C17: 2R2863631D | D17: 09001466522970 | F17: 1 | G17: 0 | H17: 45974 | J17: =CONCATENATE(B17,D17) -> 71B4A09001466522970
A18: PCA | B18: 71B5A | C18: << vacías >> | F18: 0 | G18: 0 | J18: =CONCATENATE(B18,D18) -> 71B5A
A19: PCA | B19: 71B6A | C19: << vacías >> | F19: 0 | G19: 0 | J19: =CONCATENATE(B19,D19) -> 71B6A
A20: PCA | B20: 71C1A | C20: << vacías >> | F20: 0 | G20: 0 | J20: =CONCATENATE(B20,D20) -> 71C1A
A21: PCA | B21: 71C1B | C21: << vacías >> | F21: 0 | G21: 0 | J21: =CONCATENATE(B21,D21) -> 71C1B
A22: PCA | B22: 71C1C | C22: << vacías >> | F22: 0 | G22: 0 | J22: =CONCATENATE(B22,D22) -> 71C1C
A23: PCA | B23: 71C2A | C23: 23H121333 | D23: 09001467303641 | F23: 1 | G23: 0 | H23: 46002 | J23: =CONCATENATE(B23,D23) -> 71C2A09001467303641
A24: PCA | B24: 71C2A BIS | C24: << vacías >> | F24: 0 | G24: 0 | J24: =CONCATENATE(B24,D24) -> 71C2A BIS
A25: PCA | B25: 71C3A | C25: 2RD201737 | D25: 09001467212881 | F25: 72 | G25: 0 | H25: 45976 | J25: =CONCATENATE(B25,D25) -> 71C3A09001467212881
A26: PCA | B26: 71C4A | C26: << vacías >> | F26: 0 | G26: 0 | J26: =CONCATENATE(B26,D26) -> 71C4A
A27: PCA | B27: 71C5A | C27: << vacías >> | F27: 0 | G27: 0 | J27: =CONCATENATE(B27,D27) -> 71C5A
A28: PCA | B28: 71C6A | C28: << vacías >> | F28: 0 | G28: 0 | J28: =CONCATENATE(B28,D28) -> 71C6A
A29: PCA | B29: 71D1A | C29: << vacías >> | F29: 0 | G29: 0 | J29: =CONCATENATE(B29,D29) -> 71D1A
A30: PCA | B30: 71D1B | C30: << vacías >> | F30: 0 | G30: 0 | J30: =CONCATENATE(B30,D30) -> 71D1B
A31: PCA | B31: 71D1C | C31: << vacías >> | F31: 0 | G31: 0 | J31: =CONCATENATE(B31,D31) -> 71D1C
A32: PCA | B32: 71D2A | C32: 23H121333 | D32: 09001467310649 | F32: 1 | G32: 0 | H32: 46002 | J32: =CONCATENATE(B32,D32) -> 71D2A09001467310649
A33: PCA | B33: 71D2A BIS | C33: 23H121333 | D33: 09001467310648 | F33: 1 | G33: 0 | H33: 46002 | J33: =CONCATENATE(B33,D33) -> 71D2A BIS09001467310648
A34: PCA | B34: 71D3A | C34: << vacías >> | F34: 0 | G34: 0 | J34: =CONCATENATE(B34,D34) -> 71D3A
A35: PCA | B35: 71D4A | C35: << vacías >> | F35: 0 | G35: 0 | J35: =CONCATENATE(B35,D35) -> 71D4A
A36: PCA | B36: 71D5A | C36: << vacías >> | F36: 0 | G36: 0 | J36: =CONCATENATE(B36,D36) -> 71D5A
A37: PCA | B37: 71D6A | C37: << vacías >> | F37: 0 | G37: 0 | J37: =CONCATENATE(B37,D37) -> 71D6A
A38: PCA | B38: 71E1A | C38: 23B121249F | D38: 09001466972273 | F38: 2 | G38: 0 | H38: 45954 | J38: =CONCATENATE(B38,D38) -> 71E1A09001466972273
A39: PCA | B39: 71E1B | C39: 23B121249F | D39: 09001467091496 | F39: 2 | G39: 0 | H39: 45978 | J39: =CONCATENATE(B39,D39) -> 71E1B09001467091496
A40: PCA | B40: 71E2A | C40: << vacías >> | F40: 0 | G40: 0 | J40: =CONCATENATE(B40,D40) -> 71E2A
A41: PCA | B41: 71E2B | C41: 23B121249F | D41: 09001467091495 | F41: 2 | G41: 0 | H41: 45973 | J41: =CONCATENATE(B41,D41) -> 71E2B09001467091495
A42: PCA | B42: 71E3A | C42: 23B121249F | D42: 09001467091493 | F42: 2 | G42: 0 | H42: 45973 | J42: =CONCATENATE(B42,D42) -> 71E3A09001467091493
A43: PCA | B43: 71E3B | C43: << vacías >> | F43: 0 | G43: 0 | J43: =CONCATENATE(B43,D43) -> 71E3B
A44: PCA | B44: 71E4A | C44: << vacías >> | F44: 0 | G44: 0 | J44: =CONCATENATE(B44,D44) -> 71E4A
A45: PCA | B45: 71E4B | C45: << vacías >> | F45: 0 | G45: 0 | J45: =CONCATENATE(B45,D45) -> 71E4B
A46: PCA | B46: 71E5A | C46: << vacías >> | F46: 0 | G46: 0 | J46: =CONCATENATE(B46,D46) -> 71E5A
A47: PCA | B47: 71E5B | C47: << vacías >> | F47: 0 | G47: 0 | J47: =CONCATENATE(B47,D47) -> 71E5B
A48: PCA | B48: 71E6A | C48: << vacías >> | F48: 0 | G48: 0 | J48: =CONCATENATE(B48,D48) -> 71E6A
A49: PCA | B49: 71E6B | C49: << vacías >> | F49: 0 | G49: 0 | J49: =CONCATENATE(B49,D49) -> 71E6B
A50: PCA | B50: 71E7A | C50: 23B121249F | D50: 09001466972272 | F50: 2 | G50: 0 | H50: 45954 | J50: =CONCATENATE(B50,D50) -> 71E7A09001466972272
A51: PCA | B51: 71E7B | C51: << vacías >> | F51: 0 | G51: 0 | J51: =CONCATENATE(B51,D51) -> 71E7B
A52: PCA | B52: 71E8A | C52: << vacías >> | F52: 0 | G52: 0 | J52: =CONCATENATE(B52,D52) -> 71E8A
A53: PCA | B53: 71E8B | C53: << vacías >> | F53: 0 | G53: 0 | J53: =CONCATENATE(B53,D53) -> 71E8B
A54: PCA | B54: 71F1A | C54: << vacías >> | F54: 0 | G54: 0 | J54: =CONCATENATE(B54,D54) -> 71F1A
A55: PCA | B55: 71F1B | C55: << vacías >> | F55: 0 | G55: 0 | J55: =CONCATENATE(B55,D55) -> 71F1B
A56: PCA | B56: 71F1C | C56: << vacías >> | F56: 0 | G56: 0 | J56: =CONCATENATE(B56,D56) -> 71F1C
A57: PCA | B57: 71F2A | C57: 23B121481 | D57: 09001466978533 | F57: 1 | G57: 0 | H57: 45957 | J57: =CONCATENATE(B57,D57) -> 71F2A09001466978533
A58: PCA | B58: 71F2A BIS | C58: 23B121481 | D58: 09001466978532 | F58: 1 | G58: 0 | H58: 45957 | J58: =CONCATENATE(B58,D58) -> 71F2A BIS09001466978532
A59: PCA | B59: 71F3A | C59: 23B100009K | D59: 09001466982016 | F59: 1 | G59: 0 | H59: 45952 | J59: =CONCATENATE(B59,D59) -> 71F3A09001466982016
A60: PCA | B60: 71F4A | C60: << vacías >> | F60: 0 | G60: 0 | J60: =CONCATENATE(B60,D60) -> 71F4A
A61: PCA | B61: 71F5A | C61: << vacías >> | F61: 0 | G61: 0 | J61: =CONCATENATE(B61,D61) -> 71F5A
A62: PCA | B62: 71F6A | C62: << vacías >> | F62: 0 | G62: 0 | J62: =CONCATENATE(B62,D62) -> 71F6A
A63: PCA | B63: 71G1A | C63: << vacías >> | F63: 0 | G63: 0 | J63: =CONCATENATE(B63,D63) -> 71G1A
A64: PCA | B64: 71G1B | C64: << vacías >> | F64: 0 | G64: 0 | J64: =CONCATENATE(B64,D64) -> 71G1B
A65: PCA | B65: 71G1C | C65: << vacías >> | F65: 0 | G65: 0 | J65: =CONCATENATE(B65,D65) -> 71G1C
A66: PCA | B66: 71G2A | C66: 23H121333 | D66: 09001467323487 | F66: 1 | G66: 0 | H66: 46000 | J66: =CONCATENATE(B66,D66) -> 71G2A09001467323487
A67: PCA | B67: 71G2A BIS | C67: << vacías >> | F67: 0 | G67: 0 | J67: =CONCATENATE(B67,D67) -> 71G2A BIS
A68: PCA | B68: 71G3A | C68: 23B100009K | D68: 09001466978519 | F68: 1 | G68: 0 | H68: 45957 | J68: =CONCATENATE(B68,D68) -> 71G3A09001466978519
A69: PCA | B69: 71G4A | C69: << vacías >> | F69: 0 | G69: 0 | J69: =CONCATENATE(B69,D69) -> 71G4A
A70: PCA | B70: 71G5A | C70: << vacías >> | F70: 0 | G70: 0 | J70: =CONCATENATE(B70,D70) -> 71G5A
A71: PCA | B71: 71G6A | C71: << vacías >> | F71: 0 | G71: 0 | J71: =CONCATENATE(B71,D71) -> 71G6A
A72: PCA | B72: 71H1A | C72: << vacías >> | F72: 0 | G72: 0 | J72: =CONCATENATE(B72,D72) -> 71H1A
A73: PCA | B73: 71H1B | C73: << vacías >> | F73: 0 | G73: 0 | J73: =CONCATENATE(B73,D73) -> 71H1B
A74: PCA | B74: 71H1C | C74: << vacías >> | F74: 0 | G74: 0 | J74: =CONCATENATE(B74,D74) -> 71H1C
A75: PCA | B75: 71H2A | C75: 23H121333 | D75: 09001467323485 | F75: 1 | G75: 0 | H75: 46000 | J75: =CONCATENATE(B75,D75) -> 71H2A09001467323485
A76: PCA | B76: 71H2A BIS | C76: 23H121333 | D76: 09001467323486 | F76: 1 | G76: 0 | H76: 46000 | J76: =CONCATENATE(B76,D76) -> 71H2A BIS09001467323486
A77: PCA | B77: 71H3A | C77: << vacías >> | F77: 0 | G77: 0 | J77: =CONCATENATE(B77,D77) -> 71H3A
A78: PCA | B78: 71H4A | C78: << vacías >> | F78: 0 | G78: 0 | J78: =CONCATENATE(B78,D78) -> 71H4A
A79: PCA | B79: 71H5A | C79: << vacías >> | F79: 0 | G79: 0 | J79: =CONCATENATE(B79,D79) -> 71H5A
A80: PCA | B80: 71H6A | C80: << vacías >> | F80: 0 | G80: 0 | J80: =CONCATENATE(B80,D80) -> 71H6A
A81: PCA | B81: 72A1A | C81: 23B131131 | D81: 09001460805919 | F81: 624 | G81: 0 | H81: 45959 | J81: =CONCATENATE(B81,D81) -> 72A1A09001460805919
A82: PCA | B82: 72A1A BIS | C82: 23B201136B | D82: 09001466287102 | F82: 24 | G82: 0 | H82: 45976 | J82: =CONCATENATE(B82,D82) -> 72A1A BIS09001466287102
A83: PCA | B83: 72A1B | C83: 07W145287 | D83: 09001462389229 | F83: 9 | G83: 0 | H83: 45951 | J83: =CONCATENATE(B83,D83) -> 72A1B09001462389229
A84: PCA | B84: 72A1B BIS | C84: 2376119871 | D84: 09001465707515 | F84: 180 | G84: 0 | H84: 46001 | J84: =CONCATENATE(B84,D84) -> 72A1B BIS09001465707515
A85: PCA | B85: 72A2A | C85: 22B201100 | D85: 09001463556149 | F85: 50 | G85: 0 | H85: 45951 | J85: =CONCATENATE(B85,D85) -> 72A2A09001463556149
A86: PCA | B86: 72A2A BIS | C86: 2376119871 | D86: 09001462273803 | F86: 172 | G86: 0 | H86: 45951 | J86: =CONCATENATE(B86,D86) -> 72A2A BIS09001462273803
A87: PCA | B87: 72A2B | C87: 2R2803875C | D87: 09001461825140 | F87: 383 | G87: 0 | H87: 45952 | J87: =CONCATENATE(B87,D87) -> 72A2B09001461825140
A88: PCA | B88: 72A2B BIS | C88: 07W145287 | D88: 09001465886270 | F88: 5 | G88: 0 | H88: 45952 | J88: =CONCATENATE(B88,D88) -> 72A2B BIS09001465886270
A89: PCA | B89: 72A3A | C89: 2R2863631D | D89: 09001461336020 | F89: 1 | G89: 0 | H89: 45972 | J89: =CONCATENATE(B89,D89) -> 72A3A09001461336020
A90: PCA | B90: 72A3B | C90: 2RD201735 | D90: 09001467241215 | F90: 260 | G90: 0 | H90: 45976 | J90: =CONCATENATE(B90,D90) -> 72A3B09001467241215
A91: PCA | B91: 72A3B BIS | C91: << vacías >> | F91: 0 | G91: 0 | J91: =CONCATENATE(B91,D91) -> 72A3B BIS
A92: PCA | B92: 72A4A | C92: << vacías >> | F92: 0 | G92: 0 | J92: =CONCATENATE(B92,D92) -> 72A4A
A93: PCA | B93: 72A4B | C93: << vacías >> | F93: 0 | G93: 0 | J93: =CONCATENATE(B93,D93) -> 72A4B
A94: PCA | B94: 72A5A | C94: 22B201512B | D94: 09001466522974 | F94: 1 | G94: 0 | H94: 46000 | J94: =CONCATENATE(B94,D94) -> 72A5A09001466522974
A95: PCA | B95: 72A5B | C95: 22B201512B | D95: 09001460806934 | F95: 1 | G95: 0 | H95: 46000 | J95: =CONCATENATE(B95,D95) -> 72A5B09001460806934
A96: PCA | B96: 72A6A | C96: << vacías >> | F96: 0 | G96: 0 | J96: =CONCATENATE(B96,D96) -> 72A6A
A97: PCA | B97: 72A6B | C97: << vacías >> | F97: 0 | G97: 0 | J97: =CONCATENATE(B97,D97) -> 72A6B
A98: PCA | B98: 72A7A | C98: 2T2121251F | D98: 09001467084213 | F98: 1 | G98: 0 | H98: 45958 | J98: =CONCATENATE(B98,D98) -> 72A7A09001467084213
A99: PCA | B99: 72A7B | C99: 1J0121321B | D99: 09001466522722 | F99: 1 | G99: 0 | H99: 45972 | J99: =CONCATENATE(B99,D99) -> 72A7B09001466522722
A100: PCA | B100: 72A8A | C100: << vacías >> | F100: 0 | G100: 0 | J100: =CONCATENATE(B100,D100) -> 72A8A
...

Sheet Hoja2
A1: 21A1B
A2: 21A1C
A3: 21I1A
A4: 21I2A
A5: 22D3A
A6: 22I1C
A7: 23A1B
A8: 23C2C
A9: 23E2C
A10: 23H2C
A11: 23H3C
A12: 23I1C
... A42: 04L3C

Sheet Ub inicio 
O1: PC2 | P1: RAB | Q1: PC5 | R1: 1FO | S1: 1CT | T1: PCD | U1: RDU
A2: Tipo almacén | B2: Ubicación | C2: Bloqueo de salidas | D2: Bloqueo de entradas | E2: Motivo bloqueo | F2: calle, modulo y nivel | G2: Nivel | H2: Calle | I2: Alveolo | J2: Deposito | L2: FECHA | M2: AUDITADO | O2: MQ200 | P2: MQ200 | Q2: MQ250 | R2: D3 | S2: D4 | T2: DUCATI | U2: DUCATI
A3: PC2 | B3: 01I6B | F3: =IF(OR(LEN(B3)=9,LEN(B3)=5),MID(B3,1,4),MID(B3,1,5)) -> 01I6 | G3: =IF(MID(F3,5,1)<>"",MID(F3,4,2),MID(F3,4,1))*1 -> 6 | H3: =+MID(B3,1,2)*1 -> 1 | I3: =+MID(B3,3,1) -> I | J3: =HLOOKUP(A3,$O$1:$U$2,2,0) -> MQ200 | K3: =CONCATENATE(A3,B3) -> PC201I6B | L3: =VLOOKUP(K3,'Planilla de control'!#REF!,2,0) -> #REF! | M3: =IF(COUNTIF('Planilla de control'!#REF!,K3)>0,"SI","NO") -> #REF! | P3: =COUNTIF($J:$J,P2) -> 2334 | Q3: =COUNTIF($J:$J,Q2) -> 1594 | R3: =COUNTIF($J:$J,R2) -> 2658 | S3: =COUNTIF($J:$J,S2) -> 278 | T3: =COUNTIF($J:$J,T2) -> 536
A4: PC2 | B4: 01I6C | F4: =IF(OR(LEN(B4)=9,LEN(B4)=5),MID(B4,1,4),MID(B4,1,5)) -> 01I6 | G4: =IF(MID(F4,5,1)<>"",MID(F4,4,2),MID(F4,4,1))*1 -> 6 | H4: =+MID(B4,1,2)*1 -> 1 | I4: =+MID(B4,3,1) -> I | J4: =HLOOKUP(A4,$O$1:$U$2,2,0) -> MQ200 | K4: =CONCATENATE(A4,B4) -> PC201I6C | L4: =VLOOKUP(K4,'Planilla de control'!#REF!,2,0) -> #REF! | M4: =IF(COUNTIF('Planilla de control'!#REF!,K4)>0,"SI","NO") -> #REF! | P4: 2334 | Q4: 2241 | R4: 2659 | S4: 266 | T4: 0
A5: PC2 | B5: 01J1A BIS | F5: =IF(OR(LEN(B5)=9,LEN(B5)=5),MID(B5,1,4),MID(B5,1,5)) -> 01J1 | G5: =IF(MID(F5,5,1)<>"",MID(F5,4,2),MID(F5,4,1))*1 -> 1 | H5: =+MID(B5,1,2)*1 -> 1 | I5: =+MID(B5,3,1) -> J | J5: =HLOOKUP(A5,$O$1:$U$2,2,0) -> MQ200 | K5: =CONCATENATE(A5,B5) -> PC201J1A BIS | L5: =VLOOKUP(K5,'Planilla de control'!#REF!,2,0) -> #REF! | M5: =IF(COUNTIF('Planilla de control'!#REF!,K5)>0,"SI","NO") -> #REF!
A6: PC2 | B6: 01J1B BIS | F6: =IF(OR(LEN(B6)=9,LEN(B6)=5),MID(B6,1,4),MID(B6,1,5)) -> 01J1 | G6: =IF(MID(F6,5,1)<>"",MID(F6,4,2),MID(F6,4,1))*1 -> 1 | H6: =+MID(B6,1,2)*1 -> 1 | I6: =+MID(B6,3,1) -> J | J6: =HLOOKUP(A6,$O$1:$U$2,2,0) -> MQ200 | K6: =CONCATENATE(A6,B6) -> PC201J1B BIS | L6: =VLOOKUP(K6,'Planilla de control'!#REF!,2,0) -> #REF! | M6: =IF(COUNTIF('Planilla de control'!#REF!,K6)>0,"SI","NO") -> #REF!
A7: PC2 | B7: 01J2A BIS | F7: =IF(OR(LEN(B7)=9,LEN(B7)=5),MID(B7,1,4),MID(B7,1,5)) -> 01J2 | G7: =IF(MID(F7,5,1)<>"",MID(F7,4,2),MID(F7,4,1))*1 -> 2 | H7: =+MID(B7,1,2)*1 -> 1 | I7: =+MID(B7,3,1) -> J | J7: =HLOOKUP(A7,$O$1:$U$2,2,0) -> MQ200 | K7: =CONCATENATE(A7,B7) -> PC201J2A BIS | L7: =VLOOKUP(K7,'Planilla de control'!#REF!,2,0) -> #REF! | M7: =IF(COUNTIF('Planilla de control'!#REF!,K7)>0,"SI","NO") -> #REF!
A8: PC2 | B8: 01J2B | F8: =IF(OR(LEN(B8)=9,LEN(B8)=5),MID(B8,1,4),MID(B8,1,5)) -> 01J2 | G8: =IF(MID(F8,5,1)<>"",MID(F8,4,2),MID(F8,4,1))*1 -> 2 | H8: =+MID(B8,1,2)*1 -> 1 | I8: =+MID(B8,3,1) -> J | J8: =HLOOKUP(A8,$O$1:$U$2,2,0) -> MQ200 | K8: =CONCATENATE(A8,B8) -> PC201J2B | L8: =VLOOKUP(K8,'Planilla de control'!#REF!,2,0) -> #REF! | M8: =IF(COUNTIF('Planilla de control'!#REF!,K8)>0,"SI","NO") -> #REF!
A9: PC2 | B9: 01J2B BIS | F9: =IF(OR(LEN(B9)=9,LEN(B9)=5),MID(B9,1,4),MID(B9,1,5)) -> 01J2 | G9: =IF(MID(F9,5,1)<>"",MID(F9,4,2),MID(F9,4,1))*1 -> 2 | H9: =+MID(B9,1,2)*1 -> 1 | I9: =+MID(B9,3,1) -> J | J9: =HLOOKUP(A9,$O$1:$U$2,2,0) -> MQ200 | K9: =CONCATENATE(A9,B9) -> PC201J2B BIS | L9: =VLOOKUP(K9,'Planilla de control'!#REF!,2,0) -> #REF! | M9: =IF(COUNTIF('Planilla de control'!#REF!,K9)>0,"SI","NO") -> #REF!
A10: PC2 | B10: 01K1A BIS | F10: =IF(OR(LEN(B10)=9,LEN(B10)=5),MID(B10,1,4),MID(B10,1,5)) -> 01K1 | G10: =IF(MID(F10,5,1)<>"",MID(F10,4,2),MID(F10,4,1))*1 -> 1 | H10: =+MID(B10,1,2)*1 -> 1 | I10: =+MID(B10,3,1) -> K | J10: =HLOOKUP(A10,$O$1:$U$2,2,0) -> MQ200 | K10: =CONCATENATE(A10,B10) -> PC201K1A BIS | L10: =VLOOKUP(K10,'Planilla de control'!#REF!,2,0) -> #REF! | M10: =IF(COUNTIF('Planilla de control'!#REF!,K10)>0,"SI","NO") -> #REF!
A11: PC2 | B11: 01K1B BIS | F11: =IF(OR(LEN(B11)=9,LEN(B11)=5),MID(B11,1,4),MID(B11,1,5)) -> 01K1 | G11: =IF(MID(F11,5,1)<>"",MID(F11,4,2),MID(F11,4,1))*1 -> 1 | H11: =+MID(B11,1,2)*1 -> 1 | I11: =+MID(B11,3,1) -> K | J11: =HLOOKUP(A11,$O$1:$U$2,2,0) -> MQ200 | K11: =CONCATENATE(A11,B11) -> PC201K1B BIS | L11: =VLOOKUP(K11,'Planilla de control'!#REF!,2,0) -> #REF! | M11: =IF(COUNTIF('Planilla de control'!#REF!,K11)>0,"SI","NO") -> #REF!
A12: PC2 | B12: 01K1C BIS | F12: =IF(OR(LEN(B12)=9,LEN(B12)=5),MID(B12,1,4),MID(B12,1,5)) -> 01K1 | G12: =IF(MID(F12,5,1)<>"",MID(F12,4,2),MID(F12,4,1))*1 -> 1 | H12: =+MID(B12,1,2)*1 -> 1 | I12: =+MID(B12,3,1) -> K | J12: =HLOOKUP(A12,$O$1:$U$2,2,0) -> MQ200 | K12: =CONCATENATE(A12,B12) -> PC201K1C BIS | L12: =VLOOKUP(K12,'Planilla de control'!#REF!,2,0) -> #REF! | M12: =IF(COUNTIF('Planilla de control'!#REF!,K12)>0,"SI","NO") -> #REF!
A13: PC2 | B13: 01K2A BIS | F13: =IF(OR(LEN(B13)=9,LEN(B13)=5),MID(B13,1,4),MID(B13,1,5)) -> 01K2 | G13: =IF(MID(F13,5,1)<>"",MID(F13,4,2),MID(F13,4,1))*1 -> 2 | H13: =+MID(B13,1,2)*1 -> 1 | I13: =+MID(B13,3,1) -> K | J13: =HLOOKUP(A13,$O$1:$U$2,2,0) -> MQ200 | K13: =CONCATENATE(A13,B13) -> PC201K2A BIS | L13: =VLOOKUP(K13,'Planilla de control'!#REF!,2,0) -> #REF! | M13: =IF(COUNTIF('Planilla de control'!#REF!,K13)>0,"SI","NO") -> #REF!
A14: PC2 | B14: 01K2B BIS | F14: =IF(OR(LEN(B14)=9,LEN(B14)=5),MID(B14,1,4),MID(B14,1,5)) -> 01K2 | G14: =IF(MID(F14,5,1)<>"",MID(F14,4,2),MID(F14,4,1))*1 -> 2 | H14: =+MID(B14,1,2)*1 -> 1 | I14: =+MID(B14,3,1) -> K | J14: =HLOOKUP(A14,$O$1:$U$2,2,0) -> MQ200 | K14: =CONCATENATE(A14,B14) -> PC201K2B BIS | L14: =VLOOKUP(K14,'Planilla de control'!#REF!,2,0) -> #REF! | M14: =IF(COUNTIF('Planilla de control'!#REF!,K14)>0,"SI","NO") -> #REF!
A15: PC2 | B15: 01K2C | F15: =IF(OR(LEN(B15)=9,LEN(B15)=5),MID(B15,1,4),MID(B15,1,5)) -> 01K2 | G15: =IF(MID(F15,5,1)<>"",MID(F15,4,2),MID(F15,4,1))*1 -> 2 | H15: =+MID(B15,1,2)*1 -> 1 | I15: =+MID(B15,3,1) -> K | J15: =HLOOKUP(A15,$O$1:$U$2,2,0) -> MQ200 | K15: =CONCATENATE(A15,B15) -> PC201K2C | L15: =VLOOKUP(K15,'Planilla de control'!#REF!,2,0) -> #REF! | M15: =IF(COUNTIF('Planilla de control'!#REF!,K15)>0,"SI","NO") -> #REF!
A16: PC2 | B16: 01K2C BIS | F16: =IF(OR(LEN(B16)=9,LEN(B16)=5),MID(B16,1,4),MID(B16,1,5)) -> 01K2 | G16: =IF(MID(F16,5,1)<>"",MID(F16,4,2),MID(F16,4,1))*1 -> 2 | H16: =+MID(B16,1,2)*1 -> 1 | I16: =+MID(B16,3,1) -> K | J16: =HLOOKUP(A16,$O$1:$U$2,2,0) -> MQ200 | K16: =CONCATENATE(A16,B16) -> PC201K2C BIS | L16: =VLOOKUP(K16,'Planilla de control'!#REF!,2,0) -> #REF! | M16: =IF(COUNTIF('Planilla de control'!#REF!,K16)>0,"SI","NO") -> #REF!
... A173: PC2 | B173: 02L1A | F173: =IF(OR(LEN(B173)=9,LEN(B173)=5),MID(B173,1,4),MID(B173,1,5)) -> 02L1 | G173: =IF(MID(F173,5,1)<>"",MID(F173,4,2),MID(F173,4,1))*1 -> 1 | H173: =+MID(B173,1,2)*1 -> 2 | I173: =+MID(B173,3,1) -> L | J173: =HLOOKUP(A173,$O$1:$U$2,2,0) -> MQ200 | K173: =CONCATENATE(A173,B173) -> PC202L1A | L173: =VLOOKUP(K173,'Planilla de control'!#REF!,2,0) -> #REF! | M173: =IF(COUNTIF('Planilla de control'!#REF!,K173)>0,"SI","NO") -> #REF!
A174: RAB | B174: 02A2A | E174: T | F174: =IF(OR(LEN(B174)=9,LEN(B174)=5),MID(B174,1,4),MID(B174,1,5)) -> 02A2 | G174: =IF(MID(F174,5,1)<>"",MID(F174,4,2),MID(F174,4,1))*1 -> 2 | H174: =+MID(B174,1,2)*1 -> 2 | I174: =+MID(B174,3,1) -> A | J174: =HLOOKUP(A174,$O$1:$U$2,2,0) -> MQ200 | K174: =CONCATENATE(A174,B174) -> RAB02A2A | L174: =VLOOKUP(K174,'Planilla de control'!#REF!,2,0) -> #REF! | M174: =IF(COUNTIF('Planilla de control'!#REF!,K174)>0,"SI","NO") -> #REF!
A175: RAB | B175: 02A2B | E175: T | F175: =IF(OR(LEN(B175)=9,LEN(B175)=5),MID(B175,1,4),MID(B175,1,5)) -> 02A2 | G175: =IF(MID(F175,5,1)<>"",MID(F175,4,2),MID(F175,4,1))*1 -> 2 | H175: =+MID(B175,1,2)*1 -> 2 | I175: =+MID(B175,3,1) -> A | J175: =HLOOKUP(A175,$O$1:$U$2,2,0) -> MQ200 | K175: =CONCATENATE(A175,B175) -> RAB02A2B | L175: =VLOOKUP(K175,'Planilla de control'!#REF!,2,0) -> #REF! | M175: =IF(COUNTIF('Planilla de control'!#REF!,K175)>0,"SI","NO") -> #REF!
A176: RAB | B176: 02A2C | E176: T | F176: =IF(OR(LEN(B176)=9,LEN(B176)=5),MID(B176,1,4),MID(B176,1,5)) -> 02A2 | G176: =IF(MID(F176,5,1)<>"",MID(F176,4,2),MID(F176,4,1))*1 -> 2 | H176: =+MID(B176,1,2)*1 -> 2 | I176: =+MID(B176,3,1) -> A | J176: =HLOOKUP(A176,$O$1:$U$2,2,0) -> MQ200 | K176: =CONCATENATE(A176,B176) -> RAB02A2C | L176: =VLOOKUP(K176,'Planilla de control'!#REF!,2,0) -> #REF! | M176: =IF(COUNTIF('Planilla de control'!#REF!,K176)>0,"SI","NO") -> #REF!
A177: RAB | B177: 02A3A | E177: T | F177: =IF(OR(LEN(B177)=9,LEN(B177)=5),MID(B177,1,4),MID(B177,1,5)) -> 02A3 | G177: =IF(MID(F177,5,1)<>"",MID(F177,4,2),MID(F177,4,1))*1 -> 3 | H177: =+MID(B177,1,2)*1 -> 2 | I177: =+MID(B177,3,1) -> A | J177: =HLOOKUP(A177,$O$1:$U$2,2,0) -> MQ200 | K177: =CONCATENATE(A177,B177) -> RAB02A3A | L177: =VLOOKUP(K177,'Planilla de control'!#REF!,2,0) -> #REF! | M177: =IF(COUNTIF('Planilla de control'!#REF!,K177)>0,"SI","NO") -> #REF!
A178: RAB | B178: 02A3B | E178: T | F178: =IF(OR(LEN(B178)=9,LEN(B178)=5),MID(B178,1,4),MID(B178,1,5)) -> 02A3 | G178: =IF(MID(F178,5,1)<>"",MID(F178,4,2),MID(F178,4,1))*1 -> 3 | H178: =+MID(B178,1,2)*1 -> 2 | I178: =+MID(B178,3,1) -> A | J178: =HLOOKUP(A178,$O$1:$U$2,2,0) -> MQ200 | K178: =CONCATENATE(A178,B178) -> RAB02A3B | L178: =VLOOKUP(K178,'Planilla de control'!#REF!,2,0) -> #REF! | M178: =IF(COUNTIF('Planilla de control'!#REF!,K178)>0,"SI","NO") -> #REF!
A179: RAB | B179: 02A4A | E179: T | F179: =IF(OR(LEN(B179)=9,LEN(B179)=5),MID(B179,1,4),MID(B179,1,5)) -> 02A4 | G179: =IF(MID(F179,5,1)<>"",MID(F179,4,2),MID(F179,4,1))*1 -> 4 | H179: =+MID(B179,1,2)*1 -> 2 | I179: =+MID(B179,3,1) -> A | J179: =HLOOKUP(A179,$O$1:$U$2,2,0) -> MQ200 | K179: =CONCATENATE(A179,B179) -> RAB02A4A | L179: =VLOOKUP(K179,'Planilla de control'!#REF!,2,0) -> #REF! | M179: =IF(COUNTIF('Planilla de control'!#REF!,K179)>0,"SI","NO") -> #REF!
A180: RAB | B180: 02A4B | E180: T | F180: =IF(OR(LEN(B180)=9,LEN(B180)=5),MID(B180,1,4),MID(B180,1,5)) -> 02A4 | G180: =IF(MID(F180,5,1)<>"",MID(F180,4,2),MID(F180,4,1))*1 -> 4 | H180: =+MID(B180,1,2)*1 -> 2 | I180: =+MID(B180,3,1) -> A | J180: =HLOOKUP(A180,$O$1:$U$2,2,0) -> MQ200 | K180: =CONCATENATE(A180,B180) -> RAB02A4B | L180: =VLOOKUP(K180,'Planilla de control'!#REF!,2,0) -> #REF! | M180: =IF(COUNTIF('Planilla de control'!#REF!,K180)>0,"SI","NO") -> #REF!
A181: RAB | B181: 02A4C | E181: T | F181: =IF(OR(LEN(B181)=9,LEN(B181)=5),MID(B181,1,4),MID(B181,1,5)) -> 02A4 | G181: =IF(MID(F181,5,1)<>"",MID(F181,4,2),MID(F181,4,1))*1 -> 4 | H181: =+MID(B181,1,2)*1 -> 2 | I181: =+MID(B181,3,1) -> A | J181: =HLOOKUP(A181,$O$1:$U$2,2,0) -> MQ200 | K181: =CONCATENATE(A181,B181) -> RAB02A4C | L181: =VLOOKUP(K181,'Planilla de control'!#REF!,2,0) -> #REF! | M181: =IF(COUNTIF('Planilla de control'!#REF!,K181)>0,"SI","NO") -> #REF!
A182: RAB | B182: 02A5A | E182: T | F182: =IF(OR(LEN(B182)=9,LEN(B182)=5),MID(B182,1,4),MID(B182,1,5)) -> 02A5 | G182: =IF(MID(F182,5,1)<>"",MID(F182,4,2),MID(F182,4,1))*1 -> 5 | H182: =+MID(B182,1,2)*1 -> 2 | I182: =+MID(B182,3,1) -> A | J182: =HLOOKUP(A182,$O$1:$U$2,2,0) -> MQ200 | K182: =CONCATENATE(A182,B182) -> RAB02A5A | L182: =VLOOKUP(K182,'Planilla de control'!#REF!,2,0) -> #REF! | M182: =IF(COUNTIF('Planilla de control'!#REF!,K182)>0,"SI","NO") -> #REF!
A183: RAB | B183: 02A5B | E183: T | F183: =IF(OR(LEN(B183)=9,LEN(B183)=5),MID(B183,1,4),MID(B183,1,5)) -> 02A5 | G183: =IF(MID(F183,5,1)<>"",MID(F183,4,2),MID(F183,4,1))*1 -> 5 | H183: =+MID(B183,1,2)*1 -> 2 | I183: =+MID(B183,3,1) -> A | J183: =HLOOKUP(A183,$O$1:$U$2,2,0) -> MQ200 | K183: =CONCATENATE(A183,B183) -> RAB02A5B | L183: =VLOOKUP(K183,'Planilla de control'!#REF!,2,0) -> #REF! | M183: =IF(COUNTIF('Planilla de control'!#REF!,K183)>0,"SI","NO") -> #REF!
A184: RAB | B184: 02A5C | E184: T | F184: =IF(OR(LEN(B184)=9,LEN(B184)=5),MID(B184,1,4),MID(B184,1,5)) -> 02A5 | G184: =IF(MID(F184,5,1)<>"",MID(F184,4,2),MID(F184,4,1))*1 -> 5 | H184: =+MID(B184,1,2)*1 -> 2 | I184: =+MID(B184,3,1) -> A | J184: =HLOOKUP(A184,$O$1:$U$2,2,0) -> MQ200 | K184: =CONCATENATE(A184,B184) -> RAB02A5C | L184: =VLOOKUP(K184,'Planilla de control'!#REF!,2,0) -> #REF! | M184: =IF(COUNTIF('Planilla de control'!#REF!,K184)>0,"SI","NO") -> #REF!
A185: RAB | B185: 02A6A | E185: T | F185: =IF(OR(LEN(B185)=9,LEN(B185)=5),MID(B185,1,4),MID(B185,1,5)) -> 02A6 | G185: =IF(MID(F185,5,1)<>"",MID(F185,4,2),MID(F185,4,1))*1 -> 6 | H185: =+MID(B185,1,2)*1 -> 2 | I185: =+MID(B185,3,1) -> A | J185: =HLOOKUP(A185,$O$1:$U$2,2,0) -> MQ200 | K185: =CONCATENATE(A185,B185) -> RAB02A6A | L185: =VLOOKUP(K185,'Planilla de control'!#REF!,2,0) -> #REF! | M185: =IF(COUNTIF('Planilla de control'!#REF!,K185)>0,"SI","NO") -> #REF!
... A211: RAB | B211: 02B8C | E211: T | F211: =IF(OR(LEN(B211)=9,LEN(B211)=5),MID(B211,1,4),MID(B211,1,5)) -> 02B8 | G211: =IF(MID(F211,5,1)<>"",MID(F211,4,2),MID(F211,4,1))*1 -> 8 | H211: =+MID(B211,1,2)*1 -> 2 | I211: =+MID(B211,3,1) -> B | J211: =HLOOKUP(A211,$O$1:$U$2,2,0) -> MQ200 | K211: =CONCATENATE(A211,B211) -> RAB02B8C | L211: =VLOOKUP(K211,'Planilla de control'!#REF!,2,0) -> #REF! | M211: =IF(COUNTIF('Planilla de control'!#REF!,K211)>0,"SI","NO") -> #REF!
A212: RAB | B212: 02C4A | F212: =IF(OR(LEN(B212)=9,LEN(B212)=5),MID(B212,1,4),MID(B212,1,5)) -> 02C4 | G212: =IF(MID(F212,5,1)<>"",MID(F212,4,2),MID(F212,4,1))*1 -> 4 | H212: =+MID(B212,1,2)*1 -> 2 | I212: =+MID(B212,3,1) -> C | J212: =HLOOKUP(A212,$O$1:$U$2,2,0) -> MQ200 | K212: =CONCATENATE(A212,B212) -> RAB02C4A | L212: =VLOOKUP(K212,'Planilla de control'!#REF!,2,0) -> #REF! | M212: =IF(COUNTIF('Planilla de control'!#REF!,K212)>0,"SI","NO") -> #REF!
A213: RAB | B213: 02C4C | F213: =IF(OR(LEN(B213)=9,LEN(B213)=5),MID(B213,1,4),MID(B213,1,5)) -> 02C4 | G213: =IF(MID(F213,5,1)<>"",MID(F213,4,2),MID(F213,4,1))*1 -> 4 | H213: =+MID(B213,1,2)*1 -> 2 | I213: =+MID(B213,3,1) -> C | J213: =HLOOKUP(A213,$O$1:$U$2,2,0) -> MQ200 | K213: =CONCATENATE(A213,B213) -> RAB02C4C | L213: =VLOOKUP(K213,'Planilla de control'!#REF!,2,0) -> #REF! | M213: =IF(COUNTIF('Planilla de control'!#REF!,K213)>0,"SI","NO") -> #REF!
A214: RAB | B214: 02C5C | F214: =IF(OR(LEN(B214)=9,LEN(B214)=5),MID(B214,1,4),MID(B214,1,5)) -> 02C5 | G214: =IF(MID(F214,5,1)<>"",MID(F214,4,2),MID(F214,4,1))*1 -> 5 | H214: =+MID(B214,1,2)*1 -> 2 | I214: =+MID(B214,3,1) -> C | J214: =HLOOKUP(A214,$O$1:$U$2,2,0) -> MQ200 | K214: =CONCATENATE(A214,B214) -> RAB02C5C | L214: =VLOOKUP(K214,'Planilla de control'!#REF!,2,0) -> #REF! | M214: =IF(COUNTIF('Planilla de control'!#REF!,K214)>0,"SI","NO") -> #REF!
A215: RAB | B215: 02C6C | F215: =IF(OR(LEN(B215)=9,LEN(B215)=5),MID(B215,1,4),MID(B215,1,5)) -> 02C6 | G215: =IF(MID(F215,5,1)<>"",MID(F215,4,2),MID(F215,4,1))*1 -> 6 | H215: =+MID(B215,1,2)*1 -> 2 | I215: =+MID(B215,3,1) -> C | J215: =HLOOKUP(A215,$O$1:$U$2,2,0) -> MQ200 | K215: =CONCATENATE(A215,B215) -> RAB02C6C | L215: =VLOOKUP(K215,'Planilla de control'!#REF!,2,0) -> #REF! | M215: =IF(COUNTIF('Planilla de control'!#REF!,K215)>0,"SI","NO") -> #REF!
A216: RAB | B216: 02F2A | F216: =IF(OR(LEN(B216)=9,LEN(B216)=5),MID(B216,1,4),MID(B216,1,5)) -> 02F2 | G216: =IF(MID(F216,5,1)<>"",MID(F216,4,2),MID(F216,4,1))*1 -> 2 | H216: =+MID(B216,1,2)*1 -> 2 | I216: =+MID(B216,3,1) -> F | J216: =HLOOKUP(A216,$O$1:$U$2,2,0) -> MQ200 | K216: =CONCATENATE(A216,B216) -> RAB02F2A | L216: =VLOOKUP(K216,'Planilla de control'!#REF!,2,0) -> #REF! | M216: =IF(COUNTIF('Planilla de control'!#REF!,K216)>0,"SI","NO") -> #REF!
A217: RAB | B217: 02G2A | E217: T | F217: =IF(OR(LEN(B217)=9,LEN(B217)=5),MID(B217,1,4),MID(B217,1,5)) -> 02G2 | G217: =IF(MID(F217,5,1)<>"",MID(F217,4,2),MID(F217,4,1))*1 -> 2 | H217: =+MID(B217,1,2)*1 -> 2 | I217: =+MID(B217,3,1) -> G | J217: =HLOOKUP(A217,$O$1:$U$2,2,0) -> MQ200 | K217: =CONCATENATE(A217,B217) -> RAB02G2A | L217: =VLOOKUP(K217,'Planilla de control'!#REF!,2,0) -> #REF! | M217: =IF(COUNTIF('Planilla de control'!#REF!,K217)>0,"SI","NO") -> #REF!
A218: RAB | B218: 02G2B | E218: T | F218: =IF(OR(LEN(B218)=9,LEN(B218)=5),MID(B218,1,4),MID(B218,1,5)) -> 02G2 | G218: =IF(MID(F218,5,1)<>"",MID(F218,4,2),MID(F218,4,1))*1 -> 2 | H218: =+MID(B218,1,2)*1 -> 2 | I218: =+MID(B218,3,1) -> G | J218: =HLOOKUP(A218,$O$1:$U$2,2,0) -> MQ200 | K218: =CONCATENATE(A218,B218) -> RAB02G2B | L218: =VLOOKUP(K218,'Planilla de control'!#REF!,2,0) -> #REF! | M218: =IF(COUNTIF('Planilla de control'!#REF!,K218)>0,"SI","NO") -> #REF!
A219: RAB | B219: 02G2C | E219: T | F219: =IF(OR(LEN(B219)=9,LEN(B219)=5),MID(B219,1,4),MID(B219,1,5)) -> 02G2 | G219: =IF(MID(F219,5,1)<>"",MID(F219,4,2),MID(F219,4,1))*1 -> 2 | H219: =+MID(B219,1,2)*1 -> 2 | I219: =+MID(B219,3,1) -> G | J219: =HLOOKUP(A219,$O$1:$U$2,2,0) -> MQ200 | K219: =CONCATENATE(A219,B219) -> RAB02G2C | L219: =VLOOKUP(K219,'Planilla de control'!#REF!,2,0) -> #REF! | M219: =IF(COUNTIF('Planilla de control'!#REF!,K219)>0,"SI","NO") -> #REF!
A220: RAB | B220: 02H2A | E220: T | F220: =IF(OR(LEN(B220)=9,LEN(B220)=5),MID(B220,1,4),MID(B220,1,5)) -> 02H2 | G220: =IF(MID(F220,5,1)<>"",MID(F220,4,2),MID(F220,4,1))*1 -> 2 | H220: =+MID(B220,1,2)*1 -> 2 | I220: =+MID(B220,3,1) -> H | J220: =HLOOKUP(A220,$O$1:$U$2,2,0) -> MQ200 | K220: =CONCATENATE(A220,B220) -> RAB02H2A | L220: =VLOOKUP(K220,'Planilla de control'!#REF!,2,0) -> #REF! | M220: =IF(COUNTIF('Planilla de control'!#REF!,K220)>0,"SI","NO") -> #REF!
A221: RAB | B221: 02H2B | E221: T | F221: =IF(OR(LEN(B221)=9,LEN(B221)=5),MID(B221,1,4),MID(B221,1,5)) -> 02H2 | G221: =IF(MID(F221,5,1)<>"",MID(F221,4,2),MID(F221,4,1))*1 -> 2 | H221: =+MID(B221,1,2)*1 -> 2 | I221: =+MID(B221,3,1) -> H | J221: =HLOOKUP(A221,$O$1:$U$2,2,0) -> MQ200 | K221: =CONCATENATE(A221,B221) -> RAB02H2B | L221: =VLOOKUP(K221,'Planilla de control'!#REF!,2,0) -> #REF! | M221: =IF(COUNTIF('Planilla de control'!#REF!,K221)>0,"SI","NO") -> #REF!
A222: RAB | B222: 02H2C | E222: T | F222: =IF(OR(LEN(B222)=9,LEN(B222)=5),MID(B222,1,4),MID(B222,1,5)) -> 02H2 | G222: =IF(MID(F222,5,1)<>"",MID(F222,4,2),MID(F222,4,1))*1 -> 2 | H222: =+MID(B222,1,2)*1 -> 2 | I222: =+MID(B222,3,1) -> H | J222: =HLOOKUP(A222,$O$1:$U$2,2,0) -> MQ200 | K222: =CONCATENATE(A222,B222) -> RAB02H2C | L222: =VLOOKUP(K222,'Planilla de control'!#REF!,2,0) -> #REF! | M222: =IF(COUNTIF('Planilla de control'!#REF!,K222)>0,"SI","NO") -> #REF!
A223: RAB | B223: 02H3B | F223: =IF(OR(LEN(B223)=9,LEN(B223)=5),MID(B223,1,4),MID(B223,1,5)) -> 02H3 | G223: =IF(MID(F223,5,1)<>"",MID(F223,4,2),MID(F223,4,1))*1 -> 3 | H223: =+MID(B223,1,2)*1 -> 2 | I223: =+MID(B223,3,1) -> H | J223: =HLOOKUP(A223,$O$1:$U$2,2,0) -> MQ200 | K223: =CONCATENATE(A223,B223) -> RAB02H3B | L223: =VLOOKUP(K223,'Planilla de control'!#REF!,2,0) -> #REF! | M223: =IF(COUNTIF('Planilla de control'!#REF!,K223)>0,"SI","NO") -> #REF!
A224: RAB | B224: 02K2A | E224: T | F224: =IF(OR(LEN(B224)=9,LEN(B224)=5),MID(B224,1,4),MID(B224,1,5)) -> 02K2 | G224: =IF(MID(F224,5,1)<>"",MID(F224,4,2),MID(F224,4,1))*1 -> 2 | H224: =+MID(B224,1,2)*1 -> 2 | I224: =+MID(B224,3,1) -> K | J224: =HLOOKUP(A224,$O$1:$U$2,2,0) -> MQ200 | K224: =CONCATENATE(A224,B224) -> RAB02K2A | L224: =VLOOKUP(K224,'Planilla de control'!#REF!,2,0) -> #REF! | M224: =IF(COUNTIF('Planilla de control'!#REF!,K224)>0,"SI","NO") -> #REF!
A225: RAB | B225: 02K2B | E225: T | F225: =IF(OR(LEN(B225)=9,LEN(B225)=5),MID(B225,1,4),MID(B225,1,5)) -> 02K2 | G225: =IF(MID(F225,5,1)<>"",MID(F225,4,2),MID(F225,4,1))*1 -> 2 | H225: =+MID(B225,1,2)*1 -> 2 | I225: =+MID(B225,3,1) -> K | J225: =HLOOKUP(A225,$O$1:$U$2,2,0) -> MQ200 | K225: =CONCATENATE(A225,B225) -> RAB02K2B | L225: =VLOOKUP(K225,'Planilla de control'!#REF!,2,0) -> #REF! | M225: =IF(COUNTIF('Planilla de control'!#REF!,K225)>0,"SI","NO") -> #REF!
A226: RAB | B226: 02K2C | E226: T | F226: =IF(OR(LEN(B226)=9,LEN(B226)=5),MID(B226,1,4),MID(B226,1,5)) -> 02K2 | G226: =IF(MID(F226,5,1)<>"",MID(F226,4,2),MID(F226,4,1))*1 -> 2 | H226: =+MID(B226,1,2)*1 -> 2 | I226: =+MID(B226,3,1) -> K | J226: =HLOOKUP(A226,$O$1:$U$2,2,0) -> MQ200 | K226: =CONCATENATE(A226,B226) -> RAB02K2C | L226: =VLOOKUP(K226,'Planilla de control'!#REF!,2,0) -> #REF! | M226: =IF(COUNTIF('Planilla de control'!#REF!,K226)>0,"SI","NO") -> #REF!
A227: RAB | B227: 02L7A | E227: T | F227: =IF(OR(LEN(B227)=9,LEN(B227)=5),MID(B227,1,4),MID(B227,1,5)) -> 02L7 | G227: =IF(MID(F227,5,1)<>"",MID(F227,4,2),MID(F227,4,1))*1 -> 7 | H227: =+MID(B227,1,2)*1 -> 2 | I227: =+MID(B227,3,1) -> L | J227: =HLOOKUP(A227,$O$1:$U$2,2,0) -> MQ200 | K227: =CONCATENATE(A227,B227) -> RAB02L7A | L227: =VLOOKUP(K227,'Planilla de control'!#REF!,2,0) -> #REF! | M227: =IF(COUNTIF('Planilla de control'!#REF!,K227)>0,"SI","NO") -> #REF!
A228: RAB | B228: 02L7B | E228: T | F228: =IF(OR(LEN(B228)=9,LEN(B228)=5),MID(B228,1,4),MID(B228,1,5)) -> 02L7 | G228: =IF(MID(F228,5,1)<>"",MID(F228,4,2),MID(F228,4,1))*1 -> 7 | H228: =+MID(B228,1,2)*1 -> 2 | I228: =+MID(B228,3,1) -> L | J228: =HLOOKUP(A228,$O$1:$U$2,2,0) -> MQ200 | K228: =CONCATENATE(A228,B228) -> RAB02L7B | L228: =VLOOKUP(K228,'Planilla de control'!#REF!,2,0) -> #REF! | M228: =IF(COUNTIF('Planilla de control'!#REF!,K228)>0,"SI","NO") -> #REF!
A229: RAB | B229: 02C2C | F229: =IF(OR(LEN(B229)=9,LEN(B229)=5),MID(B229,1,4),MID(B229,1,5)) -> 02C2 | G229: =IF(MID(F229,5,1)<>"",MID(F229,4,2),MID(F229,4,1))*1 -> 2 | H229: =+MID(B229,1,2)*1 -> 2 | I229: =+MID(B229,3,1) -> C | J229: =HLOOKUP(A229,$O$1:$U$2,2,0) -> MQ200 | K229: =CONCATENATE(A229,B229) -> RAB02C2C | L229: =VLOOKUP(K229,'Planilla de control'!#REF!,2,0) -> #REF! | M229: =IF(COUNTIF('Planilla de control'!#REF!,K229)>0,"SI","NO") -> #REF!
A230: RAB | B230: 02C3B | F230: =IF(OR(LEN(B230)=9,LEN(B230)=5),MID(B230,1,4),MID(B230,1,5)) -> 02C3 | G230: =IF(MID(F230,5,1)<>"",MID(F230,4,2),MID(F230,4,1))*1 -> 3 | H230: =+MID(B230,1,2)*1 -> 2 | I230: =+MID(B230,3,1) -> C | J230: =HLOOKUP(A230,$O$1:$U$2,2,0) -> MQ200 | K230: =CONCATENATE(A230,B230) -> RAB02C3B | L230: =VLOOKUP(K230,'Planilla de control'!#REF!,2,0) -> #REF! | M230: =IF(COUNTIF('Planilla de control'!#REF!,K230)>0,"SI","NO") -> #REF!
A231: RAB | B231: 02D1A | F231: =IF(OR(LEN(B231)=9,LEN(B231)=5),MID(B231,1,4),MID(B231,1,5)) -> 02D1 | G231: =IF(MID(F231,5,1)<>"",MID(F231,4,2),MID(F231,4,1))*1 -> 1 | H231: =+MID(B231,1,2)*1 -> 2 | I231: =+MID(B231,3,1) -> D | J231: =HLOOKUP(A231,$O$1:$U$2,2,0) -> MQ200 | K231: =CONCATENATE(A231,B231) -> RAB02D1A | L231: =VLOOKUP(K231,'Planilla de control'!#REF!,2,0) -> #REF! | M231: =IF(COUNTIF('Planilla de control'!#REF!,K231)>0,"SI","NO") -> #REF!
A232: RAB | B232: 02B1B | F232: =IF(OR(LEN(B232)=9,LEN(B232)=5),MID(B232,1,4),MID(B232,1,5)) -> 02B1 | G232: =IF(MID(F232,5,1)<>"",MID(F232,4,2),MID(F232,4,1))*1 -> 1 | H232: =+MID(B232,1,2)*1 -> 2 | I232: =+MID(B232,3,1) -> B | J232: =HLOOKUP(A232,$O$1:$U$2,2,0) -> MQ200 | K232: =CONCATENATE(A232,B232) -> RAB02B1B | L232: =VLOOKUP(K232,'Planilla de control'!#REF!,2,0) -> #REF! | M232: =IF(COUNTIF('Planilla de control'!#REF!,K232)>0,"SI","NO") -> #REF!
A233: RAB | B233: 02I8A | F233: =IF(OR(LEN(B233)=9,LEN(B233)=5),MID(B233,1,4),MID(B233,1,5)) -> 02I8 | G233: =IF(MID(F233,5,1)<>"",MID(F233,4,2),MID(F233,4,1))*1 -> 8 | H233: =+MID(B233,1,2)*1 -> 2 | I233: =+MID(B233,3,1) -> I | J233: =HLOOKUP(A233,$O$1:$U$2,2,0) -> MQ200 | K233: =CONCATENATE(A233,B233) -> RAB02I8A | L233: =VLOOKUP(K233,'Planilla de control'!#REF!,2,0) -> #REF! | M233: =IF(COUNTIF('Planilla de control'!#REF!,K233)>0,"SI","NO") -> #REF!
A234: RAB | B234: 02K1C | F234: =IF(OR(LEN(B234)=9,LEN(B234)=5),MID(B234,1,4),MID(B234,1,5)) -> 02K1 | G234: =IF(MID(F234,5,1)<>"",MID(F234,4,2),MID(F234,4,1))*1 -> 1 | H234: =+MID(B234,1,2)*1 -> 2 | I234: =+MID(B234,3,1) -> K | J234: =HLOOKUP(A234,$O$1:$U$2,2,0) -> MQ200 | K234: =CONCATENATE(A234,B234) -> RAB02K1C | L234: =VLOOKUP(K234,'Planilla de control'!#REF!,2,0) -> #REF! | M234: =IF(COUNTIF('Planilla de control'!#REF!,K234)>0,"SI","NO") -> #REF!
A235: RAB | B235: 02C1A | F235: =IF(OR(LEN(B235)=9,LEN(B235)=5),MID(B235,1,4),MID(B235,1,5)) -> 02C1 | G235: =IF(MID(F235,5,1)<>"",MID(F235,4,2),MID(F235,4,1))*1 -> 1 | H235: =+MID(B235,1,2)*1 -> 2 | I235: =+MID(B235,3,1) -> C | J235: =HLOOKUP(A235,$O$1:$U$2,2,0) -> MQ200 | K235: =CONCATENATE(A235,B235) -> RAB02C1A | L235: =VLOOKUP(K235,'Planilla de control'!#REF!,2,0) -> #REF! | M235: =IF(COUNTIF('Planilla de control'!#REF!,K235)>0,"SI","NO") -> #REF!
A236: RAB | B236: 02J6B | F236: =IF(OR(LEN(B236)=9,LEN(B236)=5),MID(B236,1,4),MID(B236,1,5)) -> 02J6 | G236: =IF(MID(F236,5,1)<>"",MID(F236,4,2),MID(F236,4,1))*1 -> 6 | H236: =+MID(B236,1,2)*1 -> 2 | I236: =+MID(B236,3,1) -> J | J236: =HLOOKUP(A236,$O$1:$U$2,2,0) -> MQ200 | K236: =CONCATENATE(A236,B236) -> RAB02J6B | L236: =VLOOKUP(K236,'Planilla de control'!#REF!,2,0) -> #REF! | M236: =IF(COUNTIF('Planilla de control'!#REF!,K236)>0,"SI","NO") -> #REF!
A237: RAB | B237: 02H7A | F237: =IF(OR(LEN(B237)=9,LEN(B237)=5),MID(B237,1,4),MID(B237,1,5)) -> 02H7 | G237: =IF(MID(F237,5,1)<>"",MID(F237,4,2),MID(F237,4,1))*1 -> 7 | H237: =+MID(B237,1,2)*1 -> 2 | I237: =+MID(B237,3,1) -> H | J237: =HLOOKUP(A237,$O$1:$U$2,2,0) -> MQ200 | K237: =CONCATENATE(A237,B237) -> RAB02H7A | L237: =VLOOKUP(K237,'Planilla de control'!#REF!,2,0) -> #REF! | M237: =IF(COUNTIF('Planilla de control'!#REF!,K237)>0,"SI","NO") -> #REF!
A238: RAB | B238: 02J7B | F238: =IF(OR(LEN(B238)=9,LEN(B238)=5),MID(B238,1,4),MID(B238,1,5)) -> 02J7 | G238: =IF(MID(F238,5,1)<>"",MID(F238,4,2),MID(F238,4,1))*1 -> 7 | H238: =+MID(B238,1,2)*1 -> 2 | I238: =+MID(B238,3,1) -> J | J238: =HLOOKUP(A238,$O$1:$U$2,2,0) -> MQ200 | K238: =CONCATENATE(A238,B238) -> RAB02J7B | L238: =VLOOKUP(K238,'Planilla de control'!#REF!,2,0) -> #REF! | M238: =IF(COUNTIF('Planilla de control'!#REF!,K238)>0,"SI","NO") -> #REF!
A239: RAB | B239: 02K5A | F239: =IF(OR(LEN(B239)=9,LEN(B239)=5),MID(B239,1,4),MID(B239,1,5)) -> 02K5 | G239: =IF(MID(F239,5,1)<>"",MID(F239,4,2),MID(F239,4,1))*1 -> 5 | H239: =+MID(B239,1,2)*1 -> 2 | I239: =+MID(B239,3,1) -> K | J239: =HLOOKUP(A239,$O$1:$U$2,2,0) -> MQ200 | K239: =CONCATENATE(A239,B239) -> RAB02K5A | L239: =VLOOKUP(K239,'Planilla de control'!#REF!,2,0) -> #REF! | M239: =IF(COUNTIF('Planilla de control'!#REF!,K239)>0,"SI","NO") -> #REF!
A240: RAB | B240: 02K8A | F240: =IF(OR(LEN(B240)=9,LEN(B240)=5),MID(B240,1,4),MID(B240,1,5)) -> 02K8 | G240: =IF(MID(F240,5,1)<>"",MID(F240,4,2),MID(F240,4,1))*1 -> 8 | H240: =+MID(B240,1,2)*1 -> 2 | I240: =+MID(B240,3,1) -> K | J240: =HLOOKUP(A240,$O$1:$U$2,2,0) -> MQ200 | K240: =CONCATENATE(A240,B240) -> RAB02K8A | L240: =VLOOKUP(K240,'Planilla de control'!#REF!,2,0) -> #REF! | M240: =IF(COUNTIF('Planilla de control'!#REF!,K240)>0,"SI","NO") -> #REF!
... A549: PC2 | B549: 03D7A | F549: =IF(OR(LEN(B549)=9,LEN(B549)=5),MID(B549,1,4),MID(B549,1,5)) -> 03D7 | G549: =IF(MID(F549,5,1)<>"",MID(F549,4,2),MID(F549,4,1))*1 -> 7 | H549: =+MID(B549,1,2)*1 -> 3 | I549: =+MID(B549,3,1) -> D | J549: =HLOOKUP(A549,$O$1:$U$2,2,0) -> MQ200 | K549: =CONCATENATE(A549,B549) -> PC203D7A | L549: =VLOOKUP(K549,'Planilla de control'!#REF!,2,0) -> #REF! | M549: =IF(COUNTIF('Planilla de control'!#REF!,K549)>0,"SI","NO") -> #REF!
A550: RAB | B550: 03C3A | E550: T | F550: =IF(OR(LEN(B550)=9,LEN(B550)=5),MID(B550,1,4),MID(B550,1,5)) -> 03C3 | G550: =IF(MID(F550,5,1)<>"",MID(F550,4,2),MID(F550,4,1))*1 -> 3 | H550: =+MID(B550,1,2)*1 -> 3 | I550: =+MID(B550,3,1) -> C | J550: =HLOOKUP(A550,$O$1:$U$2,2,0) -> MQ200 | K550: =CONCATENATE(A550,B550) -> RAB03C3A | L550: =VLOOKUP(K550,'Planilla de control'!#REF!,2,0) -> #REF! | M550: =IF(COUNTIF('Planilla de control'!#REF!,K550)>0,"SI","NO") -> #REF!
A551: RAB | B551: 03C3B | E551: T | F551: =IF(OR(LEN(B551)=9,LEN(B551)=5),MID(B551,1,4),MID(B551,1,5)) -> 03C3 | G551: =IF(MID(F551,5,1)<>"",MID(F551,4,2),MID(F551,4,1))*1 -> 3 | H551: =+MID(B551,1,2)*1 -> 3 | I551: =+MID(B551,3,1) -> C | J551: =HLOOKUP(A551,$O$1:$U$2,2,0) -> MQ200 | K551: =CONCATENATE(A551,B551) -> RAB03C3B | L551: =VLOOKUP(K551,'Planilla de control'!#REF!,2,0) -> #REF! | M551: =IF(COUNTIF('Planilla de control'!#REF!,K551)>0,"SI","NO") -> #REF!
A552: RAB | B552: 03F6C | F552: =IF(OR(LEN(B552)=9,LEN(B552)=5),MID(B552,1,4),MID(B552,1,5)) -> 03F6 | G552: =IF(MID(F552,5,1)<>"",MID(F552,4,2),MID(F552,4,1))*1 -> 6 | H552: =+MID(B552,1,2)*1 -> 3 | I552: =+MID(B552,3,1) -> F | J552: =HLOOKUP(A552,$O$1:$U$2,2,0) -> MQ200 | K552: =CONCATENATE(A552,B552) -> RAB03F6C | L552: =VLOOKUP(K552,'Planilla de control'!#REF!,2,0) -> #REF! | M552: =IF(COUNTIF('Planilla de control'!#REF!,K552)>0,"SI","NO") -> #REF!
A553: RAB | B553: 03F8A | F553: =IF(OR(LEN(B553)=9,LEN(B553)=5),MID(B553,1,4),MID(B553,1,5)) -> 03F8 | G553: =IF(MID(F553,5,1)<>"",MID(F553,4,2),MID(F553,4,1))*1 -> 8 | H553: =+MID(B553,1,2)*1 -> 3 | I553: =+MID(B553,3,1) -> F | J553: =HLOOKUP(A553,$O$1:$U$2,2,0) -> MQ200 | K553: =CONCATENATE(A553,B553) -> RAB03F8A | L553: =VLOOKUP(K553,'Planilla de control'!#REF!,2,0) -> #REF! | M553: =IF(COUNTIF('Planilla de control'!#REF!,K553)>0,"SI","NO") -> #REF!
A554: RAB | B554: 03H4A | F554: =IF(OR(LEN(B554)=9,LEN(B554)=5),MID(B554,1,4),MID(B554,1,5)) -> 03H4 | G554: =IF(MID(F554,5,1)<>"",MID(F554,4,2),MID(F554,4,1))*1 -> 4 | H554: =+MID(B554,1,2)*1 -> 3 | I554: =+MID(B554,3,1) -> H | J554: =HLOOKUP(A554,$O$1:$U$2,2,0) -> MQ200 | K554: =CONCATENATE(A554,B554) -> RAB03H4A | L554: =VLOOKUP(K554,'Planilla de control'!#REF!,2,0) -> #REF! | M554: =IF(COUNTIF('Planilla de control'!#REF!,K554)>0,"SI","NO") -> #REF!
A555: RAB | B555: 03G3C | F555: =IF(OR(LEN(B555)=9,LEN(B555)=5),MID(B555,1,4),MID(B555,1,5)) -> 03G3 | G555: =IF(MID(F555,5,1)<>"",MID(F555,4,2),MID(F555,4,1))*1 -> 3 | H555: =+MID(B555,1,2)*1 -> 3 | I555: =+MID(B555,3,1) -> G | J555: =HLOOKUP(A555,$O$1:$U$2,2,0) -> MQ200 | K555: =CONCATENATE(A555,B555) -> RAB03G3C | L555: =VLOOKUP(K555,'Planilla de control'!#REF!,2,0) -> #REF! | M555: =IF(COUNTIF('Planilla de control'!#REF!,K555)>0,"SI","NO") -> #REF!
A556: RAB | B556: 03E5B | F556: =IF(OR(LEN(B556)=9,LEN(B556)=5),MID(B556,1,4),MID(B556,1,5)) -> 03E5 | G556: =IF(MID(F556,5,1)<>"",MID(F556,4,2),MID(F556,4,1))*1 -> 5 | H556: =+MID(B556,1,2)*1 -> 3 | I556: =+MID(B556,3,1) -> E | J556: =HLOOKUP(A556,$O$1:$U$2,2,0) -> MQ200 | K556: =CONCATENATE(A556,B556) -> RAB03E5B | L556: =VLOOKUP(K556,'Planilla de control'!#REF!,2,0) -> #REF! | M556: =IF(COUNTIF('Planilla de control'!#REF!,K556)>0,"SI","NO") -> #REF!
A557: RAB | B557: 03E5A | F557: =IF(OR(LEN(B557)=9,LEN(B557)=5),MID(B557,1,4),MID(B557,1,5)) -> 03E5 | G557: =IF(MID(F557,5,1)<>"",MID(F557,4,2),MID(F557,4,1))*1 -> 5 | H557: =+MID(B557,1,2)*1 -> 3 | I557: =+MID(B557,3,1) -> E | J557: =HLOOKUP(A557,$O$1:$U$2,2,0) -> MQ200 | K557: =CONCATENATE(A557,B557) -> RAB03E5A | L557: =VLOOKUP(K557,'Planilla de control'!#REF!,2,0) -> #REF! | M557: =IF(COUNTIF('Planilla de control'!#REF!,K557)>0,"SI","NO") -> #REF!
A558: RAB | B558: 03B7B | F558: =IF(OR(LEN(B558)=9,LEN(B558)=5),MID(B558,1,4),MID(B558,1,5)) -> 03B7 | G558: =IF(MID(F558,5,1)<>"",MID(F558,4,2),MID(F558,4,1))*1 -> 7 | H558: =+MID(B558,1,2)*1 -> 3 | I558: =+MID(B558,3,1) -> B | J558: =HLOOKUP(A558,$O$1:$U$2,2,0) -> MQ200 | K558: =CONCATENATE(A558,B558) -> RAB03B7B | L558: =VLOOKUP(K558,'Planilla de control'!#REF!,2,0) -> #REF! | M558: =IF(COUNTIF('Planilla de control'!#REF!,K558)>0,"SI","NO") -> #REF!
A559: RAB | B559: 03F4B | F559: =IF(OR(LEN(B559)=9,LEN(B559)=5),MID(B559,1,4),MID(B559,1,5)) -> 03F4 | G559: =IF(MID(F559,5,1)<>"",MID(F559,4,2),MID(F559,4,1))*1 -> 4 | H559: =+MID(B559,1,2)*1 -> 3 | I559: =+MID(B559,3,1) -> F | J559: =HLOOKUP(A559,$O$1:$U$2,2,0) -> MQ200 | K559: =CONCATENATE(A559,B559) -> RAB03F4B | L559: =VLOOKUP(K559,'Planilla de control'!#REF!,2,0) -> #REF! | M559: =IF(COUNTIF('Planilla de control'!#REF!,K559)>0,"SI","NO") -> #REF!
A560: RAB | B560: 03I6A | F560: =IF(OR(LEN(B560)=9,LEN(B560)=5),MID(B560,1,4),MID(B560,1,5)) -> 03I6 | G560: =IF(MID(F560,5,1)<>"",MID(F560,4,2),MID(F560,4,1))*1 -> 6 | H560: =+MID(B560,1,2)*1 -> 3 | I560: =+MID(B560,3,1) -> I | J560: =HLOOKUP(A560,$O$1:$U$2,2,0) -> MQ200 | K560: =CONCATENATE(A560,B560) -> RAB03I6A | L560: =VLOOKUP(K560,'Planilla de control'!#REF!,2,0) -> #REF! | M560: =IF(COUNTIF('Planilla de control'!#REF!,K560)>0,"SI","NO") -> #REF!
A561: RAB | B561: 03I3C | F561: =IF(OR(LEN(B561)=9,LEN(B561)=5),MID(B561,1,4),MID(B561,1,5)) -> 03I3 | G561: =IF(MID(F561,5,1)<>"",MID(F561,4,2),MID(F561,4,1))*1 -> 3 | H561: =+MID(B561,1,2)*1 -> 3 | I561: =+MID(B561,3,1) -> I | J561: =HLOOKUP(A561,$O$1:$U$2,2,0) -> MQ200 | K561: =CONCATENATE(A561,B561) -> RAB03I3C | L561: =VLOOKUP(K561,'Planilla de control'!#REF!,2,0) -> #REF! | M561: =IF(COUNTIF('Planilla de control'!#REF!,K561)>0,"SI","NO") -> #REF!
A562: RAB | B562: 03H5A | F562: =IF(OR(LEN(B562)=9,LEN(B562)=5),MID(B562,1,4),MID(B562,1,5)) -> 03H5 | G562: =IF(MID(F562,5,1)<>"",MID(F562,4,2),MID(F562,4,1))*1 -> 5 | H562: =+MID(B562,1,2)*1 -> 3 | I562: =+MID(B562,3,1) -> H | J562: =HLOOKUP(A562,$O$1:$U$2,2,0) -> MQ200 | K562: =CONCATENATE(A562,B562) -> RAB03H5A | L562: =VLOOKUP(K562,'Planilla de control'!#REF!,2,0) -> #REF! | M562: =IF(COUNTIF('Planilla de control'!#REF!,K562)>0,"SI","NO") -> #REF!
A563: RAB | B563: 03F3C | F563: =IF(OR(LEN(B563)=9,LEN(B563)=5),MID(B563,1,4),MID(B563,1,5)) -> 03F3 | G563: =IF(MID(F563,5,1)<>"",MID(F563,4,2),MID(F563,4,1))*1 -> 3 | H563: =+MID(B563,1,2)*1 -> 3 | I563: =+MID(B563,3,1) -> F | J563: =HLOOKUP(A563,$O$1:$U$2,2,0) -> MQ200 | K563: =CONCATENATE(A563,B563) -> RAB03F3C | L563: =VLOOKUP(K563,'Planilla de control'!#REF!,2,0) -> #REF! | M563: =IF(COUNTIF('Planilla de control'!#REF!,K563)>0,"SI","NO") -> #REF!
... A599: RAB | B599: 03H5C | F599: =IF(OR(LEN(B599)=9,LEN(B599)=5),MID(B599,1,4),MID(B599,1,5)) -> 03H5 | G599: =IF(MID(F599,5,1)<>"",MID(F599,4,2),MID(F599,4,1))*1 -> 5 | H599: =+MID(B599,1,2)*1 -> 3 | I599: =+MID(B599,3,1) -> H | J599: =HLOOKUP(A599,$O$1:$U$2,2,0) -> MQ200 | K599: =CONCATENATE(A599,B599) -> RAB03H5C | L599: =VLOOKUP(K599,'Planilla de control'!#REF!,2,0) -> #REF! | M599: =IF(COUNTIF('Planilla de control'!#REF!,K599)>0,"SI","NO") -> #REF!
A600: RAB | B600: 03C3C | E600: T | F600: =IF(OR(LEN(B600)=9,LEN(B600)=5),MID(B600,1,4),MID(B600,1,5)) -> 03C3 | G600: =IF(MID(F600,5,1)<>"",MID(F600,4,2),MID(F600,4,1))*1 -> 3 | H600: =+MID(B600,1,2)*1 -> 3 | I600: =+MID(B600,3,1) -> C | J600: =HLOOKUP(A600,$O$1:$U$2,2,0) -> MQ200 | K600: =CONCATENATE(A600,B600) -> RAB03C3C | L600: =VLOOKUP(K600,'Planilla de control'!#REF!,2,0) -> #REF! | M600: =IF(COUNTIF('Planilla de control'!#REF!,K600)>0,"SI","NO") -> #REF!
A601: RAB | B601: 03L6C | F601: =IF(OR(LEN(B601)=9,LEN(B601)=5),MID(B601,1,4),MID(B601,1,5)) -> 03L6 | G601: =IF(MID(F601,5,1)<>"",MID(F601,4,2),MID(F601,4,1))*1 -> 6 | H601: =+MID(B601,1,2)*1 -> 3 | I601: =+MID(B601,3,1) -> L | J601: =HLOOKUP(A601,$O$1:$U$2,2,0) -> MQ200 | K601: =CONCATENATE(A601,B601) -> RAB03L6C | L601: =VLOOKUP(K601,'Planilla de control'!#REF!,2,0) -> #REF! | M601: =IF(COUNTIF('Planilla de control'!#REF!,K601)>0,"SI","NO") -> #REF!
A602: RAB | B602: 03L7C | F602: =IF(OR(LEN(B602)=9,LEN(B602)=5),MID(B602,1,4),MID(B602,1,5)) -> 03L7 | G602: =IF(MID(F602,5,1)<>"",MID(F602,4,2),MID(F602,4,1))*1 -> 7 | H602: =+MID(B602,1,2)*1 -> 3 | I602: =+MID(B602,3,1) -> L | J602: =HLOOKUP(A602,$O$1:$U$2,2,0) -> MQ200 | K602: =CONCATENATE(A602,B602) -> RAB03L7C | L602: =VLOOKUP(K602,'Planilla de control'!#REF!,2,0) -> #REF! | M602: =IF(COUNTIF('Planilla de control'!#REF!,K602)>0,"SI","NO") -> #REF!
A603: RAB | B603: 03G6A | F603: =IF(OR(LEN(B603)=9,LEN(B603)=5),MID(B603,1,4),MID(B603,1,5)) -> 03G6 | G603: =IF(MID(F603,5,1)<>"",MID(F603,4,2),MID(F603,4,1))*1 -> 6 | H603: =+MID(B603,1,2)*1 -> 3 | I603: =+MID(B603,3,1) -> G | J603: =HLOOKUP(A603,$O$1:$U$2,2,0) -> MQ200 | K603: =CONCATENATE(A603,B603) -> RAB03G6A | L603: =VLOOKUP(K603,'Planilla de control'!#REF!,2,0) -> #REF! | M603: =IF(COUNTIF('Planilla de control'!#REF!,K603)>0,"SI","NO") -> #REF!
A604: RAB | B604: 03F7A | F604: =IF(OR(LEN(B604)=9,LEN(B604)=5),MID(B604,1,4),MID(B604,1,5)) -> 03F7 | G604: =IF(MID(F604,5,1)<>"",MID(F604,4,2),MID(F604,4,1))*1 -> 7 | H604: =+MID(B604,1,2)*1 -> 3 | I604: =+MID(B604,3,1) -> F | J604: =HLOOKUP(A604,$O$1:$U$2,2,0) -> MQ200 | K604: =CONCATENATE(A604,B604) -> RAB03F7A | L604: =VLOOKUP(K604,'Planilla de control'!#REF!,2,0) -> #REF! | M604: =IF(COUNTIF('Planilla de control'!#REF!,K604)>0,"SI","NO") -> #REF!
A605: RAB | B605: 03D5C | F605: =IF(OR(LEN(B605)=9,LEN(B605)=5),MID(B605,1,4),MID(B605,1,5)) -> 03D5 | G605: =IF(MID(F605,5,1)<>"",MID(F605,4,2),MID(F605,4,1))*1 -> 5 | H605: =+MID(B605,1,2)*1 -> 3 | I605: =+MID(B605,3,1) -> D | J605: =HLOOKUP(A605,$O$1:$U$2,2,0) -> MQ200 | K605: =CONCATENATE(A605,B605) -> RAB03D5C | L605: =VLOOKUP(K605,'Planilla de control'!#REF!,2,0) -> #REF! | M605: =IF(COUNTIF('Planilla de control'!#REF!,K605)>0,"SI","NO") -> #REF!
A606: RAB | B606: 03E6C | F606: =IF(OR(LEN(B606)=9,LEN(B606)=5),MID(B606,1,4),MID(B606,1,5)) -> 03E6 | G606: =IF(MID(F606,5,1)<>"",MID(F606,4,2),MID(F606,4,1))*1 -> 6 | H606: =+MID(B606,1,2)*1 -> 3 | I606: =+MID(B606,3,1) -> E | J606: =HLOOKUP(A606,$O$1:$U$2,2,0) -> MQ200 | K606: =CONCATENATE(A606,B606) -> RAB03E6C | L606: =VLOOKUP(K606,'Planilla de control'!#REF!,2,0) -> #REF! | M606: =IF(COUNTIF('Planilla de control'!#REF!,K606)>0,"SI","NO") -> #REF!
A607: RAB | B607: 03F3B | F607: =IF(OR(LEN(B607)=9,LEN(B607)=5),MID(B607,1,4),MID(B607,1,5)) -> 03F3 | G607: =IF(MID(F607,5,1)<>"",MID(F607,4,2),MID(F607,4,1))*1 -> 3 | H607: =+MID(B607,1,2)*1 -> 3 | I607: =+MID(B607,3,1) -> F | J607: =HLOOKUP(A607,$O$1:$U$2,2,0) -> MQ200 | K607: =CONCATENATE(A607,B607) -> RAB03F3B | L607: =VLOOKUP(K607,'Planilla de control'!#REF!,2,0) -> #REF! | M607: =IF(COUNTIF('Planilla de control'!#REF!,K607)>0,"SI","NO") -> #REF!
A608: RAB | B608: 03L6B | F608: =IF(OR(LEN(B608)=9,LEN(B608)=5),MID(B608,1,4),MID(B608,1,5)) -> 03L6 | G608: =IF(MID(F608,5,1)<>"",MID(F608,4,2),MID(F608,4,1))*1 -> 6 | H608: =+MID(B608,1,2)*1 -> 3 | I608: =+MID(B608,3,1) -> L | J608: =HLOOKUP(A608,$O$1:$U$2,2,0) -> MQ200 | K608: =CONCATENATE(A608,B608) -> RAB03L6B | L608: =VLOOKUP(K608,'Planilla de control'!#REF!,2,0) -> #REF! | M608: =IF(COUNTIF('Planilla de control'!#REF!,K608)>0,"SI","NO") -> #REF!
A609: RAB | B609: 03E5C | F609: =IF(OR(LEN(B609)=9,LEN(B609)=5),MID(B609,1,4),MID(B609,1,5)) -> 03E5 | G609: =IF(MID(F609,5,1)<>"",MID(F609,4,2),MID(F609,4,1))*1 -> 5 | H609: =+MID(B609,1,2)*1 -> 3 | I609: =+MID(B609,3,1) -> E | J609: =HLOOKUP(A609,$O$1:$U$2,2,0) -> MQ200 | K609: =CONCATENATE(A609,B609) -> RAB03E5C | L609: =VLOOKUP(K609,'Planilla de control'!#REF!,2,0) -> #REF! | M609: =IF(COUNTIF('Planilla de control'!#REF!,K609)>0,"SI","NO") -> #REF!
A610: RAB | B610: 03E3B | F610: =IF(OR(LEN(B610)=9,LEN(B610)=5),MID(B610,1,4),MID(B610,1,5)) -> 03E3 | G610: =IF(MID(F610,5,1)<>"",MID(F610,4,2),MID(F610,4,1))*1 -> 3 | H610: =+MID(B610,1,2)*1 -> 3 | I610: =+MID(B610,3,1) -> E | J610: =HLOOKUP(A610,$O$1:$U$2,2,0) -> MQ200 | K610: =CONCATENATE(A610,B610) -> RAB03E3B | L610: =VLOOKUP(K610,'Planilla de control'!#REF!,2,0) -> #REF! | M610: =IF(COUNTIF('Planilla de control'!#REF!,K610)>0,"SI","NO") -> #REF!
A611: RAB | B611: 03I5A | F611: =IF(OR(LEN(B611)=9,LEN(B611)=5),MID(B611,1,4),MID(B611,1,5)) -> 03I5 | G611: =IF(MID(F611,5,1)<>"",MID(F611,4,2),MID(F611,4,1))*1 -> 5 | H611: =+MID(B611,1,2)*1 -> 3 | I611: =+MID(B611,3,1) -> I | J611: =HLOOKUP(A611,$O$1:$U$2,2,0) -> MQ200 | K611: =CONCATENATE(A611,B611) -> RAB03I5A | L611: =VLOOKUP(K611,'Planilla de control'!#REF!,2,0) -> #REF! | M611: =IF(COUNTIF('Planilla de control'!#REF!,K611)>0,"SI","NO") -> #REF!
A612: RAB | B612: 03I5B | F612: =IF(OR(LEN(B612)=9,LEN(B612)=5),MID(B612,1,4),MID(B612,1,5)) -> 03I5 | G612: =IF(MID(F612,5,1)<>"",MID(F612,4,2),MID(F612,4,1))*1 -> 5 | H612: =+MID(B612,1,2)*1 -> 3 | I612: =+MID(B612,3,1) -> I | J612: =HLOOKUP(A612,$O$1:$U$2,2,0) -> MQ200 | K612: =CONCATENATE(A612,B612) -> RAB03I5B | L612: =VLOOKUP(K612,'Planilla de control'!#REF!,2,0) -> #REF! | M612: =IF(COUNTIF('Planilla de control'!#REF!,K612)>0,"SI","NO") -> #REF!
... A723: PC2 | B723: 04B2D | F723: =IF(OR(LEN(B723)=9,LEN(B723)=5),MID(B723,1,4),MID(B723,1,5)) -> 04B2 | G723: =IF(MID(F723,5,1)<>"",MID(F723,4,2),MID(F723,4,1))*1 -> 2 | H723: =+MID(B723,1,2)*1 -> 4 | I723: =+MID(B723,3,1) -> B | J723: =HLOOKUP(A723,$O$1:$U$2,2,0) -> MQ200 | K723: =CONCATENATE(A723,B723) -> PC204B2D | L723: =VLOOKUP(K723,'Planilla de control'!#REF!,2,0) -> #REF! | M723: =IF(COUNTIF('Planilla de control'!#REF!,K723)>0,"SI","NO") -> #REF!
A724: PC2 | B724: 04B6A | E724: T | F724: =IF(OR(LEN(B724)=9,LEN(B724)=5),MID(B724,1,4),MID(B724,1,5)) -> 04B6 | G724: =IF(MID(F724,5,1)<>"",MID(F724,4,2),MID(F724,4,1))*1 -> 6 | H724: =+MID(B724,1,2)*1 -> 4 | I724: =+MID(B724,3,1) -> B | J724: =HLOOKUP(A724,$O$1:$U$2,2,0) -> MQ200 | K724: =CONCATENATE(A724,B724) -> PC204B6A | L724: =VLOOKUP(K724,'Planilla de control'!#REF!,2,0) -> #REF! | M724: =IF(COUNTIF('Planilla de control'!#REF!,K724)>0,"SI","NO") -> #REF!
A725: PC2 | B725: 04B6B | E725: T | F725: =IF(OR(LEN(B725)=9,LEN(B725)=5),MID(B725,1,4),MID(B725,1,5)) -> 04B6 | G725: =IF(MID(F725,5,1)<>"",MID(F725,4,2),MID(F725,4,1))*1 -> 6 | H725: =+MID(B725,1,2)*1 -> 4 | I725: =+MID(B725,3,1) -> B | J725: =HLOOKUP(A725,$O$1:$U$2,2,0) -> MQ200 | K725: =CONCATENATE(A725,B725) -> PC204B6B | L725: =VLOOKUP(K725,'Planilla de control'!#REF!,2,0) -> #REF! | M725: =IF(COUNTIF('Planilla de control'!#REF!,K725)>0,"SI","NO") -> #REF!
A726: PC2 | B726: 04B6C | E726: T | F726: =IF(OR(LEN(B726)=9,LEN(B726)=5),MID(B726,1,4),MID(B726,1,5)) -> 04B6 | G726: =IF(MID(F726,5,1)<>"",MID(F726,4,2),MID(F726,4,1))*1 -> 6 | H726: =+MID(B726,1,2)*1 -> 4 | I726: =+MID(B726,3,1) -> B | J726: =HLOOKUP(A726,$O$1:$U$2,2,0) -> MQ200 | K726: =CONCATENATE(A726,B726) -> PC204B6C | L726: =VLOOKUP(K726,'Planilla de control'!#REF!,2,0) -> #REF! | M726: =IF(COUNTIF('Planilla de control'!#REF!,K726)>0,"SI","NO") -> #REF!
A727: PC2 | B727: 04C1C | F727: =IF(OR(LEN(B727)=9,LEN(B727)=5),MID(B727,1,4),MID(B727,1,5)) -> 04C1 | G727: =IF(MID(F727,5,1)<>"",MID(F727,4,2),MID(F727,4,1))*1 -> 1 | H727: =+MID(B727,1,2)*1 -> 4 | I727: =+MID(B727,3,1) -> C | J727: =HLOOKUP(A727,$O$1:$U$2,2,0) -> MQ200 | K727: =CONCATENATE(A727,B727) -> PC204C1C | L727: =VLOOKUP(K727,'Planilla de control'!#REF!,2,0) -> #REF! | M727: =IF(COUNTIF('Planilla de control'!#REF!,K727)>0,"SI","NO") -> #REF!
A728: PC2 | B728: 04C2A | F728: =IF(OR(LEN(B728)=9,LEN(B728)=5),MID(B728,1,4),MID(B728,1,5)) -> 04C2 | G728: =IF(MID(F728,5,1)<>"",MID(F728,4,2),MID(F728,4,1))*1 -> 2 | H728: =+MID(B728,1,2)*1 -> 4 | I728: =+MID(B728,3,1) -> C | J728: =HLOOKUP(A728,$O$1:$U$2,2,0) -> MQ200 | K728: =CONCATENATE(A728,B728) -> PC204C2A | L728: =VLOOKUP(K728,'Planilla de control'!#REF!,2,0) -> #REF! | M728: =IF(COUNTIF('Planilla de control'!#REF!,K728)>0,"SI","NO") -> #REF!
A729: PC2 | B729: 04C2B | F729: =IF(OR(LEN(B729)=9,LEN(B729)=5),MID(B729,1,4),MID(B729,1,5)) -> 04C2 | G729: =IF(MID(F729,5,1)<>"",MID(F729,4,2),MID(F729,4,1))*1 -> 2 | H729: =+MID(B729,1,2)*1 -> 4 | I729: =+MID(B729,3,1) -> C | J729: =HLOOKUP(A729,$O$1:$U$2,2,0) -> MQ200 | K729: =CONCATENATE(A729,B729) -> PC204C2B | L729: =VLOOKUP(K729,'Planilla de control'!#REF!,2,0) -> #REF! | M729: =IF(COUNTIF('Planilla de control'!#REF!,K729)>0,"SI","NO") -> #REF!
A730: PC2 | B730: 04D7A | F730: =IF(OR(LEN(B730)=9,LEN(B730)=5),MID(B730,1,4),MID(B730,1,5)) -> 04D7 | G730: =IF(MID(F730,5,1)<>"",MID(F730,4,2),MID(F730,4,1))*1 -> 7 | H730: =+MID(B730,1,2)*1 -> 4 | I730: =+MID(B730,3,1) -> D | J730: =HLOOKUP(A730,$O$1:$U$2,2,0) -> MQ200 | K730: =CONCATENATE(A730,B730) -> PC204D7A | L730: =VLOOKUP(K730,'Planilla de control'!#REF!,2,0) -> #REF! | M730: =IF(COUNTIF('Planilla de control'!#REF!,K730)>0,"SI","NO") -> #REF!
A731: PC2 | B731: 04D7C | F731: =IF(OR(LEN(B731)=9,LEN(B731)=5),MID(B731,1,4),MID(B731,1,5)) -> 04D7 | G731: =IF(MID(F731,5,1)<>"",MID(F731,4,2),MID(F731,4,1))*1 -> 7 | H731: =+MID(B731,1,2)*1 -> 4 | I731: =+MID(B731,3,1) -> D | J731: =HLOOKUP(A731,$O$1:$U$2,2,0) -> MQ200 | K731: =CONCATENATE(A731,B731) -> PC204D7C | L731: =VLOOKUP(K731,'Planilla de control'!#REF!,2,0) -> #REF! | M731: =IF(COUNTIF('Planilla de control'!#REF!,K731)>0,"SI","NO") -> #REF!
A732: PC2 | B732: 04E5A | F732: =IF(OR(LEN(B732)=9,LEN(B732)=5),MID(B732,1,4),MID(B732,1,5)) -> 04E5 | G732: =IF(MID(F732,5,1)<>"",MID(F732,4,2),MID(F732,4,1))*1 -> 5 | H732: =+MID(B732,1,2)*1 -> 4 | I732: =+MID(B732,3,1) -> E | J732: =HLOOKUP(A732,$O$1:$U$2,2,0) -> MQ200 | K732: =CONCATENATE(A732,B732) -> PC204E5A | L732: =VLOOKUP(K732,'Planilla de control'!#REF!,2,0) -> #REF! | M732: =IF(COUNTIF('Planilla de control'!#REF!,K732)>0,"SI","NO") -> #REF!
A733: PC2 | B733: 04E5B | F733: =IF(OR(LEN(B733)=9,LEN(B733)=5),MID(B733,1,4),MID(B733,1,5)) -> 04E5 | G733: =IF(MID(F733,5,1)<>"",MID(F733,4,2),MID(F733,4,1))*1 -> 5 | H733: =+MID(B733,1,2)*1 -> 4 | I733: =+MID(B733,3,1) -> E | J733: =HLOOKUP(A733,$O$1:$U$2,2,0) -> MQ200 | K733: =CONCATENATE(A733,B733) -> PC204E5B | L733: =VLOOKUP(K733,'Planilla de control'!#REF!,2,0) -> #REF! | M733: =IF(COUNTIF('Planilla de control'!#REF!,K733)>0,"SI","NO") -> #REF!
A734: PC2 | B734: 04F1C | F734: =IF(OR(LEN(B734)=9,LEN(B734)=5),MID(B734,1,4),MID(B734,1,5)) -> 04F1 | G734: =IF(MID(F734,5,1)<>"",MID(F734,4,2),MID(F734,4,1))*1 -> 1 | H734: =+MID(B734,1,2)*1 -> 4 | I734: =+MID(B734,3,1) -> F | J734: =HLOOKUP(A734,$O$1:$U$2,2,0) -> MQ200 | K734: =CONCATENATE(A734,B734) -> PC204F1C | L734: =VLOOKUP(K734,'Planilla de control'!#REF!,2,0) -> #REF! | M734: =IF(COUNTIF('Planilla de control'!#REF!,K734)>0,"SI","NO") -> #REF!
...

Sheet Plan auditoria y avance
A1: Mes | B1: Dias trabajo | C1: Conteo Buffer | D1: Conteo PT | E1: Dias audit de ubic
A2: Marzo | B2: =GETPIVOTDATA("Cuenta",dias!$P$1,"mes",3) -> 22 | C2: 2 | D2: 2 | E2: =B2-C2-D2 -> 18
A3: Abril | B3: =GETPIVOTDATA("Cuenta",dias!$P$1,"mes",4) -> 19 | C3: 2 | D3: 2 | E3: =B3-C3-D3 -> 15
A5: dias habiles | C5: =GETPIVOTDATA("Cuenta",dias!$U$1,"semana",C11,"mes",3) -> 3 | D5: =GETPIVOTDATA("Cuenta",dias!$U$1,"semana",D11,"mes",3) -> 5 | E5: =GETPIVOTDATA("Cuenta",dias!$U$1,"semana",E11,"mes",3) -> 5 | F5: =GETPIVOTDATA("Cuenta",dias!$U$1,"semana",F11,"mes",3) -> 4 | G5: =GETPIVOTDATA("Cuenta",dias!$U$1,"semana",G11,"mes",3) -> 5 | H5: =GETPIVOTDATA("Cuenta",dias!$U$1,"semana",H11,"mes",4) -> 4 | I5: =GETPIVOTDATA("Cuenta",dias!$U$1,"semana",I11,"mes",4) -> 5 | J5: =GETPIVOTDATA("Cuenta",dias!$U$1,"semana",J11,"mes",4) -> 5 | K5: =GETPIVOTDATA("Cuenta",dias!$U$1,"semana",K11,"mes",4) -> 5 | L5: =GETPIVOTDATA("Cuenta",dias!$U$1,"semana",L11,"mes",4) -> 0
A7: Mes | C7: Marzo | D7: Marzo | E7: Marzo | F7: Marzo | G7: Marzo | H7: Abril | I7: Abril | J7: Abril | K7: Abril | L7: Abril
A8: Dias de conteo | C8: 3 | D8: 5 | E8: 3 | F8: 4 | G8: 3 | H8: 4 | I8: 5 | J8: 4 | K8: 2 | L8: 0
A9: Dias de conteo real | C9: =GETPIVOTDATA("conto?",dias!$K$3,"semana",C11,"mes",3) -> 0 | D9: =GETPIVOTDATA("conto?",dias!$K$3,"semana",D11,"mes",3) -> 0 | E9: =GETPIVOTDATA("conto?",dias!$K$3,"semana",E11,"mes",3) -> 0 | F9: =GETPIVOTDATA("conto?",dias!$K$3,"semana",F11,"mes",3) -> 0 | G9: =GETPIVOTDATA("conto?",dias!$K$3,"semana",G11,"mes",3) -> 0 | H9: =GETPIVOTDATA("conto?",dias!$K$3,"semana",H11,"mes",4) -> 0 | I9: =GETPIVOTDATA("conto?",dias!$K$3,"semana",I11,"mes",4) -> 0 | J9: =GETPIVOTDATA("conto?",dias!$K$3,"semana",J11,"mes",4) -> 0 | K9: =GETPIVOTDATA("conto?",dias!$K$3,"semana",K11,"mes",4) -> 0 | L9: =GETPIVOTDATA("conto?",dias!$K$3,"semana",L11,"mes",4) -> 0
A10: Mes | C10: =A2 -> Marzo | H10: =A3 -> Abril
A11: Semana | B11: Ub total | C11: 9 | D11: 10 | E11: 11 | F11: 12 | G11: 13 | H11: 14 | I11: 15 | J11: 16 | K11: 17 | L11: 18
A12: Planificado | B12: =SUM(Graficos!T9:T19) -> 2810 | C12: =$B$12/SUM($E$2:$E$3)*C8 -> 255.45455 | D12: =$B$12/SUM($E$2:$E$3)*D8 -> 425.75758 | E12: =$B$12/SUM($E$2:$E$3)*E8 -> 255.45455 | F12: =$B$12/SUM($E$2:$E$3)*F8 -> 340.60606 | G12: =$B$12/SUM($E$2:$E$3)*G8 -> 255.45455 | H12: =$B$12/SUM($E$2:$E$3)*H8 -> 340.60606 | I12: =$B$12/SUM($E$2:$E$3)*I8 -> 425.75758 | J12: =$B$12/SUM($E$2:$E$3)*J8 -> 340.60606 | ... L12: =$B$12/SUM($E$2:$E$3)*L8 -> 0
A13: Real | B13: =SUM(C13:L13) -> 0 | C13: =+COUNTIFS(TD!$C:$C,'Plan auditoria y avance'!C11,TD!$A:$A,C7) -> 0 | D13: =+COUNTIFS(TD!$C:$C,'Plan auditoria y avance'!D11,TD!$A:$A,D7) -> 0 | E13: =+COUNTIFS(TD!$C:$C,'Plan auditoria y avance'!E11,TD!$A:$A,E7) -> 0 | F13: =+COUNTIFS(TD!$C:$C,'Plan auditoria y avance'!F11,TD!$A:$A,F7) -> 0 | G13: =+COUNTIFS(TD!$C:$C,'Plan auditoria y avance'!G11,TD!$A:$A,G7) -> 0 | H13: =+COUNTIFS(TD!$C:$C,'Plan auditoria y avance'!H11,TD!$A:$A,H7) -> 0 | I13: =+COUNTIFS(TD!$C:$C,'Plan auditoria y avance'!I11,TD!$A:$A,I7) -> 0 | J13: =+COUNTIFS(TD!$C:$C,'Plan auditoria y avance'!J11,TD!$A:$A,J7) -> 0 | ... L13: =+COUNTIFS(TD!$C:$C,'Plan auditoria y avance'!L11,TD!$A:$A,L7) -> 0
A14: % Cumpl. Semanal | C14: =IFERROR(C13/C12,0) -> 0 | D14: =IFERROR(D13/D12,0) -> 0 | E14: =IFERROR(E13/E12,0) -> 0 | F14: =IFERROR(F13/F12,0) -> 0 | G14: =IFERROR(G13/G12,0) -> 0 | H14: =IFERROR(H13/H12,0) -> 0 | I14: =IFERROR(I13/I12,0) -> 0 | J14: =IFERROR(J13/J12,0) -> 0 | ... L14: =IFERROR(L13/L12,0) -> 0
A15: Plan Acum | C15: =+C12+B15 -> 255.45455 | D15: =+D12+C15 -> 681.21212 | E15: =+E12+D15 -> 936.66667 | F15: =+F12+E15 -> 1277.2727 | G15: =+G12+F15 -> 1532.7273 | H15: =+H12+G15 -> 1873.3333 | I15: =+I12+H15 -> 2299.0909 | J15: =+J12+I15 -> 2639.697 | ... L15: =+L12+K15 -> 2810
A16: % Plan Acum | C16: =+C15/SUM($C$12:$L$12) -> 0.090909091 | D16: =+D15/SUM($C$12:$L$12) -> 0.24242424 | E16: =+E15/SUM($C$12:$L$12) -> 0.33333333 | F16: =+F15/SUM($C$12:$L$12) -> 0.45454545 | G16: =+G15/SUM($C$12:$L$12) -> 0.54545455 | H16: =+H15/SUM($C$12:$L$12) -> 0.66666667 | I16: =+I15/SUM($C$12:$L$12) -> 0.81818182 | J16: =+J15/SUM($C$12:$L$12) -> 0.93939394 | ... L16: =+L15/SUM($C$12:$L$12) -> 1
A17: Real Acum | C17: =+C13+B17 -> 0 | D17: =+D13+C17 -> 0 | E17: =+E13+D17 -> 0 | F17: =+F13+E17 -> 0 | G17: =+G13+F17 -> 0 | H17: =+H13+G17 -> 0 | I17: =+I13+H17 -> 0 | J17: =+J13+I17 -> 0 | ... L17: =+L13+K17 -> 0
A18: % Real Acum | C18: =+C17/SUM($C$12:$L$12) -> 0 | D18: =+D17/SUM($C$12:$L$12) -> 0 | E18: =+E17/SUM($C$12:$L$12) -> 0 | F18: =+F17/SUM($C$12:$L$12) -> 0 | G18: =+G17/SUM($C$12:$L$12) -> 0 | H18: =+H17/SUM($C$12:$L$12) -> 0 | I18: =+I17/SUM($C$12:$L$12) -> 0 | J18: =+J17/SUM($C$12:$L$12) -> 0 | ... L18: =+L17/SUM($C$12:$L$12) -> 0
A19: FALTAN: | C19: =C15-C17 -> 255.45455 | D19: =D15-D17 -> 681.21212 | E19: =E15-E17 -> 936.66667 | F19: =F15-F17 -> 1277.2727 | G19: =G15-G17 -> 1532.7273 | H19: =H15-H17 -> 1873.3333 | I19: =I15-I17 -> 2299.0909 | J19: =J15-J17 -> 2639.697 | ... L19: =L15-L17 -> 2810
A20: % Actual | B20: =B13/B12 -> 0 | C20: =C17/C15 -> 0 | D20: =D17/D15 -> 0 | E20: =E17/E15 -> 0 | F20: =F17/F15 -> 0 | G20: =G17/G15 -> 0 | H20: =H17/H15 -> 0 | I20: =I17/I15 -> 0 | J20: =J17/J15 -> 0 | ... L20: =L17/L15 -> 0
A22: Deposito | B22: =A2 -> Marzo | C22: =A3 -> Abril | D22: =#REF! -> #REF! | E22: Acum | F22: Target
A23: D3 | B23: =IFERROR(COUNTIFS(TD!$B:$B,'Plan auditoria y avance'!$A23,TD!$A:$A,'Plan auditoria y avance'!B$22,TD!$F:$F,">0")/COUNTIFS(TD!$B:$B,'Plan auditoria y avance'!$A23,TD!$A:$A,'Plan auditoria y avance'!B$22),"S/D") -> S/D | C23: =IFERROR(COUNTIFS(TD!$B:$B,'Plan auditoria y avance'!$A23,TD!$A:$A,'Plan auditoria y avance'!C$22,TD!$F:$F,">0")/COUNTIFS(TD!$B:$B,'Plan auditoria y avance'!$A23,TD!$A:$A,'Plan auditoria y avance'!C$22),"S/D") -> S/D | D23: =IFERROR(COUNTIFS(TD!$B:$B,'Plan auditoria y avance'!$A23,TD!$A:$A,'Plan auditoria y avance'!D$22,TD!$F:$F,">0")/COUNTIFS(TD!$B:$B,'Plan auditoria y avance'!$A23,TD!$A:$A,'Plan auditoria y avance'!D$22),"S/D") -> S/D | E23: =IFERROR(COUNTIFS(TD!$B:$B,'Plan auditoria y avance'!A23,TD!$F:$F,">0")/COUNTIF(TD!$B:$B,'Plan auditoria y avance'!A23),"S/D") -> 1 | F23: 0.995
A24: D4 | B24: =IFERROR(COUNTIFS(TD!$B:$B,'Plan auditoria y avance'!$A24,TD!$A:$A,'Plan auditoria y avance'!B$22,TD!$F:$F,">0")/COUNTIFS(TD!$B:$B,'Plan auditoria y avance'!$A24,TD!$A:$A,'Plan auditoria y avance'!B$22),"S/D") -> S/D | C24: =IFERROR(COUNTIFS(TD!$B:$B,'Plan auditoria y avance'!$A24,TD!$A:$A,'Plan auditoria y avance'!C$22,TD!$F:$F,">0")/COUNTIFS(TD!$B:$B,'Plan auditoria y avance'!$A24,TD!$A:$A,'Plan auditoria y avance'!C$22),"S/D") -> S/D | D24: =IFERROR(COUNTIFS(TD!$B:$B,'Plan auditoria y avance'!$A24,TD!$A:$A,'Plan auditoria y avance'!D$22,TD!$F:$F,">0")/COUNTIFS(TD!$B:$B,'Plan auditoria y avance'!$A24,TD!$A:$A,'Plan auditoria y avance'!D$22),"S/D") -> S/D | E24: =IFERROR(COUNTIFS(TD!$B:$B,'Plan auditoria y avance'!A24,TD!$F:$F,">0")/COUNTIF(TD!$B:$B,'Plan auditoria y avance'!A24),"S/D") -> S/D | F24: 0.995
A25: MQ200 | B25: =IFERROR(COUNTIFS(TD!$B:$B,'Plan auditoria y avance'!$A25,TD!$A:$A,'Plan auditoria y avance'!B$22,TD!$F:$F,">0")/COUNTIFS(TD!$B:$B,'Plan auditoria y avance'!$A25,TD!$A:$A,'Plan auditoria y avance'!B$22),"S/D") -> S/D | C25: =IFERROR(COUNTIFS(TD!$B:$B,'Plan auditoria y avance'!$A25,TD!$A:$A,'Plan auditoria y avance'!C$22,TD!$F:$F,">0")/COUNTIFS(TD!$B:$B,'Plan auditoria y avance'!$A25,TD!$A:$A,'Plan auditoria y avance'!C$22),"S/D") -> S/D | D25: =IFERROR(COUNTIFS(TD!$B:$B,'Plan auditoria y avance'!$A25,TD!$A:$A,'Plan auditoria y avance'!D$22,TD!$F:$F,">0")/COUNTIFS(TD!$B:$B,'Plan auditoria y avance'!$A25,TD!$A:$A,'Plan auditoria y avance'!D$22),"S/D") -> S/D | E25: =IFERROR(COUNTIFS(TD!$B:$B,'Plan auditoria y avance'!A25,TD!$F:$F,">0")/COUNTIF(TD!$B:$B,'Plan auditoria y avance'!A25),"S/D") -> S/D | F25: 0.995
A26: MQ250 | B26: =IFERROR(COUNTIFS(TD!$B:$B,'Plan auditoria y avance'!$A26,TD!$A:$A,'Plan auditoria y avance'!B$22,TD!$F:$F,">0")/COUNTIFS(TD!$B:$B,'Plan auditoria y avance'!$A26,TD!$A:$A,'Plan auditoria y avance'!B$22),"S/D") -> S/D | C26: =IFERROR(COUNTIFS(TD!$B:$B,'Plan auditoria y avance'!$A26,TD!$A:$A,'Plan auditoria y avance'!C$22,TD!$F:$F,">0")/COUNTIFS(TD!$B:$B,'Plan auditoria y avance'!$A26,TD!$A:$A,'Plan auditoria y avance'!C$22),"S/D") -> S/D | D26: =IFERROR(COUNTIFS(TD!$B:$B,'Plan auditoria y avance'!$A26,TD!$A:$A,'Plan auditoria y avance'!D$22,TD!$F:$F,">0")/COUNTIFS(TD!$B:$B,'Plan auditoria y avance'!$A26,TD!$A:$A,'Plan auditoria y avance'!D$22),"S/D") -> S/D | E26: =IFERROR(COUNTIFS(TD!$B:$B,'Plan auditoria y avance'!A26,TD!$F:$F,">0")/COUNTIF(TD!$B:$B,'Plan auditoria y avance'!A26),"S/D") -> S/D | F26: 0.995
A27: DUCATI | B27: =IFERROR(COUNTIFS(TD!$B:$B,'Plan auditoria y avance'!$A27,TD!$A:$A,'Plan auditoria y avance'!B$22,TD!$F:$F,">0")/COUNTIFS(TD!$B:$B,'Plan auditoria y avance'!$A27,TD!$A:$A,'Plan auditoria y avance'!B$22),"S/D") -> S/D | C27: =IFERROR(COUNTIFS(TD!$B:$B,'Plan auditoria y avance'!$A27,TD!$A:$A,'Plan auditoria y avance'!C$22,TD!$F:$F,">0")/COUNTIFS(TD!$B:$B,'Plan auditoria y avance'!$A27,TD!$A:$A,'Plan auditoria y avance'!C$22),"S/D") -> S/D | D27: =IFERROR(COUNTIFS(TD!$B:$B,'Plan auditoria y avance'!$A27,TD!$A:$A,'Plan auditoria y avance'!D$22,TD!$F:$F,">0")/COUNTIFS(TD!$B:$B,'Plan auditoria y avance'!$A27,TD!$A:$A,'Plan auditoria y avance'!D$22),"S/D") -> S/D | E27: =IFERROR(COUNTIFS(TD!$B:$B,'Plan auditoria y avance'!A27,TD!$F:$F,">0")/COUNTIF(TD!$B:$B,'Plan auditoria y avance'!A27),"S/D") -> S/D | F27: 0.995
A28: Total | B28: =+COUNTIFS(TD!$A:$A,'Plan auditoria y avance'!B22,TD!$F:$F,">0")/COUNTIF(TD!$A:$A,'Plan auditoria y avance'!B22) -> #DIV/0! | C28: =+COUNTIFS(TD!$A:$A,'Plan auditoria y avance'!C22,TD!$F:$F,">0")/COUNTIF(TD!$A:$A,'Plan auditoria y avance'!C22) -> #DIV/0! | D28: =+COUNTIFS(TD!$A:$A,'Plan auditoria y avance'!D22,TD!$F:$F,">0")/COUNTIF(TD!$A:$A,'Plan auditoria y avance'!D22) -> #DIV/0! | E28: =+COUNTIF(TD!$F:$F,">0")/COUNTA(TD!$A:$A) -> 0.99928876 | F28: 0.995 | G28: =COUNTIFS(TD!$B:$B,'Plan auditoria y avance'!$A28,TD!$A:$A,'Plan auditoria y avance'!B$22,TD!$F:$F,">0") -> 0
C30: =A2 -> Marzo | H30: =A3 -> Abril
B31: Tipo de errores | C31: D3 | D31: D4 | E31: MQ200 | F31: MQ250 | G31: Total | H31: D3 | I31: D4 | J31: MQ200 | K31: MQ250 | L31: Total
B32: Material mal guardado | C32: =+SUMIFS('TD errores'!$D$4:$D$1048576,'TD errores'!$A$4:$A$1048576,$C$30,'TD errores'!$B$4:$B$1048576,C$31) -> 0 | D32: =+SUMIFS('TD errores'!$D$4:$D$1048576,'TD errores'!$A$4:$A$1048576,$C$30,'TD errores'!$B$4:$B$1048576,D$31) -> 0 | E32: =+SUMIFS('TD errores'!$D$4:$D$1048576,'TD errores'!$A$4:$A$1048576,$C$30,'TD errores'!$B$4:$B$1048576,E$31) -> 0 | F32: =+SUMIFS('TD errores'!$D$4:$D$1048576,'TD errores'!$A$4:$A$1048576,$C$30,'TD errores'!$B$4:$B$1048576,F$31) -> 0 | G32: =+SUMIF('TD errores'!$A$4:$A$1048576,$C$30,'TD errores'!$D$4:$D$1048576) -> 0 | H32: =+SUMIFS('TD errores'!$D$4:$D$1048576,'TD errores'!$A$4:$A$1048576,$H$30,'TD errores'!$B$4:$B$1048576,H$31) -> 0 | I32: =+SUMIFS('TD errores'!$D$4:$D$1048576,'TD errores'!$A$4:$A$1048576,$H$30,'TD errores'!$B$4:$B$1048576,I$31) -> 0 | J32: =+SUMIFS('TD errores'!$D$4:$D$1048576,'TD errores'!$A$4:$A$1048576,$H$30,'TD errores'!$B$4:$B$1048576,J$31) -> 0 | K32: =+SUMIFS('TD errores'!$D$4:$D$1048576,'TD errores'!$A$4:$A$1048576,$H$30,'TD errores'!$B$4:$B$1048576,K$31) -> 0 | L32: =+SUMIF('TD errores'!$A$4:$A$1048576,$H$30,'TD errores'!$D$4:$D$1048576) -> 0
B33: Material pagado sin dar de baja | C33: =+SUMIFS('TD errores'!$E$4:$E$1048576,'TD errores'!$A$4:$A$1048576,$C$30,'TD errores'!$B$4:$B$1048576,C$31) -> 0 | D33: =+SUMIFS('TD errores'!$E$4:$E$1048576,'TD errores'!$A$4:$A$1048576,$C$30,'TD errores'!$B$4:$B$1048576,D$31) -> 0 | E33: =+SUMIFS('TD errores'!$E$4:$E$1048576,'TD errores'!$A$4:$A$1048576,$C$30,'TD errores'!$B$4:$B$1048576,E$31) -> 0 | F33: =+SUMIFS('TD errores'!$E$4:$E$1048576,'TD errores'!$A$4:$A$1048576,$C$30,'TD errores'!$B$4:$B$1048576,F$31) -> 0 | G33: =+SUMIF('TD errores'!$A$4:$A$1048576,$C$30,'TD errores'!$E$4:$E$1048576) -> 0 | H33: =+SUMIFS('TD errores'!$E$4:$E$1048576,'TD errores'!$A$4:$A$1048576,$H$30,'TD errores'!$B$4:$B$1048576,H$31) -> 0 | I33: =+SUMIFS('TD errores'!$E$4:$E$1048576,'TD errores'!$A$4:$A$1048576,$H$30,'TD errores'!$B$4:$B$1048576,I$31) -> 0 | J33: =+SUMIFS('TD errores'!$E$4:$E$1048576,'TD errores'!$A$4:$A$1048576,$H$30,'TD errores'!$B$4:$B$1048576,J$31) -> 0 | K33: =+SUMIFS('TD errores'!$E$4:$E$1048576,'TD errores'!$A$4:$A$1048576,$H$30,'TD errores'!$B$4:$B$1048576,K$31) -> 0 | L33: =+SUMIF('TD errores'!$A$4:$A$1048576,$H$30,'TD errores'!$E$4:$E$1048576) -> 0
B34: Error de cantidad | C34: =+SUMIFS('TD errores'!$F$4:$F$1048576,'TD errores'!$A$4:$A$1048576,$C$30,'TD errores'!$B$4:$B$1048576,C$31) -> 0 | D34: =+SUMIFS('TD errores'!$F$4:$F$1048576,'TD errores'!$A$4:$A$1048576,$C$30,'TD errores'!$B$4:$B$1048576,D$31) -> 0 | E34: =+SUMIFS('TD errores'!$F$4:$F$1048576,'TD errores'!$A$4:$A$1048576,$C$30,'TD errores'!$B$4:$B$1048576,E$31) -> 0 | F34: =+SUMIFS('TD errores'!$F$4:$F$1048576,'TD errores'!$A$4:$A$1048576,$C$30,'TD errores'!$B$4:$B$1048576,F$31) -> 0 | G34: =+SUMIF('TD errores'!$A$4:$A$1048576,$C$30,'TD errores'!$F$4:$F$1048576) -> 0 | H34: =+SUMIFS('TD errores'!$F$4:$F$1048576,'TD errores'!$A$4:$A$1048576,$H$30,'TD errores'!$B$4:$B$1048576,H$31) -> 0 | I34: =+SUMIFS('TD errores'!$F$4:$F$1048576,'TD errores'!$A$4:$A$1048576,$H$30,'TD errores'!$B$4:$B$1048576,I$31) -> 0 | J34: =+SUMIFS('TD errores'!$F$4:$F$1048576,'TD errores'!$A$4:$A$1048576,$H$30,'TD errores'!$B$4:$B$1048576,J$31) -> 0 | K34: =+SUMIFS('TD errores'!$F$4:$F$1048576,'TD errores'!$A$4:$A$1048576,$H$30,'TD errores'!$B$4:$B$1048576,K$31) -> 0 | L34: =+SUMIF('TD errores'!$A$4:$A$1048576,$H$30,'TD errores'!$F$4:$F$1048576) -> 0
B35: Material mal identificado | C35: =+SUMIFS('TD errores'!$G$4:$G$1048576,'TD errores'!$A$4:$A$1048576,$C$30,'TD errores'!$B$4:$B$1048576,C$31) -> 0 | D35: =+SUMIFS('TD errores'!$G$4:$G$1048576,'TD errores'!$A$4:$A$1048576,$C$30,'TD errores'!$B$4:$B$1048576,D$31) -> 0 | E35: =+SUMIFS('TD errores'!$G$4:$G$1048576,'TD errores'!$A$4:$A$1048576,$C$30,'TD errores'!$B$4:$B$1048576,E$31) -> 0 | F35: =+SUMIFS('TD errores'!$G$4:$G$1048576,'TD errores'!$A$4:$A$1048576,$C$30,'TD errores'!$B$4:$B$1048576,F$31) -> 0 | G35: =+SUMIF('TD errores'!$A$4:$A$1048576,$C$30,'TD errores'!$G$4:$G$1048576) -> 0 | H35: =+SUMIFS('TD errores'!$G$4:$G$1048576,'TD errores'!$A$4:$A$1048576,$H$30,'TD errores'!$B$4:$B$1048576,H$31) -> 0 | I35: =+SUMIFS('TD errores'!$G$4:$G$1048576,'TD errores'!$A$4:$A$1048576,$H$30,'TD errores'!$B$4:$B$1048576,I$31) -> 0 | J35: =+SUMIFS('TD errores'!$G$4:$G$1048576,'TD errores'!$A$4:$A$1048576,$H$30,'TD errores'!$B$4:$B$1048576,J$31) -> 0 | K35: =+SUMIFS('TD errores'!$G$4:$G$1048576,'TD errores'!$A$4:$A$1048576,$H$30,'TD errores'!$B$4:$B$1048576,K$31) -> 0 | L35: =+SUMIF('TD errores'!$A$4:$A$1048576,$H$30,'TD errores'!$G$4:$G$1048576) -> 0
B36: Material dado de baja | C36: =+SUMIFS('TD errores'!$H$4:$H$1048576,'TD errores'!$A$4:$A$1048576,$C$30,'TD errores'!$B$4:$B$1048576,C$31) -> 0 | D36: =+SUMIFS('TD errores'!$H$4:$H$1048576,'TD errores'!$A$4:$A$1048576,$C$30,'TD errores'!$B$4:$B$1048576,D$31) -> 0 | E36: =+SUMIFS('TD errores'!$H$4:$H$1048576,'TD errores'!$A$4:$A$1048576,$C$30,'TD errores'!$B$4:$B$1048576,E$31) -> 0 | F36: =+SUMIFS('TD errores'!$H$4:$H$1048576,'TD errores'!$A$4:$A$1048576,$C$30,'TD errores'!$B$4:$B$1048576,F$31) -> 0 | G36: =+SUMIF('TD errores'!$A$4:$A$1048576,$C$30,'TD errores'!$H$4:$H$1048576) -> 0 | H36: =+SUMIFS('TD errores'!$H$4:$H$1048576,'TD errores'!$A$4:$A$1048576,$H$30,'TD errores'!$B$4:$B$1048576,H$31) -> 0 | I36: =+SUMIFS('TD errores'!$H$4:$H$1048576,'TD errores'!$A$4:$A$1048576,$H$30,'TD errores'!$B$4:$B$1048576,I$31) -> 0 | J36: =+SUMIFS('TD errores'!$H$4:$H$1048576,'TD errores'!$A$4:$A$1048576,$H$30,'TD errores'!$B$4:$B$1048576,J$31) -> 0 | K36: =+SUMIFS('TD errores'!$H$4:$H$1048576,'TD errores'!$A$4:$A$1048576,$H$30,'TD errores'!$B$4:$B$1048576,K$31) -> 0 | L36: =+SUMIF('TD errores'!$A$4:$A$1048576,$H$30,'TD errores'!$H$4:$H$1048576) -> 0
A40: Objetivo | B40: Rotulo de categoria | C40: Valor | D40: Total
A41: 5 | B41: 0.9 | C41: 9.5 | D41: =+(E28-B41)*100 -> 9.9288762
A42: 4.5 | B42: 0.995 | C42: 0.5 | D42: 0.05
A43: 0.5 | C43: 10 | D43: =10-D41-D42 -> 0.021123755
A44: 10 | D44: 10

Sheet Graficos
A1: Mes | B1: Dias trabajo | C1: Conteo Buffer | D1: Conteo PT | E1: Dias audit de ubic
A2: SEPTIEMBRE | B2: 17 | C2: 5 | D2: 2 | E2: =B2-C2-D2 -> 10 | F2: =SUM(E2:E3) -> 20 | U2: AUDITORÍA DE UBICACIONES 2025 | AD2: DICIEMBRE | AR2: AUDITORÍA DE UBICACIONES 2025
A3: OCTUBRE | B3: 17 | C3: 5 | D3: 2 | E3: =B3-C3-D3 -> 10
A5: dias habiles | C5: =GETPIVOTDATA("Cuenta",dias!$U$1,"semana",C11,"mes",C7) -> #REF! | D5: =GETPIVOTDATA("Cuenta",dias!$U$1,"semana",D11,"mes",D7) -> #REF! | E5: =GETPIVOTDATA("Cuenta",dias!$U$1,"semana",E11,"mes",E7) -> #REF! | F5: =GETPIVOTDATA("Cuenta",dias!$U$1,"semana",F11,"mes",F7) -> #REF! | G5: =GETPIVOTDATA("Cuenta",dias!$U$1,"semana",G11,"mes",G7) -> #REF! | H5: =GETPIVOTDATA("Cuenta",dias!$U$1,"semana",H11,"mes",H7) -> #REF! | I5: =GETPIVOTDATA("Cuenta",dias!$U$1,"semana",I11,"mes",I7) -> #REF! | J5: =GETPIVOTDATA("Cuenta",dias!$U$1,"semana",J11,"mes",J7) -> #REF! | ... L5: =GETPIVOTDATA("Cuenta",dias!$U$1,"semana",L11,"mes",L7) -> #REF!
N6: 200 | O6: 1 | S6: Avance por Deposito
A7: Mes | C7: 3 | D7: 3 | E7: 3 | F7: 3 | G7: 4 | H7: 4 | I7: 4 | J7: 4 | K7: 4 | L7: 4 | N7: =T19 -> 1405 | O7: =+N7*O6/N6 -> 7.025
A8: Dias de conteo | C8: 5 | D8: 4 | E8: 3 | F8: 1 | G8: 2 | H8: 1 | I8: 2 | J8: 1 | K8: 1 | L8: 0 | S8: Deposito | T8: Ubicaciones | U8: Status | Y8: CONTROL | Z8: ERRORES
A9: Dias de conteo real | C9: =GETPIVOTDATA("conto?",dias!$K$3,"semana",C11) -> 0 | D9: =GETPIVOTDATA("conto?",dias!$K$3,"semana",D11,"mes",3) -> #REF! | E9: =GETPIVOTDATA("conto?",dias!$K$3,"semana",E11,"mes",3) -> #REF! | F9: =GETPIVOTDATA("conto?",dias!$K$3,"semana",F11,"mes",3) -> #REF! | G9: =GETPIVOTDATA("conto?",dias!$K$3,"semana",G11,"mes",3) -> #REF! | H9: =GETPIVOTDATA("conto?",dias!$K$3,"semana",H11,"mes",4) -> #REF! | I9: =GETPIVOTDATA("conto?",dias!$K$3,"semana",I11,"mes",4) -> #REF! | J9: =GETPIVOTDATA("conto?",dias!$K$3,"semana",J11,"mes",4) -> #REF! | K9: =GETPIVOTDATA("conto?",dias!$K$3,"semana",K11,"mes",4) -> #REF! | L9: =GETPIVOTDATA("conto?",dias!$K$3,"semana",L11,"mes",4) -> #REF! | S9: D3 | T9: 1405 | U9: =+COUNTIF(TD!$B:$B,Graficos!$S$9)/$T$9 -> 1 | Y9: =COUNTIF(TD!B:B,S9) -> 1405 | Z9: =SUM(C34:C39) -> 2
A10: Mes | C10: NOVIEMBRE | G10: DICIEMBRE
A11: Semana | B11: Ub total | C11: 45 | D11: =1+C11 -> 46 | E11: =1+D11 -> 47 | F11: =1+E11 -> 48 | G11: =1+F11 -> 49 | H11: =1+G11 -> 50 | I11: =1+H11 -> 51 | J11: =1+I11 -> 52 | K11: =1+J11 -> 53 | L11: =1+K11 -> 54 | S11: D4 | T11: 0 | U11: =+COUNTIF(TD!$B:$B,Graficos!$S$11)/$T$11 -> #DIV/0! | Y11: =COUNTIF(TD!B:B,S11) -> 0 | Z11: =SUM(D34:D39) -> 0
A12: Planificado | B12: =SUM(Graficos!T9:T18) -> 1405 | C12: =$B$12/SUM($E$2:$E$3)*C8 -> 351.25 | D12: =$B$12/SUM($E$2:$E$3)*D8 -> 281 | E12: =$B$12/SUM($E$2:$E$3)*E8 -> 210.75 | F12: =$B$12/SUM($E$2:$E$3)*F8 -> 70.25 | G12: =$B$12/SUM($E$2:$E$3)*G8 -> 140.5 | H12: =$B$12/SUM($E$2:$E$3)*H8 -> 70.25 | I12: =$B$12/SUM($E$2:$E$3)*I8 -> 140.5 | J12: =$B$12/SUM($E$2:$E$3)*J8 -> 70.25 | ... L12: =$B$12/SUM($E$2:$E$3)*L8 -> 0
A13: Real | B13: =SUM(C13:L13) -> 0 | C13: =+COUNTIFS(TD!$C:$C,C11) -> 0 | D13: =+COUNTIFS(TD!$C:$C,D11) -> 0 | E13: =+COUNTIFS(TD!$C:$C,E11) -> 0 | F13: =+COUNTIFS(TD!$C:$C,F11) -> 0 | G13: =+COUNTIFS(TD!$C:$C,G11) -> 0 | H13: =+COUNTIFS(TD!$C:$C,H11) -> 0 | I13: =+COUNTIFS(TD!$C:$C,I11) -> 0 | J13: =+COUNTIFS(TD!$C:$C,J11) -> 0 | ... L13: =+COUNTIFS(TD!$C:$C,L11) -> 0 | S13: MQ200 | T13: 0 | U13: =+COUNTIF(TD!$B:$B,Graficos!$S$13)/$T$13 -> #DIV/0! | Y13: =COUNTIF(TD!B:B,S13) -> 0 | Z13: =SUM(E34:E39) -> 0
A14: % Cumpl. Semanal | C14: =IFERROR(C13/C12,0) -> 0 | D14: =IFERROR(D13/D12,0) -> 0 | E14: =IFERROR(E13/E12,0) -> 0 | F14: =IFERROR(F13/F12,0) -> 0 | G14: =IFERROR(G13/G12,0) -> 0 | H14: =IFERROR(H13/H12,0) -> 0 | I14: =IFERROR(I13/I12,0) -> 0 | J14: =IFERROR(J13/J12,0) -> 0 | ... L14: =IFERROR(L13/L12,0) -> 0
A15: Plan Acum | C15: =+C12+B15 -> 351.25 | D15: =+D12+C15 -> 632.25 | E15: =+E12+D15 -> 843 | F15: =+F12+E15 -> 913.25 | G15: =+G12+F15 -> 1053.75 | H15: =+H12+G15 -> 1124 | I15: =+I12+H15 -> 1264.5 | J15: =+J12+I15 -> 1334.75 | ... L15: =+L12+K15 -> 1405 | S15: DUCATI | T15: 0 | U15: =+COUNTIF(TD!$B:$B,Graficos!$S$15)/$T$15 -> #DIV/0! | Y15: =COUNTIF(TD!B:B,S15) -> 0 | Z15: =SUM(F34:F39) -> 0
A16: % Plan Acum | C16: =+C15/SUM($C$12:$L$12) -> 0.25 | D16: =+D15/SUM($C$12:$L$12) -> 0.45 | E16: =+E15/SUM($C$12:$L$12) -> 0.6 | F16: =+F15/SUM($C$12:$L$12) -> 0.65 | G16: =+G15/SUM($C$12:$L$12) -> 0.75 | H16: =+H15/SUM($C$12:$L$12) -> 0.8 | I16: =+I15/SUM($C$12:$L$12) -> 0.9 | J16: =+J15/SUM($C$12:$L$12) -> 0.95 | ... L16: =+L15/SUM($C$12:$L$12) -> 1
A17: Real Acum | C17: =+C13+B17 -> 0 | D17: =+D13+C17 -> 0 | E17: =+E13+D17 -> 0 | F17: =+F13+E17 -> 0 | G17: =+G13+F17 -> 0 | H17: =+H13+G17 -> 0 | I17: =+I13+H17 -> 0 | J17: =+J13+I17 -> 0 | ... L17: =+L13+K17 -> 0 | N17: lx | S17: CAMIONES | T17: 0 | U17: =+COUNTIF(TD!$B:$B,Graficos!$S$17)/$T$17 -> #DIV/0! | Y17: =COUNTIF(TD!B:B,S17) -> 0 | Z17: =SUM(G34:G39) -> 0
A18: % Real Acum | C18: =+C17/SUM($C$12:$L$12) -> 0 | D18: =+D17/SUM($C$12:$L$12) -> 0 | E18: =+E17/SUM($C$12:$L$12) -> 0 | F18: =+F17/SUM($C$12:$L$12) -> 0 | G18: =+G17/SUM($C$12:$L$12) -> 0 | H18: =+H17/SUM($C$12:$L$12) -> 0 | I18: =+I17/SUM($C$12:$L$12) -> 0 | J18: =+J17/SUM($C$12:$L$12) -> 0 | ... L18: =+L17/SUM($C$12:$L$12) -> 0
S19: TOTAL: | T19: =SUM(T9:T18) -> 1405 | U19: =Y19/$T$19 -> 1 | Y19: =SUM(Y9:Y18) -> 1405 | Z19: =SUM(Z9:Z18) -> 2
A21: FALTAN: | C21: =C15-C17 -> 351.25 | D21: =D15-D17 -> 632.25 | E21: =E15-E17 -> 843 | F21: =F15-F17 -> 913.25 | G21: =G15-G17 -> 1053.75 | H21: =H15-H17 -> 1124 | I21: =I15-I17 -> 1264.5 | J21: =J15-J17 -> 1334.75 | ... L21: =L15-L17 -> 1405
A22: % Actual | B22: =B13/B12 -> 0 | C22: =C17/C15 -> 0 | D22: =D17/D15 -> 0 | E22: =E17/E15 -> 0 | F22: =F17/F15 -> 0 | G22: =G17/G15 -> 0 | H22: =H17/H15 -> 0 | I22: =I17/I15 -> 0 | J22: =J17/J15 -> 0 | ... L22: =L17/L15 -> 0
A24: Deposito | B24: =A2 -> SEPTIEMBRE | C24: =A3 -> OCTUBRE | D24: IRA | E24: ILA | F24: Target
A25: D3 | B25: =IFERROR(COUNTIFS(TD!$B:$B,Graficos!$A25,TD!$A:$A,Graficos!B$24,TD!$F:$F,">0")/COUNTIFS(TD!$B:$B,Graficos!$A25,TD!$A:$A,Graficos!B$24),"S/D") -> S/D | C25: =IFERROR(COUNTIFS(TD!$B:$B,Graficos!$A25,TD!$A:$A,Graficos!C$24,TD!$F:$F,">0")/COUNTIFS(TD!$B:$B,Graficos!$A25,TD!$A:$A,Graficos!C$24),"S/D") -> S/D | D25: =IFERROR(1-(C40/Y9),"S/D") -> 0.99857651 | E25: =(Y9-C41)/Y9 -> 0.99857651 | F25: 0.995
A26: D4 | B26: =IFERROR(COUNTIFS(TD!$B:$B,Graficos!$A26,TD!$A:$A,Graficos!B$24,TD!$F:$F,">0")/COUNTIFS(TD!$B:$B,Graficos!$A26,TD!$A:$A,Graficos!B$24),"S/D") -> S/D | C26: =IFERROR(COUNTIFS(TD!$B:$B,Graficos!$A26,TD!$A:$A,Graficos!C$24,TD!$F:$F,">0")/COUNTIFS(TD!$B:$B,Graficos!$A26,TD!$A:$A,Graficos!C$24),"S/D") -> S/D | D26: =IFERROR(1-(D40/Y11),"S/D") -> S/D | E26: =(Y11-D41)/Y11 -> #DIV/0! | F26: 0.995
A27: MQ200 | B27: =IFERROR(COUNTIFS(TD!$B:$B,Graficos!$A27,TD!$A:$A,Graficos!B$24,TD!$F:$F,">0")/COUNTIFS(TD!$B:$B,Graficos!$A27,TD!$A:$A,Graficos!B$24),"S/D") -> S/D | C27: =IFERROR(COUNTIFS(TD!$B:$B,Graficos!$A27,TD!$A:$A,Graficos!C$24,TD!$F:$F,">0")/COUNTIFS(TD!$B:$B,Graficos!$A27,TD!$A:$A,Graficos!C$24),"S/D") -> S/D | D27: =IFERROR(1-(E40/Y13),"S/D") -> S/D | E27: =(Y13-E41)/Y13 -> #DIV/0! | F27: 0.995
A28: DUCATI | B28: =IFERROR(COUNTIFS(TD!$B:$B,Graficos!$A28,TD!$A:$A,Graficos!B$24,TD!$F:$F,">0")/COUNTIFS(TD!$B:$B,Graficos!$A28,TD!$A:$A,Graficos!B$24),"S/D") -> S/D | C28: =IFERROR(COUNTIFS(TD!$B:$B,Graficos!$A28,TD!$A:$A,Graficos!C$24,TD!$F:$F,">0")/COUNTIFS(TD!$B:$B,Graficos!$A28,TD!$A:$A,Graficos!C$24),"S/D") -> S/D | D28: =IFERROR(1-(F40/Y15),"S/D") -> S/D | E28: =(Y15-F41)/Y15 -> #DIV/0! | F28: 0.995
A29: CAMIONES | B29: =IFERROR(COUNTIFS(TD!$B:$B,Graficos!$A29,TD!$A:$A,Graficos!B$24,TD!$F:$F,">0")/COUNTIFS(TD!$B:$B,Graficos!$A29,TD!$A:$A,Graficos!B$24),"S/D") -> S/D | C29: =IFERROR(COUNTIFS(TD!$B:$B,Graficos!$A29,TD!$A:$A,Graficos!C$24,TD!$F:$F,">0")/COUNTIFS(TD!$B:$B,Graficos!$A29,TD!$A:$A,Graficos!C$24),"S/D") -> S/D | D29: =IFERROR(1-(G40/Y17),"S/D") -> S/D | E29: =(Y17-G41)/Y17 -> #DIV/0! | F29: 0.995
A30: Total | B30: =+COUNTIFS(TD!$A:$A,Graficos!B24,TD!$F:$F,">0")/COUNTIF(TD!$A:$A,Graficos!B24) -> #DIV/0! | C30: =+COUNTIFS(TD!$A:$A,Graficos!C24,TD!$F:$F,">0")/COUNTIF(TD!$A:$A,Graficos!C24) -> #DIV/0! | D30: =1-(H40/Y19) -> 0.99857651 | E30: =(Y19-H41)/Y19 -> 0.99857651 | F30: 0.995 | G30: =COUNTIFS(TD!$B:$B,'Plan auditoria y avance'!$A28,TD!$A:$A,'Plan auditoria y avance'!B$22,TD!$F:$F,">0") -> 0
B33: Tipo de errores | C33: D3 | D33: D4 | E33: MQ200 | F33: DUCATI | G33: CAMIONES | H33: Total | I33: D3 | J33: D4 | K33: MQ200 | L33: MQ250 | M33: DUCATI | N33: CAMIONES | O33: Total
B34: Material mal guardado | C34: =+SUMIFS('TD errores'!$D$4:$D$1048576,'TD errores'!$B$4:$B$1048576,C$33) -> 0 | D34: =+SUMIFS('TD errores'!$D$4:$D$1048576,'TD errores'!$B$4:$B$1048576,D$33) -> 0 | E34: =+SUMIFS('TD errores'!$D$4:$D$1048576,'TD errores'!$B$4:$B$1048576,E$33) -> 0 | F34: =+SUMIFS('TD errores'!$D$4:$D$1048576,'TD errores'!$B$4:$B$1048576,F$33) -> 0 | G34: =+SUMIFS('TD errores'!$D$4:$D$1048576,'TD errores'!$B$4:$B$1048576,G$33) -> 0 | H34: =SUM(C34:G34) -> 0 | I34: =+SUMIFS('TD errores'!$D$4:$D$1048576,'TD errores'!$A$4:$A$1048576,$I$32,'TD errores'!$B$4:$B$1048576,I$33) -> 0 | J34: =+SUMIFS('TD errores'!$D$4:$D$1048576,'TD errores'!$A$4:$A$1048576,$I$32,'TD errores'!$B$4:$B$1048576,J$33) -> 0 | K34: =+SUMIFS('TD errores'!$D$4:$D$1048576,'TD errores'!$A$4:$A$1048576,$I$32,'TD errores'!$B$4:$B$1048576,K$33) -> 0 | L34: =+SUMIFS('TD errores'!$D$4:$D$1048576,'TD errores'!$A$4:$A$1048576,$I$32,'TD errores'!$B$4:$B$1048576,L$33) -> 0 | M34: =+SUMIFS('TD errores'!$D$4:$D$1048576,'TD errores'!$A$4:$A$1048576,$I$32,'TD errores'!$B$4:$B$1048576,M$33) -> 0 | N34: =+SUMIFS('TD errores'!$D$4:$D$1048576,'TD errores'!$A$4:$A$1048576,$I$32,'TD errores'!$B$4:$B$1048576,N$33) -> 0 | O34: =+SUMIF('TD errores'!$A$4:$A$1048576,$I$32,'TD errores'!$D$4:$D$1048576) -> 0
B35: Material pagado sin dar de baja | C35: =+SUMIFS('TD errores'!$E$4:$E$1048576,'TD errores'!$B$4:$B$1048576,C$33) -> 1 | D35: =+SUMIFS('TD errores'!$E$4:$E$1048576,'TD errores'!$B$4:$B$1048576,D$33) -> 0 | E35: =+SUMIFS('TD errores'!$E$4:$E$1048576,'TD errores'!$B$4:$B$1048576,E$33) -> 0 | F35: =+SUMIFS('TD errores'!$E$4:$E$1048576,'TD errores'!$B$4:$B$1048576,F$33) -> 0 | G35: =+SUMIFS('TD errores'!$E$4:$E$1048576,'TD errores'!$B$4:$B$1048576,G$33) -> 0 | H35: =SUM(C35:G35) -> 1 | I35: =+SUMIFS('TD errores'!$E$4:$E$1048576,'TD errores'!$A$4:$A$1048576,$I$32,'TD errores'!$B$4:$B$1048576,I$33) -> 0 | J35: =+SUMIFS('TD errores'!$E$4:$E$1048576,'TD errores'!$A$4:$A$1048576,$I$32,'TD errores'!$B$4:$B$1048576,J$33) -> 0 | K35: =+SUMIFS('TD errores'!$E$4:$E$1048576,'TD errores'!$A$4:$A$1048576,$I$32,'TD errores'!$B$4:$B$1048576,K$33) -> 0 | L35: =+SUMIFS('TD errores'!$E$4:$E$1048576,'TD errores'!$A$4:$A$1048576,$I$32,'TD errores'!$B$4:$B$1048576,L$33) -> 0 | M35: =+SUMIFS('TD errores'!$E$4:$E$1048576,'TD errores'!$A$4:$A$1048576,$I$32,'TD errores'!$B$4:$B$1048576,M$33) -> 0 | N35: =+SUMIFS('TD errores'!$E$4:$E$1048576,'TD errores'!$A$4:$A$1048576,$I$32,'TD errores'!$B$4:$B$1048576,N$33) -> 0 | O35: =+SUMIF('TD errores'!$A$4:$A$1048576,$I$32,'TD errores'!$E$4:$E$1048576) -> 0
B36: Error de cantidad | C36: =+SUMIFS('TD errores'!$F$4:$F$1048576,'TD errores'!$B$4:$B$1048576,C$33) -> 1 | D36: =+SUMIFS('TD errores'!$F$4:$F$1048576,'TD errores'!$B$4:$B$1048576,D$33) -> 0 | E36: =+SUMIFS('TD errores'!$F$4:$F$1048576,'TD errores'!$B$4:$B$1048576,E$33) -> 0 | F36: =+SUMIFS('TD errores'!$F$4:$F$1048576,'TD errores'!$B$4:$B$1048576,F$33) -> 0 | G36: =+SUMIFS('TD errores'!$F$4:$F$1048576,'TD errores'!$B$4:$B$1048576,G$33) -> 0 | H36: =SUM(C36:G36) -> 1 | I36: =+SUMIFS('TD errores'!$F$4:$F$1048576,'TD errores'!$A$4:$A$1048576,$I$32,'TD errores'!$B$4:$B$1048576,I$33) -> 0 | J36: =+SUMIFS('TD errores'!$F$4:$F$1048576,'TD errores'!$A$4:$A$1048576,$I$32,'TD errores'!$B$4:$B$1048576,J$33) -> 0 | K36: =+SUMIFS('TD errores'!$F$4:$F$1048576,'TD errores'!$A$4:$A$1048576,$I$32,'TD errores'!$B$4:$B$1048576,K$33) -> 0 | L36: =+SUMIFS('TD errores'!$F$4:$F$1048576,'TD errores'!$A$4:$A$1048576,$I$32,'TD errores'!$B$4:$B$1048576,L$33) -> 0 | M36: =+SUMIFS('TD errores'!$F$4:$F$1048576,'TD errores'!$A$4:$A$1048576,$I$32,'TD errores'!$B$4:$B$1048576,M$33) -> 0 | N36: =+SUMIFS('TD errores'!$F$4:$F$1048576,'TD errores'!$A$4:$A$1048576,$I$32,'TD errores'!$B$4:$B$1048576,N$33) -> 0 | O36: =+SUMIF('TD errores'!$A$4:$A$1048576,$I$32,'TD errores'!$F$4:$F$1048576) -> 0
B37: Material mal identificado | C37: =+SUMIFS('TD errores'!$G$4:$G$1048576,'TD errores'!$B$4:$B$1048576,C$33) -> 0 | D37: =+SUMIFS('TD errores'!$G$4:$G$1048576,'TD errores'!$B$4:$B$1048576,D$33) -> 0 | E37: =+SUMIFS('TD errores'!$G$4:$G$1048576,'TD errores'!$B$4:$B$1048576,E$33) -> 0 | F37: =+SUMIFS('TD errores'!$G$4:$G$1048576,'TD errores'!$B$4:$B$1048576,F$33) -> 0 | G37: =+SUMIFS('TD errores'!$G$4:$G$1048576,'TD errores'!$B$4:$B$1048576,G$33) -> 0 | H37: =SUM(C37:G37) -> 0 | I37: =+SUMIFS('TD errores'!$G$4:$G$1048576,'TD errores'!$A$4:$A$1048576,$I$32,'TD errores'!$B$4:$B$1048576,I$33) -> 0 | J37: =+SUMIFS('TD errores'!$G$4:$G$1048576,'TD errores'!$A$4:$A$1048576,$I$32,'TD errores'!$B$4:$B$1048576,J$33) -> 0 | K37: =+SUMIFS('TD errores'!$G$4:$G$1048576,'TD errores'!$A$4:$A$1048576,$I$32,'TD errores'!$B$4:$B$1048576,K$33) -> 0 | L37: =+SUMIFS('TD errores'!$G$4:$G$1048576,'TD errores'!$A$4:$A$1048576,$I$32,'TD errores'!$B$4:$B$1048576,L$33) -> 0 | M37: =+SUMIFS('TD errores'!$G$4:$G$1048576,'TD errores'!$A$4:$A$1048576,$I$32,'TD errores'!$B$4:$B$1048576,M$33) -> 0 | N37: =+SUMIFS('TD errores'!$G$4:$G$1048576,'TD errores'!$A$4:$A$1048576,$I$32,'TD errores'!$B$4:$B$1048576,N$33) -> 0 | O37: =+SUMIF('TD errores'!$A$4:$A$1048576,$I$32,'TD errores'!$G$4:$G$1048576) -> 0
B38: Material dado de baja | C38: =+SUMIFS('TD errores'!$H$4:$H$1048576,'TD errores'!$B$4:$B$1048576,C$33) -> 0 | D38: =+SUMIFS('TD errores'!$H$4:$H$1048576,'TD errores'!$B$4:$B$1048576,D$33) -> 0 | E38: =+SUMIFS('TD errores'!$H$4:$H$1048576,'TD errores'!$B$4:$B$1048576,E$33) -> 0 | F38: =+SUMIFS('TD errores'!$H$4:$H$1048576,'TD errores'!$B$4:$B$1048576,F$33) -> 0 | G38: =+SUMIFS('TD errores'!$H$4:$H$1048576,'TD errores'!$B$4:$B$1048576,G$33) -> 0 | H38: =SUM(C38:G38) -> 0 | I38: =+SUMIFS('TD errores'!$H$4:$H$1048576,'TD errores'!$A$4:$A$1048576,$I$32,'TD errores'!$B$4:$B$1048576,I$33) -> 0 | J38: =+SUMIFS('TD errores'!$H$4:$H$1048576,'TD errores'!$A$4:$A$1048576,$I$32,'TD errores'!$B$4:$B$1048576,J$33) -> 0 | K38: =+SUMIFS('TD errores'!$H$4:$H$1048576,'TD errores'!$A$4:$A$1048576,$I$32,'TD errores'!$B$4:$B$1048576,K$33) -> 0 | L38: =+SUMIFS('TD errores'!$H$4:$H$1048576,'TD errores'!$A$4:$A$1048576,$I$32,'TD errores'!$B$4:$B$1048576,L$33) -> 0 | M38: =+SUMIFS('TD errores'!$H$4:$H$1048576,'TD errores'!$A$4:$A$1048576,$I$32,'TD errores'!$B$4:$B$1048576,M$33) -> 0 | N38: =+SUMIFS('TD errores'!$H$4:$H$1048576,'TD errores'!$A$4:$A$1048576,$I$32,'TD errores'!$B$4:$B$1048576,N$33) -> 0 | O38: =+SUMIF('TD errores'!$A$4:$A$1048576,$I$32,'TD errores'!$H$4:$H$1048576) -> 0
B39: Material no confirmado | C39: =+SUMIFS('TD errores'!$I$4:$I$1048576,'TD errores'!$B$4:$B$1048576,C$33) -> 0 | D39: =+SUMIFS('TD errores'!$I$4:$I$1048576,'TD errores'!$B$4:$B$1048576,D$33) -> 0 | E39: =+SUMIFS('TD errores'!$I$4:$I$1048576,'TD errores'!$B$4:$B$1048576,E$33) -> 0 | F39: =+SUMIFS('TD errores'!$I$4:$I$1048576,'TD errores'!$B$4:$B$1048576,F$33) -> 0 | G39: =+SUMIFS('TD errores'!$I$4:$I$1048576,'TD errores'!$B$4:$B$1048576,G$33) -> 0 | H39: =SUM(C39:G39) -> 0 | I39: =+SUMIFS('TD errores'!$H$4:$H$1048576,'TD errores'!$A$4:$A$1048576,$I$32,'TD errores'!$B$4:$B$1048576,I$33) -> 0 | J39: =+SUMIFS('TD errores'!$H$4:$H$1048576,'TD errores'!$A$4:$A$1048576,$I$32,'TD errores'!$B$4:$B$1048576,J$33) -> 0 | K39: =+SUMIFS('TD errores'!$H$4:$H$1048576,'TD errores'!$A$4:$A$1048576,$I$32,'TD errores'!$B$4:$B$1048576,K$33) -> 0 | L39: =+SUMIFS('TD errores'!$H$4:$H$1048576,'TD errores'!$A$4:$A$1048576,$I$32,'TD errores'!$B$4:$B$1048576,L$33) -> 0 | M39: =+SUMIFS('TD errores'!$H$4:$H$1048576,'TD errores'!$A$4:$A$1048576,$I$32,'TD errores'!$B$4:$B$1048576,M$33) -> 0 | N39: =+SUMIFS('TD errores'!$H$4:$H$1048576,'TD errores'!$A$4:$A$1048576,$I$32,'TD errores'!$B$4:$B$1048576,N$33) -> 0 | O39: =+SUMIF('TD errores'!$A$4:$A$1048576,$I$32,'TD errores'!$H$4:$H$1048576) -> 0 | AR39: ENE | AS39: FEB | AT39: MAR | AU39: ABR | AV39: MAY | AW39: JUN | AX39: JUL | AY39: AGO | AZ39: SEP | BA39: OCT | BB39: NOV | BC39: DIC | BD39: 2025
A40: ERRORES | B40: IRA | C40: =SUM(C35:C39) -> 2 | D40: =SUM(D35:D39) -> 0 | E40: =SUM(E35:E39) -> 0 | F40: =SUM(F35:F39) -> 0 | G40: =SUM(G35:G39) -> 0 | H40: =SUM(H35:H39) -> 2 | I40: Inventory Récord Accuracy | AO40: INTEGRIDAD ILA: | AR40: 0.998 | AS40: 0.998 | AT40: 0.998 | AU40: 0.997 | AV40: 0.998 | AW40: 0.997 | AX40: 0.997 | AY40: 0.995 | AZ40: =E30 -> 0.99857651 | BA40: 0.99649825 | BB40: 0.998 | BC40: =E30 -> 0.99857651 | BD40: =AVERAGE(AR40:BC40) -> 0.99747094 | BE40: Inventory Location Accuracy
B41: ILA | C41: =SUM(C34:C39) -> 2 | D41: =SUM(D34:D39) -> 0 | E41: =SUM(E34:E39) -> 0 | F41: =SUM(F34:F39) -> 0 | G41: =SUM(G34:G39) -> 0 | H41: =SUM(H34:H39) -> 2 | I41: Inventory Location Accuracy | BE41: El material está en la ubicación correspondiente
A42: Objetivo | B42: Rotulo de categoria | C42: Valor | D42: Total | AO42: INTEGRIDAD IRA: | AR42: 0.998 | AS42: 0.998 | AT42: 0.998 | AU42: 0.997 | AV42: 0.998 | AW42: 0.998 | AX42: 0.997 | AY42: 0.995 | AZ42: =D30 -> 0.99857651 | BA42: 0.99649825 | BB42: 0.998 | BC42: =D30 -> 0.99857651 | BD42: =AVERAGE(AR42:BC42) -> 0.99755427 | BE42: Inventory Récord Accuracy
A43: 5 | B43: 0.9 | C43: 9.5 | D43: =+(E30-B43)*100 -> 9.8576512 | BE43: El material está, no importa donde
A44: 4.5 | B44: 0.995 | C44: 0.5 | D44: 0.05 | AO44: TARGET: | AR44: 0.995 | AS44: 0.995 | AT44: 0.995 | AU44: 0.995 | AV44: 0.995 | AW44: 0.995 | AX44: 0.995 | AY44: 0.995 | AZ44: 0.995 | BA44: 0.995 | BB44: 0.995 | BC44: 0.995 | BD44: 0.995
A45: 0.5 | C45: 10 | D45: =10-D43-D44 -> 0.092348754
A46: 10 | D46: 10 | S46: Actualizado: | T46: =TODAY() -> 46148
BA49: ACURACIDAD: precisión y exactitud de un fenómeno
S52: STOCK VALORIZADO: | U52: =SUM('Planilla de control'!#REF!) -> #REF!
S53: NO ENCONTRADO: | U53: =SUM('Planilla de control'!#REF!)*-1 -> #REF! | V53: =U53/U52 -> #REF! | X53: =1+V53 -> #REF!
S54: SOBRANTES: | U54: =SUM('Planilla de control'!#REF!) -> #REF! | V54: =U54/U52 -> #REF! | X54: =1-V54 -> #REF!
S63: MQ250 | T63: 74 | U63: =+COUNTIF(TD!$B:$B,Graficos!$S$63)/$T$63 -> 0 | Y63: =COUNTIF(TD!B:B,S63) -> 0 | Z63: =SUM(#REF!) -> #REF!
A104: Deposito | B104: C. inicial | C104: 1er conteo | D104: 2do conteo | E104: 3do conteo | F104: Target
A105: D3 | B105: 0.997 | C105: 0.98905247 | D105: 0.99587315 | E105: =+'Plan auditoria y avance'!E23 -> 1 | F105: 0.995
A106: D4 | B106: 0.986 | C106: 0.98031496 | D106: 0.96992481 | E106: =+'Plan auditoria y avance'!E24 -> S/D | F106: 0.995
A107: MQ200 | B107: 0.983 | C107: 0.98798283 | D107: 0.98417722 | E107: =+'Plan auditoria y avance'!E25 -> S/D | F107: 0.995
A108: DUCATI | B108: S/D | C108: S/D | D108: S/D | E108: =+'Plan auditoria y avance'!E26 -> S/D | F108: 0.995
A109: MQ250 | B109: 0.92 | C109: 0.95974329 | D109: 0.98361522 | E109: =+'Plan auditoria y avance'!E26 -> S/D | F109: 0.995
A110: Total | B110: 0.97 | C110: 0.98114294 | D110: 0.98941622 | E110: =+'Plan auditoria y avance'!E28 -> 0.99928876 | F110: 0.995

Sheet ALVEOLOS
A2: RESULTADO DE AUDITORÍA | D2: 200 | N2: D4 | V2: DEPÓSITO 250 | AC2: DUCATI | AG2: D3 | AQ2: CAMIONES
C3: 9 | D3: =D19-D31 -> #REF! | E3: =E19-E31 -> #REF! | F3: =F19-F31 -> #REF! | G3: =G19-G31 -> #REF! | H3: =H19-H31 -> #REF! | I3: =I19-I31 -> #REF! | J3: =J19-J31 -> #REF! | K3: =K19-K31 -> #REF! | ... AZ3: =AZ19-AZ31 -> #REF!
C4: 8 | D4: =D20-D32 -> #REF! | E4: =E20-E32 -> #REF! | F4: =F20-F32 -> #REF! | G4: =G20-G32 -> #REF! | H4: =H20-H32 -> #REF! | I4: =I20-I32 -> #REF! | J4: =J20-J32 -> #REF! | K4: =K20-K32 -> #REF! | ... AZ4: =AZ20-AZ32 -> #REF!
C5: 7 | D5: =D21-D33 -> #REF! | E5: =E21-E33 -> #REF! | F5: =F21-F33 -> #REF! | G5: =G21-G33 -> #REF! | H5: =H21-H33 -> #REF! | I5: =I21-I33 -> #REF! | J5: =J21-J33 -> #REF! | K5: =K21-K33 -> #REF! | ... AZ5: =AZ21-AZ33 -> #REF!
C6: 6 | D6: =D22-D34 -> #REF! | E6: =E22-E34 -> #REF! | F6: =F22-F34 -> #REF! | G6: =G22-G34 -> #REF! | H6: =H22-H34 -> #REF! | I6: =I22-I34 -> #REF! | J6: =J22-J34 -> #REF! | K6: =K22-K34 -> #REF! | ... AZ6: =AZ22-AZ34 -> #REF!
C7: 5 | D7: =D23-D35 -> #REF! | E7: =E23-E35 -> #REF! | F7: =F23-F35 -> #REF! | G7: =G23-G35 -> #REF! | H7: =H23-H35 -> #REF! | I7: =I23-I35 -> #REF! | J7: =J23-J35 -> #REF! | K7: =K23-K35 -> #REF! | ... AZ7: =AZ23-AZ35 -> #REF!
C8: 4 | D8: =D24-D36 -> #REF! | E8: =E24-E36 -> #REF! | F8: =F24-F36 -> #REF! | G8: =G24-G36 -> #REF! | H8: =H24-H36 -> #REF! | I8: =I24-I36 -> #REF! | J8: =J24-J36 -> #REF! | K8: =K24-K36 -> #REF! | ... AZ8: =AZ24-AZ36 -> #REF!
C9: 3 | D9: =D25-D37 -> #REF! | E9: =E25-E37 -> #REF! | F9: =F25-F37 -> #REF! | G9: =G25-G37 -> #REF! | H9: =H25-H37 -> #REF! | I9: =I25-I37 -> #REF! | J9: =J25-J37 -> #REF! | K9: =K25-K37 -> #REF! | ... AZ9: =AZ25-AZ37 -> #REF!
C10: 2 | D10: =D26-D38 -> #REF! | E10: =E26-E38 -> #REF! | F10: =F26-F38 -> #REF! | G10: =G26-G38 -> #REF! | H10: =H26-H38 -> #REF! | I10: =I26-I38 -> #REF! | J10: =J26-J38 -> #REF! | K10: =K26-K38 -> #REF! | ... AZ10: =AZ26-AZ38 -> #REF!
C11: 1 | D11: =D27-D39 -> #REF! | E11: =E27-E39 -> #REF! | F11: =F27-F39 -> #REF! | G11: =G27-G39 -> #REF! | H11: =H27-H39 -> #REF! | I11: =I27-I39 -> #REF! | J11: =J27-J39 -> #REF! | K11: =K27-K39 -> #REF! | ... AZ11: =AZ27-AZ39 -> #REF!
B12: CALLE: | D12: 1 | E12: =+D12+1 -> 2 | F12: =+E12+1 -> 3 | G12: =+F12+1 -> 4 | H12: =+G12+1 -> 5 | I12: =+H12+1 -> 6 | J12: =+I12+1 -> 7 | K12: =+J12+1 -> 8 | L12: =+K12+1 -> 9 | M12: =+L12+1 -> 10 | N12: 11 | O12: =+N12+1 -> 12 | P12: =+O12+1 -> 13 | Q12: =+P12+1 -> 14 | R12: =+Q12+1 -> 15 | S12: =+R12+1 -> 16 | T12: =+S12+1 -> 17 | U12: 18 | V12: 21 | W12: 22 | X12: 23 | Y12: 24 | Z12: 25 | AA12: 26 | AB12: 27 | AC12: 28 | AD12: 29 | AE12: 30 | AF12: 31 | AG12: 51 | AH12: =+AG12+1 -> 52 | AI12: =+AH12+1 -> 53 | AJ12: =+AI12+1 -> 54 | AK12: =+AJ12+1 -> 55 | AL12: =+AK12+1 -> 56 | AM12: =+AL12+1 -> 57 | AN12: =+AM12+1 -> 58 | AO12: =+AN12+1 -> 59 | AP12: =+AO12+1 -> 60 | AQ12: 51 | AR12: =+AQ12+1 -> 52 | AS12: =+AR12+1 -> 53 | AT12: =+AS12+1 -> 54 | AU12: =+AT12+1 -> 55 | AV12: =+AU12+1 -> 56 | AW12: =+AV12+1 -> 57 | AX12: =+AW12+1 -> 58 | AY12: =+AX12+1 -> 59 | AZ12: =+AY12+1 -> 60
D14: ver niveles hasta 14
D15: ver ubicaciones BIS
A18: CONTROLADO | D18: 200 | N18: D4 | V18: DEPÓSITO 250 | AC18: DUCATI | AG18: D3 | AQ18: CAMIONES
C19: 9 | D19: =COUNTIFS('Planilla de control'!#REF!,D28,'Planilla de control'!#REF!,$C$19) -> #REF! | E19: =COUNTIFS('Planilla de control'!#REF!,E28,'Planilla de control'!#REF!,$C$19) -> #REF! | F19: =COUNTIFS('Planilla de control'!#REF!,F28,'Planilla de control'!#REF!,$C$19) -> #REF! | G19: =COUNTIFS('Planilla de control'!#REF!,G28,'Planilla de control'!#REF!,$C$19) -> #REF! | H19: =COUNTIFS('Planilla de control'!#REF!,H28,'Planilla de control'!#REF!,$C$19) -> #REF! | I19: =COUNTIFS('Planilla de control'!#REF!,I28,'Planilla de control'!#REF!,$C$19) -> #REF! | J19: =COUNTIFS('Planilla de control'!#REF!,J28,'Planilla de control'!#REF!,$C$19) -> #REF! | K19: =COUNTIFS('Planilla de control'!#REF!,K28,'Planilla de control'!#REF!,$C$19) -> #REF! | ... BC19: =COUNTIFS('Planilla de control'!#REF!,BC28,'Planilla de control'!#REF!,$C$19) -> #REF!
C20: 8 | D20: =COUNTIFS('Planilla de control'!#REF!,D28,'Planilla de control'!#REF!,$C$20) -> #REF! | E20: =COUNTIFS('Planilla de control'!#REF!,E28,'Planilla de control'!#REF!,$C$20) -> #REF! | F20: =COUNTIFS('Planilla de control'!#REF!,F28,'Planilla de control'!#REF!,$C$20) -> #REF! | G20: =COUNTIFS('Planilla de control'!#REF!,G28,'Planilla de control'!#REF!,$C$20) -> #REF! | H20: =COUNTIFS('Planilla de control'!#REF!,H28,'Planilla de control'!#REF!,$C$20) -> #REF! | I20: =COUNTIFS('Planilla de control'!#REF!,I28,'Planilla de control'!#REF!,$C$20) -> #REF! | J20: =COUNTIFS('Planilla de control'!#REF!,J28,'Planilla de control'!#REF!,$C$20) -> #REF! | K20: =COUNTIFS('Planilla de control'!#REF!,K28,'Planilla de control'!#REF!,$C$20) -> #REF! | ... BC20: =COUNTIFS('Planilla de control'!#REF!,BC28,'Planilla de control'!#REF!,$C$20) -> #REF!
C21: 7 | D21: =COUNTIFS('Planilla de control'!#REF!,D28,'Planilla de control'!#REF!,$C$21) -> #REF! | E21: =COUNTIFS('Planilla de control'!#REF!,E28,'Planilla de control'!#REF!,$C$21) -> #REF! | F21: =COUNTIFS('Planilla de control'!#REF!,F28,'Planilla de control'!#REF!,$C$21) -> #REF! | G21: =COUNTIFS('Planilla de control'!#REF!,G28,'Planilla de control'!#REF!,$C$21) -> #REF! | H21: =COUNTIFS('Planilla de control'!#REF!,H28,'Planilla de control'!#REF!,$C$21) -> #REF! | I21: =COUNTIFS('Planilla de control'!#REF!,I28,'Planilla de control'!#REF!,$C$21) -> #REF! | J21: =COUNTIFS('Planilla de control'!#REF!,J28,'Planilla de control'!#REF!,$C$21) -> #REF! | K21: =COUNTIFS('Planilla de control'!#REF!,K28,'Planilla de control'!#REF!,$C$21) -> #REF! | ... BC21: =COUNTIFS('Planilla de control'!#REF!,BC28,'Planilla de control'!#REF!,$C$21) -> #REF!
C22: 6 | D22: =COUNTIFS('Planilla de control'!#REF!,D28,'Planilla de control'!#REF!,$C$22) -> #REF! | E22: =COUNTIFS('Planilla de control'!#REF!,E28,'Planilla de control'!#REF!,$C$22) -> #REF! | F22: =COUNTIFS('Planilla de control'!#REF!,F28,'Planilla de control'!#REF!,$C$22) -> #REF! | G22: =COUNTIFS('Planilla de control'!#REF!,G28,'Planilla de control'!#REF!,$C$22) -> #REF! | H22: =COUNTIFS('Planilla de control'!#REF!,H28,'Planilla de control'!#REF!,$C$22) -> #REF! | I22: =COUNTIFS('Planilla de control'!#REF!,I28,'Planilla de control'!#REF!,$C$22) -> #REF! | J22: =COUNTIFS('Planilla de control'!#REF!,J28,'Planilla de control'!#REF!,$C$22) -> #REF! | K22: =COUNTIFS('Planilla de control'!#REF!,K28,'Planilla de control'!#REF!,$C$22) -> #REF! | ... BC22: =COUNTIFS('Planilla de control'!#REF!,BC28,'Planilla de control'!#REF!,$C$22) -> #REF!
C23: 5 | D23: =COUNTIFS('Planilla de control'!#REF!,D28,'Planilla de control'!#REF!,$C$23) -> #REF! | E23: =COUNTIFS('Planilla de control'!#REF!,E28,'Planilla de control'!#REF!,$C$23) -> #REF! | F23: =COUNTIFS('Planilla de control'!#REF!,F28,'Planilla de control'!#REF!,$C$23) -> #REF! | G23: =COUNTIFS('Planilla de control'!#REF!,G28,'Planilla de control'!#REF!,$C$23) -> #REF! | H23: =COUNTIFS('Planilla de control'!#REF!,H28,'Planilla de control'!#REF!,$C$23) -> #REF! | I23: =COUNTIFS('Planilla de control'!#REF!,I28,'Planilla de control'!#REF!,$C$23) -> #REF! | J23: =COUNTIFS('Planilla de control'!#REF!,J28,'Planilla de control'!#REF!,$C$23) -> #REF! | K23: =COUNTIFS('Planilla de control'!#REF!,K28,'Planilla de control'!#REF!,$C$23) -> #REF! | ... BC23: =COUNTIFS('Planilla de control'!#REF!,BC28,'Planilla de control'!#REF!,$C$23) -> #REF!
C24: 4 | D24: =COUNTIFS('Planilla de control'!#REF!,D28,'Planilla de control'!#REF!,$C$24) -> #REF! | E24: =COUNTIFS('Planilla de control'!#REF!,E28,'Planilla de control'!#REF!,$C$24) -> #REF! | F24: =COUNTIFS('Planilla de control'!#REF!,F28,'Planilla de control'!#REF!,$C$24) -> #REF! | G24: =COUNTIFS('Planilla de control'!#REF!,G28,'Planilla de control'!#REF!,$C$24) -> #REF! | H24: =COUNTIFS('Planilla de control'!#REF!,H28,'Planilla de control'!#REF!,$C$24) -> #REF! | I24: =COUNTIFS('Planilla de control'!#REF!,I28,'Planilla de control'!#REF!,$C$24) -> #REF! | J24: =COUNTIFS('Planilla de control'!#REF!,J28,'Planilla de control'!#REF!,$C$24) -> #REF! | K24: =COUNTIFS('Planilla de control'!#REF!,K28,'Planilla de control'!#REF!,$C$24) -> #REF! | ... BC24: =COUNTIFS('Planilla de control'!#REF!,BC28,'Planilla de control'!#REF!,$C$24) -> #REF!
C25: 3 | D25: =COUNTIFS('Planilla de control'!#REF!,D28,'Planilla de control'!#REF!,$C$25) -> #REF! | E25: =COUNTIFS('Planilla de control'!#REF!,E28,'Planilla de control'!#REF!,$C$25) -> #REF! | F25: =COUNTIFS('Planilla de control'!#REF!,F28,'Planilla de control'!#REF!,$C$25) -> #REF! | G25: =COUNTIFS('Planilla de control'!#REF!,G28,'Planilla de control'!#REF!,$C$25) -> #REF! | H25: =COUNTIFS('Planilla de control'!#REF!,H28,'Planilla de control'!#REF!,$C$25) -> #REF! | I25: =COUNTIFS('Planilla de control'!#REF!,I28,'Planilla de control'!#REF!,$C$25) -> #REF! | J25: =COUNTIFS('Planilla de control'!#REF!,J28,'Planilla de control'!#REF!,$C$25) -> #REF! | K25: =COUNTIFS('Planilla de control'!#REF!,K28,'Planilla de control'!#REF!,$C$25) -> #REF! | ... BC25: =COUNTIFS('Planilla de control'!#REF!,BC28,'Planilla de control'!#REF!,$C$25) -> #REF!
C26: 2 | D26: =COUNTIFS('Planilla de control'!#REF!,D28,'Planilla de control'!#REF!,$C$26) -> #REF! | E26: =COUNTIFS('Planilla de control'!#REF!,E28,'Planilla de control'!#REF!,$C$26) -> #REF! | F26: =COUNTIFS('Planilla de control'!#REF!,F28,'Planilla de control'!#REF!,$C$26) -> #REF! | G26: =COUNTIFS('Planilla de control'!#REF!,G28,'Planilla de control'!#REF!,$C$26) -> #REF! | H26: =COUNTIFS('Planilla de control'!#REF!,H28,'Planilla de control'!#REF!,$C$26) -> #REF! | I26: =COUNTIFS('Planilla de control'!#REF!,I28,'Planilla de control'!#REF!,$C$26) -> #REF! | J26: =COUNTIFS('Planilla de control'!#REF!,J28,'Planilla de control'!#REF!,$C$26) -> #REF! | K26: =COUNTIFS('Planilla de control'!#REF!,K28,'Planilla de control'!#REF!,$C$26) -> #REF! | ... BC26: =COUNTIFS('Planilla de control'!#REF!,BC28,'Planilla de control'!#REF!,$C$26) -> #REF!
C27: 1 | D27: =COUNTIFS('Planilla de control'!#REF!,D28,'Planilla de control'!#REF!,$C$27) -> #REF! | E27: =COUNTIFS('Planilla de control'!#REF!,E28,'Planilla de control'!#REF!,$C$27) -> #REF! | F27: =COUNTIFS('Planilla de control'!#REF!,F28,'Planilla de control'!#REF!,$C$27) -> #REF! | G27: =COUNTIFS('Planilla de control'!#REF!,G28,'Planilla de control'!#REF!,$C$27) -> #REF! | H27: =COUNTIFS('Planilla de control'!#REF!,H28,'Planilla de control'!#REF!,$C$27) -> #REF! | I27: =COUNTIFS('Planilla de control'!#REF!,I28,'Planilla de control'!#REF!,$C$27) -> #REF! | J27: =COUNTIFS('Planilla de control'!#REF!,J28,'Planilla de control'!#REF!,$C$27) -> #REF! | K27: =COUNTIFS('Planilla de control'!#REF!,K28,'Planilla de control'!#REF!,$C$27) -> #REF! | ... BC27: =COUNTIFS('Planilla de control'!#REF!,BC28,'Planilla de control'!#REF!,$C$27) -> #REF!
D28: 1 | E28: =+D28+1 -> 2 | F28: =+E28+1 -> 3 | G28: =+F28+1 -> 4 | H28: =+G28+1 -> 5 | I28: =+H28+1 -> 6 | J28: =+I28+1 -> 7 | K28: =+J28+1 -> 8 | L28: =+K28+1 -> 9 | M28: =+L28+1 -> 10 | N28: 11 | O28: =+N28+1 -> 12 | P28: =+O28+1 -> 13 | Q28: =+P28+1 -> 14 | R28: =+Q28+1 -> 15 | S28: =+R28+1 -> 16 | T28: =+S28+1 -> 17 | U28: 18 | V28: 21 | W28: 22 | X28: 23 | Y28: 24 | Z28: 25 | AA28: 26 | AB28: 27 | AC28: 28 | AD28: 29 | AE28: 30 | AF28: 31 | AG28: 51 | AH28: =+AG28+1 -> 52 | AI28: =+AH28+1 -> 53 | AJ28: =+AI28+1 -> 54 | AK28: =+AJ28+1 -> 55 | AL28: =+AK28+1 -> 56 | AM28: =+AL28+1 -> 57 | AN28: =+AM28+1 -> 58 | AO28: =+AN28+1 -> 59 | AP28: =+AO28+1 -> 60 | AQ28: 61 | AR28: =+AQ28+1 -> 62 | AS28: =+AR28+1 -> 63 | AT28: =+AS28+1 -> 64 | AU28: =+AT28+1 -> 65 | AV28: =+AU28+1 -> 66 | AW28: =+AV28+1 -> 67 | AX28: =+AW28+1 -> 68 | AY28: =+AX28+1 -> 69 | ... BC28: =+BB28+1 -> 73
A30: OK | D30: 200 | N30: D4 | V30: DEPÓSITO 250 | AC30: DUCATI | AG30: D3
C31: 9 | D31: =COUNTIFS('Planilla de control'!#REF!,D40,'Planilla de control'!#REF!,$C$31,'Planilla de control'!$H:$H,"x") -> #REF! | E31: =COUNTIFS('Planilla de control'!#REF!,E40,'Planilla de control'!#REF!,$C$31,'Planilla de control'!$H:$H,"x") -> #REF! | F31: =COUNTIFS('Planilla de control'!#REF!,F40,'Planilla de control'!#REF!,$C$31,'Planilla de control'!$H:$H,"x") -> #REF! | G31: =COUNTIFS('Planilla de control'!#REF!,G40,'Planilla de control'!#REF!,$C$31,'Planilla de control'!$H:$H,"x") -> #REF! | H31: =COUNTIFS('Planilla de control'!#REF!,H40,'Planilla de control'!#REF!,$C$31,'Planilla de control'!$H:$H,"x") -> #REF! | I31: =COUNTIFS('Planilla de control'!#REF!,I40,'Planilla de control'!#REF!,$C$31,'Planilla de control'!$H:$H,"x") -> #REF! | J31: =COUNTIFS('Planilla de control'!#REF!,J40,'Planilla de control'!#REF!,$C$31,'Planilla de control'!$H:$H,"x") -> #REF! | K31: =COUNTIFS('Planilla de control'!#REF!,K40,'Planilla de control'!#REF!,$C$31,'Planilla de control'!$H:$H,"x") -> #REF! | ... AP31: =COUNTIFS('Planilla de control'!#REF!,AP40,'Planilla de control'!#REF!,$C$31,'Planilla de control'!$H:$H,"x") -> #REF!
C32: 8 | D32: =COUNTIFS('Planilla de control'!#REF!,D40,'Planilla de control'!#REF!,$C$32,'Planilla de control'!$H:$H,"x") -> #REF! | E32: =COUNTIFS('Planilla de control'!#REF!,E40,'Planilla de control'!#REF!,$C$32,'Planilla de control'!$H:$H,"x") -> #REF! | F32: =COUNTIFS('Planilla de control'!#REF!,F40,'Planilla de control'!#REF!,$C$32,'Planilla de control'!$H:$H,"x") -> #REF! | G32: =COUNTIFS('Planilla de control'!#REF!,G40,'Planilla de control'!#REF!,$C$32,'Planilla de control'!$H:$H,"x") -> #REF! | H32: =COUNTIFS('Planilla de control'!#REF!,H40,'Planilla de control'!#REF!,$C$32,'Planilla de control'!$H:$H,"x") -> #REF! | I32: =COUNTIFS('Planilla de control'!#REF!,I40,'Planilla de control'!#REF!,$C$32,'Planilla de control'!$H:$H,"x") -> #REF! | J32: =COUNTIFS('Planilla de control'!#REF!,J40,'Planilla de control'!#REF!,$C$32,'Planilla de control'!$H:$H,"x") -> #REF! | K32: =COUNTIFS('Planilla de control'!#REF!,K40,'Planilla de control'!#REF!,$C$32,'Planilla de control'!$H:$H,"x") -> #REF! | ... AP32: =COUNTIFS('Planilla de control'!#REF!,AP40,'Planilla de control'!#REF!,$C$32,'Planilla de control'!$H:$H,"x") -> #REF!
C33: 7 | D33: =COUNTIFS('Planilla de control'!#REF!,D40,'Planilla de control'!#REF!,$C$33,'Planilla de control'!$H:$H,"x") -> #REF! | E33: =COUNTIFS('Planilla de control'!#REF!,E40,'Planilla de control'!#REF!,$C$33,'Planilla de control'!$H:$H,"x") -> #REF! | F33: =COUNTIFS('Planilla de control'!#REF!,F40,'Planilla de control'!#REF!,$C$33,'Planilla de control'!$H:$H,"x") -> #REF! | G33: =COUNTIFS('Planilla de control'!#REF!,G40,'Planilla de control'!#REF!,$C$33,'Planilla de control'!$H:$H,"x") -> #REF! | H33: =COUNTIFS('Planilla de control'!#REF!,H40,'Planilla de control'!#REF!,$C$33,'Planilla de control'!$H:$H,"x") -> #REF! | I33: =COUNTIFS('Planilla de control'!#REF!,I40,'Planilla de control'!#REF!,$C$33,'Planilla de control'!$H:$H,"x") -> #REF! | J33: =COUNTIFS('Planilla de control'!#REF!,J40,'Planilla de control'!#REF!,$C$33,'Planilla de control'!$H:$H,"x") -> #REF! | K33: =COUNTIFS('Planilla de control'!#REF!,K40,'Planilla de control'!#REF!,$C$33,'Planilla de control'!$H:$H,"x") -> #REF! | ... AP33: =COUNTIFS('Planilla de control'!#REF!,AP40,'Planilla de control'!#REF!,$C$33,'Planilla de control'!$H:$H,"x") -> #REF!
C34: 6 | D34: =COUNTIFS('Planilla de control'!#REF!,D40,'Planilla de control'!#REF!,$C$34,'Planilla de control'!$H:$H,"x") -> #REF! | E34: =COUNTIFS('Planilla de control'!#REF!,E40,'Planilla de control'!#REF!,$C$34,'Planilla de control'!$H:$H,"x") -> #REF! | F34: =COUNTIFS('Planilla de control'!#REF!,F40,'Planilla de control'!#REF!,$C$34,'Planilla de control'!$H:$H,"x") -> #REF! | G34: =COUNTIFS('Planilla de control'!#REF!,G40,'Planilla de control'!#REF!,$C$34,'Planilla de control'!$H:$H,"x") -> #REF! | H34: =COUNTIFS('Planilla de control'!#REF!,H40,'Planilla de control'!#REF!,$C$34,'Planilla de control'!$H:$H,"x") -> #REF! | I34: =COUNTIFS('Planilla de control'!#REF!,I40,'Planilla de control'!#REF!,$C$34,'Planilla de control'!$H:$H,"x") -> #REF! | J34: =COUNTIFS('Planilla de control'!#REF!,J40,'Planilla de control'!#REF!,$C$34,'Planilla de control'!$H:$H,"x") -> #REF! | K34: =COUNTIFS('Planilla de control'!#REF!,K40,'Planilla de control'!#REF!,$C$34,'Planilla de control'!$H:$H,"x") -> #REF! | ... AP34: =COUNTIFS('Planilla de control'!#REF!,AP40,'Planilla de control'!#REF!,$C$34,'Planilla de control'!$H:$H,"x") -> #REF!
C35: 5 | D35: =COUNTIFS('Planilla de control'!#REF!,D40,'Planilla de control'!#REF!,$C$35,'Planilla de control'!$H:$H,"x") -> #REF! | E35: =COUNTIFS('Planilla de control'!#REF!,E40,'Planilla de control'!#REF!,$C$35,'Planilla de control'!$H:$H,"x") -> #REF! | F35: =COUNTIFS('Planilla de control'!#REF!,F40,'Planilla de control'!#REF!,$C$35,'Planilla de control'!$H:$H,"x") -> #REF! | G35: =COUNTIFS('Planilla de control'!#REF!,G40,'Planilla de control'!#REF!,$C$35,'Planilla de control'!$H:$H,"x") -> #REF! | H35: =COUNTIFS('Planilla de control'!#REF!,H40,'Planilla de control'!#REF!,$C$35,'Planilla de control'!$H:$H,"x") -> #REF! | I35: =COUNTIFS('Planilla de control'!#REF!,I40,'Planilla de control'!#REF!,$C$35,'Planilla de control'!$H:$H,"x") -> #REF! | J35: =COUNTIFS('Planilla de control'!#REF!,J40,'Planilla de control'!#REF!,$C$35,'Planilla de control'!$H:$H,"x") -> #REF! | K35: =COUNTIFS('Planilla de control'!#REF!,K40,'Planilla de control'!#REF!,$C$35,'Planilla de control'!$H:$H,"x") -> #REF! | ... AP35: =COUNTIFS('Planilla de control'!#REF!,AP40,'Planilla de control'!#REF!,$C$35,'Planilla de control'!$H:$H,"x") -> #REF!
C36: 4 | D36: =COUNTIFS('Planilla de control'!#REF!,D40,'Planilla de control'!#REF!,$C$36,'Planilla de control'!$H:$H,"x") -> #REF! | E36: =COUNTIFS('Planilla de control'!#REF!,E40,'Planilla de control'!#REF!,$C$36,'Planilla de control'!$H:$H,"x") -> #REF! | F36: =COUNTIFS('Planilla de control'!#REF!,F40,'Planilla de control'!#REF!,$C$36,'Planilla de control'!$H:$H,"x") -> #REF! | G36: =COUNTIFS('Planilla de control'!#REF!,G40,'Planilla de control'!#REF!,$C$36,'Planilla de control'!$H:$H,"x") -> #REF! | H36: =COUNTIFS('Planilla de control'!#REF!,H40,'Planilla de control'!#REF!,$C$36,'Planilla de control'!$H:$H,"x") -> #REF! | I36: =COUNTIFS('Planilla de control'!#REF!,I40,'Planilla de control'!#REF!,$C$36,'Planilla de control'!$H:$H,"x") -> #REF! | J36: =COUNTIFS('Planilla de control'!#REF!,J40,'Planilla de control'!#REF!,$C$36,'Planilla de control'!$H:$H,"x") -> #REF! | K36: =COUNTIFS('Planilla de control'!#REF!,K40,'Planilla de control'!#REF!,$C$36,'Planilla de control'!$H:$H,"x") -> #REF! | ... AP36: =COUNTIFS('Planilla de control'!#REF!,AP40,'Planilla de control'!#REF!,$C$36,'Planilla de control'!$H:$H,"x") -> #REF!
C37: 3 | D37: =COUNTIFS('Planilla de control'!#REF!,D40,'Planilla de control'!#REF!,$C$37,'Planilla de control'!$H:$H,"x") -> #REF! | E37: =COUNTIFS('Planilla de control'!#REF!,E40,'Planilla de control'!#REF!,$C$37,'Planilla de control'!$H:$H,"x") -> #REF! | F37: =COUNTIFS('Planilla de control'!#REF!,F40,'Planilla de control'!#REF!,$C$37,'Planilla de control'!$H:$H,"x") -> #REF! | G37: =COUNTIFS('Planilla de control'!#REF!,G40,'Planilla de control'!#REF!,$C$37,'Planilla de control'!$H:$H,"x") -> #REF! | H37: =COUNTIFS('Planilla de control'!#REF!,H40,'Planilla de control'!#REF!,$C$37,'Planilla de control'!$H:$H,"x") -> #REF! | I37: =COUNTIFS('Planilla de control'!#REF!,I40,'Planilla de control'!#REF!,$C$37,'Planilla de control'!$H:$H,"x") -> #REF! | J37: =COUNTIFS('Planilla de control'!#REF!,J40,'Planilla de control'!#REF!,$C$37,'Planilla de control'!$H:$H,"x") -> #REF! | K37: =COUNTIFS('Planilla de control'!#REF!,K40,'Planilla de control'!#REF!,$C$37,'Planilla de control'!$H:$H,"x") -> #REF! | ... AP37: =COUNTIFS('Planilla de control'!#REF!,AP40,'Planilla de control'!#REF!,$C$37,'Planilla de control'!$H:$H,"x") -> #REF!
C38: 2 | D38: =COUNTIFS('Planilla de control'!#REF!,D40,'Planilla de control'!#REF!,$C$38,'Planilla de control'!$H:$H,"x") -> #REF! | E38: =COUNTIFS('Planilla de control'!#REF!,E40,'Planilla de control'!#REF!,$C$38,'Planilla de control'!$H:$H,"x") -> #REF! | F38: =COUNTIFS('Planilla de control'!#REF!,F40,'Planilla de control'!#REF!,$C$38,'Planilla de control'!$H:$H,"x") -> #REF! | G38: =COUNTIFS('Planilla de control'!#REF!,G40,'Planilla de control'!#REF!,$C$38,'Planilla de control'!$H:$H,"x") -> #REF! | H38: =COUNTIFS('Planilla de control'!#REF!,H40,'Planilla de control'!#REF!,$C$38,'Planilla de control'!$H:$H,"x") -> #REF! | I38: =COUNTIFS('Planilla de control'!#REF!,I40,'Planilla de control'!#REF!,$C$38,'Planilla de control'!$H:$H,"x") -> #REF! | J38: =COUNTIFS('Planilla de control'!#REF!,J40,'Planilla de control'!#REF!,$C$38,'Planilla de control'!$H:$H,"x") -> #REF! | K38: =COUNTIFS('Planilla de control'!#REF!,K40,'Planilla de control'!#REF!,$C$38,'Planilla de control'!$H:$H,"x") -> #REF! | ... AP38: =COUNTIFS('Planilla de control'!#REF!,AP40,'Planilla de control'!#REF!,$C$38,'Planilla de control'!$H:$H,"x") -> #REF!
C39: 1 | D39: =COUNTIFS('Planilla de control'!#REF!,D40,'Planilla de control'!#REF!,$C$39,'Planilla de control'!$H:$H,"x") -> #REF! | E39: =COUNTIFS('Planilla de control'!#REF!,E40,'Planilla de control'!#REF!,$C$39,'Planilla de control'!$H:$H,"x") -> #REF! | F39: =COUNTIFS('Planilla de control'!#REF!,F40,'Planilla de control'!#REF!,$C$39,'Planilla de control'!$H:$H,"x") -> #REF! | G39: =COUNTIFS('Planilla de control'!#REF!,G40,'Planilla de control'!#REF!,$C$39,'Planilla de control'!$H:$H,"x") -> #REF! | H39: =COUNTIFS('Planilla de control'!#REF!,H40,'Planilla de control'!#REF!,$C$39,'Planilla de control'!$H:$H,"x") -> #REF! | I39: =COUNTIFS('Planilla de control'!#REF!,I40,'Planilla de control'!#REF!,$C$39,'Planilla de control'!$H:$H,"x") -> #REF! | J39: =COUNTIFS('Planilla de control'!#REF!,J40,'Planilla de control'!#REF!,$C$39,'Planilla de control'!$H:$H,"x") -> #REF! | K39: =COUNTIFS('Planilla de control'!#REF!,K40,'Planilla de control'!#REF!,$C$39,'Planilla de control'!$H:$H,"x") -> #REF! | ... AP39: =COUNTIFS('Planilla de control'!#REF!,AP40,'Planilla de control'!#REF!,$C$39,'Planilla de control'!$H:$H,"x") -> #REF!
D40: 1 | E40: =+D40+1 -> 2 | F40: =+E40+1 -> 3 | G40: =+F40+1 -> 4 | H40: =+G40+1 -> 5 | I40: =+H40+1 -> 6 | J40: =+I40+1 -> 7 | K40: =+J40+1 -> 8 | L40: =+K40+1 -> 9 | M40: =+L40+1 -> 10 | N40: 11 | O40: =+N40+1 -> 12 | P40: =+O40+1 -> 13 | Q40: =+P40+1 -> 14 | R40: =+Q40+1 -> 15 | S40: =+R40+1 -> 16 | T40: =+S40+1 -> 17 | U40: 18 | V40: 21 | W40: 22 | X40: 23 | Y40: 24 | Z40: 25 | AA40: 26 | AB40: 27 | AC40: 28 | AD40: 29 | AE40: 30 | AF40: 31 | AG40: 51 | AH40: =+AG40+1 -> 52 | AI40: =+AH40+1 -> 53 | AJ40: =+AI40+1 -> 54 | AK40: =+AJ40+1 -> 55 | AL40: =+AK40+1 -> 56 | AM40: =+AL40+1 -> 57 | AN40: =+AM40+1 -> 58 | AO40: =+AN40+1 -> 59 | AP40: =+AO40+1 -> 60

Sheet AVANCE GENERAL
D4: AUDITORÍA DE UBICACIONES | E4: VACÍAS Y BLOQUEADAS | G4: AUDITORÍA DE BUFFER
E5: 1ERA VUELTA | F5: 2DA VUELTA | G5: 1ERA VUELTA | H5: 2DA VUELTA
C6: D3 | D6: 1 | E6: 1 | F6: 1 | G6: 4 | H6: 4 | J6: 1 | K6: CONTROLADO
C7: D4 | D7: 1 | E7: 1 | F7: 1 | G7: 4 | H7: 4 | J7: 2 | K7: PARCIAL
C8: MQ200 | D8: 1 | E8: 1 | F8: 1 | G8: 4 | H8: 4 | J8: 3 | K8: NO CONTROLADO
C9: DUCATI | D9: 1 | E9: 1 | F9: 1 | G9: 4 | H9: 4 | J9: 4 | K9: NO APLICA
C10: MQ250 | D10: 1 | E10: 1 | F10: 1 | G10: 4 | H10: 4
C11: ALERO BUY MQ200 | D11: 4 | E11: 4 | F11: 4 | G11: 1 | H11: 1
C12: TUNEL 281 | D12: 4 | E12: 4 | F12: 4 | G12: 1 | H12: 1
C13: D3-200 | D13: 4 | E13: 4 | F13: 4 | G13: 1 | H13: 1
C14: ALERO 250 | D14: 4 | E14: 4 | F14: 4 | G14: 1 | H14: 1
C15: BANCOS MQ250 | D15: 4 | E15: 4 | F15: 4 | G15: 1 | H15: 1
C16: DEPÓSITO 250 | D16: 4 | E16: 4 | F16: 4 | G16: 1 | H16: 1
C17: TRANSFER | D17: 4 | E17: 4 | F17: 4 | G17: 1 | H17: 1
C18: HERRERÍA | D18: 4 | E18: 4 | F18: 4 | G18: 1 | H18: 1

Sheet Valor material
A1: Ce. | B1: Material | C1: Cl.valor. | D1: Texto breve de material | E1: 4 | F1: 5 | G1: 6 | H1: 7 | I1: CURRENT PRICE | L1: ÚLTIMA ACTUALIZACIÓN: | M1: 45755 | N1: ACTUALIZADO CON EL VALORIZADO DE MARZO
A2: 6400 | B2: 002517185K | C2: DE0VW95 | D2: 858amiento rodillo diferencial MQ281 | E2: 59.03 | I2: 3.2938
A3: 6400 | B3: 002517185M | C3: DE0VW95 | D3: Rodamiento rodillo diferencial MQ281 | E3: 59.19 | I3: 3.7725
A4: 6400 | B4: 3507327 | C4: AR00000 | D4: TORNILLO FIJ.LATERAL | E4: 60.35 | I4: 0.17730002
A5: 6400 | B5: 003519185F | C5: BR0B02A | D5: RODAMIENTO CONICO | E5: 59.76 | I5: 4.38
A6: 6400 | B6: 003519185F | C6: BR0BROT | D6: RODAMIENTO CONICO | E6: 0.43969997 | I6: 3.8946
A7: 6400 | B7: 003519185F | C7: DE0VW95 | D7: RODAMIENTO CONICO | E7: 11.66 | I7: 3.0196
A8: 6400 | B8: 8311231 | C8: DE0VW95 | D8: Anillo seguro cubo 1ra. y 2da. MQ281 | E8: 39.576979 | I8: 0.18690001
A9: 6400 | B9: 12141741 | C9: DE0VW95 | D9: RESORTE DE PRESION | E9: 39.57 | I9: 0.03019999
A10: 6400 | B10: 012301127F | C10: AR00000 | D10: TAPON ACEITE MAGNESIO | E10: 39.56 | I10: 0.44
A11: 6400 | B11: 12409169 | C11: DE0VW95 | D11: ENGR.SATEL.TERM.200 | E11: 39.56 | I11: 4.6138
A12: 6400 | B12: 131417134 | C12: AR00000 | D12: PALANCA | E12: 39.56 | I12: 2.2
A13: 6400 | B13: 14301155 | C13: AR00000 | D13: BUJE COJINETE | E13: 14.91 | I13: 0.13810003
A14: 6400 | B14: 14301485 | C14: AR00000 | D14: VALVULA DE VENTEO | E14: 10.33 | I14: 0.069999977
A15: 6400 | B15: 14301485 | C15: DE0VW95 | D15: VALVULA DE VENTEO | E15: 61.130871 | I15: 0.023299992
A16: 6400 | B16: 01M409159C0C02 | C16: AR00000 | D16: FORJA PLANETARIO MQ-25 | E16: 102.04026 | I16: 3.1920001
A17: 6400 | B17: 01M409159C0R02 | C17: AR00000 | D17: ENGR.PLANETARIO FORJA | E17: 3.3836 | I17: 1.89
A18: 6400 | B18: 01M409159C0S04 | C18: AR00000 | D18: ENGR.PLANETARIO SEMIMEC | E18: 39.78 | I18: 2.0220129
A19: 6400 | B19: 01M409159E | C19: DE0VW95 | D19: ENGR.PLANET.radio diente reforz. | E19: 1.28 | I19: 4.1342
A20: 6400 | B20: 01M409169E | C20: DE0VW95 | D20: SATELITE MQ250 | E20: 3.64 | I20: 3.143
A21: 6400 | B21: 01M409169E0R01 | C21: AR00000 | D21: ENGR.SATEELITE FORJA | E21: 14.13 | I21: 1.2
A22: 6400 | B22: 01M409169E0S05 | C22: AR00000 | D22: ENGR.SATELITE SEMIMEC | E22: 0.77999999 | I22: 1.68
A23: 6400 | B23: 020301153A | C23: DE0VW95 | D23: CASQUILLO CENTRALIZADO | E23: 9.03 | I23: 0.020099993
A24: 6400 | B24: 020311331B | C24: DE0VW95 | D24: ARAND.TOPE.SINCR.5TA. | E24: 3.9632001 | I24: 0.24569999
A25: 6400 | B25: 20311391 | C25: DE0VW95 | D25: ARAND.SUPLEM. 0.75 | E25: 40.02 | I25: 0.095099968
A26: 6400 | B26: 020311391A | C26: DE0VW95 | D26: ARAND.SUPLEM. 0.80 | E26: 40.02 | I26: 0.095499968
A27: 6400 | B27: 020311391B | C27: DE0VW95 | D27: ARAND.SUPLEM. 0.85 | E27: 39.92 | I27: 0.096699968
A28: 6400 | B28: 020311391C | C28: DE0VW95 | D28: ARAND.SUPLEM. 0.90 | E28: 0.2136 | I28: 0.10139997
A29: 6400 | B29: 020311391D | C29: DE0VW95 | D29: ARAND.SUPLEM. 0.95 | E29: 1.17 | I29: 0.10249997
A30: 6400 | B30: 020311391E | C30: DE0VW95 | D30: ARAND.SUPLEM. 1.00 | E30: 1.17 | I30: 0.095999968
A31: 6400 | B31: 020311391F | C31: DE0VW95 | D31: ARAND.SUPLEM. 1.05 | E31: 2.8261088 | I31: 0.11339996
A32: 6400 | B32: 020311391G | C32: DE0VW95 | D32: ARAND.SUPLEM. 1.10 | E32: 14.58 | I32: 0.10989996
A33: 6400 | B33: 020311391H | C33: DE0VW95 | D33: ARAND.SUPLEM. 1.15 | E33: 37.01 | I33: 0.092199969
A34: 6400 | B34: 020311391J | C34: DE0VW95 | D34: ARAND.SUPLEM. 1.20 | E34: 8.4250672 | I34: 0.095199968
A35: 6400 | B35: 020311391K | C35: DE0VW95 | D35: ARAND.SUPLEM. 1.25 | E35: 2.8645757 | I35: 0.13120003
A36: 6400 | B36: 020311391L | C36: DE0VW95 | D36: ARAND.SUPLEM. 1.30 | E36: 1.05 | I36: 0.18110002
A37: 6400 | B37: 020311391M | C37: DE0VW95 | D37: ARAND.SUPLEM. 1.35 | E37: 1.05 | I37: 0.099899967
... A41: 6400 | B41: 020409145A | C41: AR00000 | D41: REMACHE PORTACORONA | E41: 8.41 | I41: 0.085699971
A42: 6400 | B42: 20409374 | C42: BR0B02A | D42: ANILLO CONICO | E42: 99.13 | I42: 0.51999998
A43: 6400 | B43: 20409374 | C43: BR0BROT | D43: ANILLO CONICO | E43: 11.660784 | I43: 0.4626
A44: 6400 | B44: 20409378 | C44: DE0VW95 | D44: ARANDELA TOPE | E44: 29.674446 | I44: 0.14840003
A45: 6400 | B45: 020409379B | C45: DE0VW95 | D45: RESORTE TOMA FUERZA | E45: 4.67 | I45: 0.33449996
A46: 6400 | B46: 02A141165B | C46: AR00000 | D46: CRAPODINA | E46: 2.06 | I46: 3.92
A47: 6400 | B47: 02A141165D | C47: AR00000 | D47: CRAPODINA MQ250 | E47: 0.21 | I47: 3.92
A48: 6400 | B48: 02A141165P | C48: DE0VW95 | D48: CRAPODINA MQ250 PLAST. | E48: 10.3 | I48: 3.4712
A49: 6400 | B49: 02A141165R | C49: DE0VW95 | D49: CRAPODINA MQ250 PLAST. ranurada | E49: 4.119134 | I49: 4.8179
A50: 6400 | B50: 02A141180A | C50: DE0VW95 | D50: TUBO GUIA CONJUNTO | E50: 11.66 | I50: 1.637
A51: 6400 | B51: 02A141734D | C51: AR00000 | D51: PERNO P/TRANSPORTE | E51: 10.82 | I51: 0.0013333329
A52: 6400 | B52: 02A141734D | C52: DE0VW95 | D52: PERNO P/TRANSPORTE | E52: 2.9933 | I52: 0.065499978
A53: 6400 | B53: 02A141777B | C53: AR00000 | D53: PERNO PIVOT | E53: 8.3099999 | I53: 0.35550003
A54: 6400 | B54: 02A141777B | C54: DE0VW95 | D54: PERNO PIVOT | E54: 11.68 | I54: 0.15800002
A55: 6400 | B55: 02A301115B | C55: AR00000 | D55: TAPON DE GOMA | E55: 4.42 | I55: 0.36000003
A56: 6400 | B56: 02A301211A | C56: DE0VW95 | D56: TAPA 5TA.PQ 34/35 | E56: 10.73 | I56: 1.11
... A339: 6400 | B339: 02A31136500S04 | C339: AR00000 | D339: DESL.5TA.op. 10 a 30 | E339: 14.114801 | I339: 7.2047
A340: 6400 | B340: 02A311365CROH | C340: DE0VW95 | D340: DESLIZANTE DE 5TA FORJA VWAG | I340: 1.3899
A341: 6400 | B341: 02A311490K | C341: AR00000 | D341: CONJ.ACC.MARCHAS PQ34 | E341: 11.66 | I341: 21.3239
A342: 6400 | B342: 02A311515K | C342: AR00000 | D342: EJE MARCHA TERMINADO | E342: 0.059999999 | I342: 2.4
A343: 6400 | B343: 02A311515K0S01 | C343: AR00000 | D343: EJE M.A.C/SEMIM.PQ24/3 | E343: 8.69 | I343: 2.4
A344: 6400 | B344: 02A311515K0S02 | C344: AR00000 | D344: EJE M.A.P/SEMIM.PQ24/3 | E344: 7.6 | I344: 2.4
A345: 6400 | B345: 02A311516A | C345: AR00000 | D345: SOPORTE EJE M ATRAS | E345: 10.79 | I345: 2.01
A346: 6400 | B346: 02A311516A0R00 | C346: AR00000 | D346: SOPORTE EJE MARCHA ATR | E346: 0.083599999 | I346: 2.01
A347: 6400 | B347: 02A311521E | C347: AR00000 | D347: HORQUILLA M.A.PQ34 | E347: 0.85999999 | I347: 3.9632
A348: 6400 | B348: 02A311521E | C348: DE0VW95 | D348: HORQUILLA M.A.PQ34 | E348: 0.2416 | I348: 4.6446
A349: 6400 | B349: 02A311523B | C349: DE0VW95 | D349: RODAM.EJE MARCHA .ATRAS | E349: 425.25 | I349: 0.81950003
A350: 6400 | B350: 02A311525 | C350: DE0VW95 | D350: RODAM.EJE MARCHA .ATRAS | E350: 3.2 | I350: 0.688
A351: 6400 | B351: 02A311525A | C351: DE0VW95 | D351: RODAM.EJE MARCHA .ATRAS | E351: 8.58 | I351: 0.688
A352: 6400 | B352: 02A311531K0S00 | C352: AR00000 | D352: ENGR.M.A.MOVIL SEMIM | E352: 8.57 | I352: 2.26
... A385: 6400 | B385: 02A409355D0S03 | C385: AR00000 | D385: TOMA FZA.100 PERF/ROSC | E385: 102.04026 | I385: 9.12
A386: 6400 | B386: 02A409355D0S07 | C386: AR00000 | D386: TOMA FZA.100 OP.30 | I386: 9.12
A387: 6400 | B387: 02A409355D0S08 | C387: AR00000 | D387: TOMA FZA.100 MEC.COMPL | E387: 38.6 | I387: 9.12
A388: 6400 | B388: 02A409355D0S09 | C388: AR00000 | D388: TOMA FZA.100 OP.10A30 | E388: 3.85 | I388: 9.12
A389: 6400 | B389: 02A409355D0S24 | C389: AR00000 | D389: TOMA FZA.100 C/TEM+REV | E389: 2.4 | I389: 9.12
A390: 6400 | B390: 02A409355D0S26 | C390: AR00000 | D390: TOMA FZA.100 C/RECTIF. | E390: 34.369877 | I390: 9.12
A391: 6400 | B391: 02A409355D0S28 | C391: AR00000 | D391: TOMA FZA.100 C/MAGNAFL | E391: 0.94999999 | I391: 9.12
A392: 6400 | B392: 02A409355D0S34 | C392: AR00000 | D392: TOMA FZA.100 RECT+MAG. | E392: 0.21 | I392: 9.12
A393: 6400 | B393: 02A409355F | C393: DE0VW95 | D393: TOMA FZA D107 TERM | E393: 102.04026 | I393: 6.9657
A394: 6400 | B394: 02A409355H0R00 | C394: AR00000 | D394: TOMA DE FUERZA | E394: 3.2748 | I394: 7.02
A395: 6400 | B395: 02A409355H0S26 | C395: AR00000 | D395: TOMA FZA.108 C/RECTIF. | E395: 40.02 | I395: 9.66
A396: 6400 | B396: 02A409355H0S28 | C396: AR00000 | D396: TOMA FZA.108 C/MAGNAFL | E396: 2.95 | I396: 9.12
A397: 6400 | B397: 02B301268 | C397: DE0VW95 | D397: CUBIERTA TOPE | E397: 0.14180005 | I397: 0.27199999
A398: 6400 | B398: 02B301269B | C398: AR00000 | D398: ARANDELA CENTRALIZ. | E398: 11.22 | I398: 0.00059848465
... A495: 6400 | B495: 02J311205P0R01 | C495: DE0VW95 | D495: ARBOL SEC.FORJA Z:19 | E495: 0.28 | I495: 5.3425
A496: 6400 | B496: 02J311205P0S01 | C496: AR00000 | D496: ARBOL SEC.SEMIM.OP.10 | I496: 26.834289
A497: 6400 | B497: 02J311205P0S10 | C497: AR00000 | D497: ARBOL SEC.SEMIM. | E497: 4.31 | I497: 22.409705
A498: 6400 | B498: 02J311205P0S11 | C498: AR00000 | D498: ARBOL SEC.SEMIM. | E498: 12.7 | I498: 26.834289
A499: 6400 | B499: 02J311205P0S21 | C499: AR00000 | D499: ARBOL SEC.SEM.Z19-4R | E499: 6 | I499: 26.834289
A500: 6400 | B500: 02J311205Q | C500: AR03000 | D500: ARBOL SEC Z62 17 6R 123678 | E500: 0.18 | I500: 26.783021
A501: 6400 | B501: 02J311205Q | C501: DE0VW95 | D501: ARBOL SEC Z62 17 6R 123678 | E501: 15.02 | I501: 7.1498
A502: 6400 | B502: 02J311205Q0C01 | C502: AR00000 | D502: ARBOL SEC.FORJA Z: 17 | E502: 1.0042 | I502: 26.834289
A503: 6400 | B503: 02J311205Q0R01 | C503: AR00000 | D503: ARBOL SEC.FORJA Z:17 | E503: 9.02 | I503: 13.03
A504: 6400 | B504: 02J311205Q0S01 | C504: AR00000 | D504: ARBOL SEC.SEMIM.OP.10 | E504: 14.964062 | I504: 26.834289
A505: 6400 | B505: 02J311205Q0S10 | C505: AR00000 | D505: ARBOL SEC.SEMIM. | E505: 26.79 | I505: 23.916434
A506: 6400 | B506: 02J311205Q0S11 | C506: AR00000 | D506: ARBOL SEC.SEMIM. | E506: 1.37 | I506: 26.834289
A507: 6400 | B507: 02J311205Q0S21 | C507: AR00000 | D507: ARBOL SEC.SEM.Z17-6R | E507: 0.72580004 | I507: 26.834289
A508: 6400 | B508: 02J311205R | C508: AR03000 | D508: ARBOL SEC Z72 17 SR | E508: 64.43 | I508: 14.44848
... A745: 6400 | B745: 02R301107A0S11 | C745: AR00000 | D745: CARC.EMBR.C/SELL./.A | E745: 3.99 | I745: 34.369877
A746: 6400 | B746: 02R301107A0S12 | C746: AR00000 | D746: CARC.EMBR.S/SELL./.A | I746: 34.369877
A747: 6400 | B747: 02R301107B | C747: AR00000 | D747: CARC.EMB.TER.PQ35 c/start stop | E747: 3.99 | I747: 34.369877
A748: 6400 | B748: 02R301107B0S08 | C748: AR00000 | D748: CARC.EMBR.P/IMPR..B | E748: 4.34 | I748: 34.369877
A749: 6400 | B749: 02R301107B0S11 | C749: AR00000 | D749: CARC.EMBR.C/SELL./.B | E749: 454.21 | I749: 34.369877
...

Sheet SOB Y FALT
B2: SOBRANTE | E2: FALTANTE
B3: MATERIAL | C3: PRECIO | E3: MATERIAL | F3: PRECIO | H3: DATOS DE FALTANTES Y SOBRANTES SACADOS DEL CONTROL DE CAJONES MIX
B4: 0C9311387 | C4: =0.23*(4800+2400) -> 1656 | E4: 02B409210E | F4: =0.213*500 -> 106.5
B5: 0AJ311515 | C5: =1.36*64 -> 87.04 | E5: 02B409210F | F5: =0.213*500 -> 106.5
B7: TOTAL | C7: =C4+C5 -> 1743.04 | E7: TOTAL | F7: =+F4+F5 -> 213

Sheet PESTILLOS
B2: DEPÓSITO | C2: STATUS | D2: CANTIDAD | E2: ENCASTRES NO OK | F2: PESTILLOS NO OK | G2: OBSERVACIONES | K2: CALLES | L2: NIVELES | M2: COLUMNAS (LETRAS)
B3: D3 | C3: CONTROLADO 100% | D3: 1200 | E3: 0 | F3: 0 | K3: 10 | L3: 8 | M3: 15 | N3: =M3*L3*K3 -> 1200
B4: D4 | C4: CONTROLADO 100% | D4: 200 | E4: 0 | F4: 0 | K4: 8 | L4: 5 | M4: 5 | N4: =M4*L4*K4 -> 200
B5: BUY MQ200 | C5: CONTROLADO 50% | D5: 1080 | E5: 0 | F5: 0 | K5: 10 | L5: 9 | M5: 12 | N5: =M5*L5*K5 -> 1080
B6: DUCATI | C6: FALTA CONTROLAR | D6: 320 | E6: 0 | F6: 0 | K6: 4 | L6: 8 | M6: 10 | N6: =M6*L6*K6 -> 320
B7: MQ250 | C7: FALTA CONTROLAR | D7: 360 | E7: 0 | F7: 0 | K7: 4 | L7: 9 | M7: 10 | N7: =M7*L7*K7 -> 360
F15: A | G15: B | H15: C | K15: D | L15: E | M15: F | N15: G | O15: H | P15: I | Q15: J | R15: K | S15: L | T15: M | U15: N | V15: O

Sheet INSTRUCTIVO

Sheet HU REIMPRESAS
A1: FECHA | B1: HU
A2: 45707 | B2: 09001439768267
A3: 45707 | B3: 09001437656561
A4: 45707 | B4: 09001456410248
A5: 45707 | B5: 09001459167257
A6: 45707 | B6: 09001457274663
A7: 45707 | B7: 09001457704202
A8: 45707 | B8: 09001462321896
A9: 45707 | B9: 09001457430404
A10: 45707 | B10: 09001450663741
A11: 45707 | B11: 09001462341057
A12: 45708 | B12: 09001445613020
A13: 45708 | B13: 09001445613020
... A115: 45713 | B115: 09001453074266

Sheet Valor material (2)
A1: Ce. | B1: Material | C1: Cl.valor. | D1: Texto breve de material | E1: 4 | F1: 5 | G1: 6 | J1: 7 | K1: CURRENT PRICE | N1: ÚLTIMA ACTUALIZACIÓN: | O1: 45317
A2: 6400 | B2: DUC00292346B | C2: IT0OEKR | D2: MOTOR MTS V2 SMALL ARG'23 - DMH | E2: =LEN(B2) -> 12 | F2: =E2-3 -> 9 | G2: =MID(B2,1,F2) -> DUC002923 | H2: =MID(B2,F2+1,5) -> 46B | I2: =CONCATENATE(G2," ",H2) -> DUC002923 46B | K2: 3850
A3: 6400 | B3: DUC00292417B | C3: IT0OEKR | D3: MOTOR M20B ARG'24 - DMH | E3: =LEN(B3) -> 12 | F3: =E3-3 -> 9 | G3: =MID(B3,1,F3) -> DUC002924 | H3: =MID(B3,F3+1,5) -> 17B | I3: =CONCATENATE(G3," ",H3) -> DUC002924 17B | K3: 2983.37
A4: 6400 | B4: DUC0029Z161D | C4: IT0OEKR | D4: MOTOR 1603-800 EUR'22 /DPT E5. | E4: =LEN(B4) -> 12 | F4: =E4-3 -> 9 | G4: =MID(B4,1,F4) -> DUC0029Z1 | H4: =MID(B4,F4+1,5) -> 61D | I4: =CONCATENATE(G4," ",H4) -> DUC0029Z1 61D | K4: 2682.06
A5: 6400 | B5: DUC069191030 | C5: IT0OEKR | D5: Clamp Ducati | E5: =LEN(B5) -> 12 | F5: =E5-3 -> 9 | G5: =MID(B5,1,F5) -> DUC069191 | H5: =MID(B5,F5+1,5) -> 030 | I5: =CONCATENATE(G5," ",H5) -> DUC069191 030 | K5: 0.21000006
A6: 6400 | B6: DUC11723553AA | C6: IT0OEKR | D6: VARILLA CONTROL | E6: =LEN(B6) -> 13 | F6: =E6-3 -> 10 | G6: =MID(B6,1,F6) -> DUC1172355 | H6: =MID(B6,F6+1,5) -> 3AA | I6: =CONCATENATE(G6," ",H6) -> DUC1172355 3AA | K6: 1.64
A7: 6400 | B7: DUC117G3891AA | C7: IT0OEKR | D7: ASTA COMANDO CAMBIO V20B | E7: =LEN(B7) -> 13 | F7: =E7-3 -> 10 | G7: =MID(B7,1,F7) -> DUC117G389 | H7: =MID(B7,F7+1,5) -> 1AA | I7: =CONCATENATE(G7," ",H7) -> DUC117G389 1AA | K7: 12.8
A8: 6400 | B8: DUC19510411D | C8: IT0OEKR | D8: DISTANCIADOR | E8: =LEN(B8) -> 12 | F8: =E8-3 -> 9 | G8: =MID(B8,1,F8) -> DUC195104 | H8: =MID(B8,F8+1,5) -> 11D | I8: =CONCATENATE(G8," ",H8) -> DUC195104 11D | K8: 3.5100001
A9: 6400 | B9: DUC24714911A | C9: IT0OEKR | D9: PANEL DE CONTROL | E9: =LEN(B9) -> 12 | F9: =E9-3 -> 9 | G9: =MID(B9,1,F9) -> DUC247149 | H9: =MID(B9,F9+1,5) -> 11A | I9: =CONCATENATE(G9," ",H9) -> DUC247149 11A | K9: 1.18
A10: 6400 | B10: DUC24714951A | C10: IT0OEKR | D10: TAPA DEL CABLEADO 1106 | E10: =LEN(B10) -> 12 | F10: =E10-3 -> 9 | G10: =MID(B10,1,F10) -> DUC247149 | H10: =MID(B10,F10+1,5) -> 51A | I10: =CONCATENATE(G10," ",H10) -> DUC247149 51A | K10: 0.48
A11: 6400 | B11: DUC247G4933A | C11: IT0OEKR | D11: STGR TAPA DE LA CAJA DE AIRE 1504 | E11: =LEN(B11) -> 12 | F11: =E11-3 -> 9 | G11: =MID(B11,1,F11) -> DUC247G49 | H11: =MID(B11,F11+1,5) -> 33A | I11: =CONCATENATE(G11," ",H11) -> DUC247G49 33A | K11: 5.6900001
A12: 6400 | B12: DUC247G7521A | C12: IT0OEKR | D12: TAPA DEL FILTRO DE AIRE | E12: =LEN(B12) -> 12 | F12: =E12-3 -> 9 | G12: =MID(B12,1,F12) -> DUC247G75 | H12: =MID(B12,F12+1,5) -> 21A | I12: =CONCATENATE(G12," ",H12) -> DUC247G75 21A | K12: 14.45
A13: 6400 | B13: DUC247P4933A | C13: IT0OEKR | D13: STGR TAPA DE LA CAJA DE AIRE 1504 | E13: =LEN(B13) -> 12 | F13: =E13-3 -> 9 | G13: =MID(B13,1,F13) -> DUC247P49 | H13: =MID(B13,F13+1,5) -> 33A | I13: =CONCATENATE(G13," ",H13) -> DUC247P49 33A | K13: 5.28
... A802: 6400 | B802: DUCAM200EMB01 | C802: IT0OEKR | D802: EMBALAJE PRODUCTO FINAL | E802: =LEN(B802) -> 13 | F802: =E802-3 -> 10 | G802: =MID(B802,1,F802) -> DUCAM200EM | H802: =MID(B802,F802+1,5) -> B01 | I802: =CONCATENATE(G802," ",H802) -> DUCAM200EM B01 | K802: 185.4

Sheet Pendientes
A1: Deposito | B1: Ubicación | C1: Observaciones | D1: Estado

Sheet Clasif de ub
A1: calle, modulo y nivel | B1: Tipo de ub
A2: 51A4 | B2: Altura
A3: 51A5 | B3: Altura
A4: 51A6 | B4: Altura
A5: 51A7 | B5: Altura
A6: 51A8 | B6: Altura
A7: 51B4 | B7: Altura
A8: 51B5 | B8: Altura
A9: 51B6 | B9: Altura
A10: 51B7 | B10: Altura
A11: 51B8 | B11: Altura
A12: 51C4 | B12: Altura
... A2651: 570 | B2651: Piso
